Workbook

Sheet BIData
A2: =IFERROR(IF(0=LEN(ReferenceData!$A$2),"",ReferenceData!$A$2),"") -> Description | B2: =IFERROR(IF(0=LEN(ReferenceData!$B$2),"",ReferenceData!$B$2),"") -> Ticker | C2: =IFERROR(IF(0=LEN(ReferenceData!$C$2),"",ReferenceData!$C$2),"") -> Field ID | D2: =IFERROR(IF(0=LEN(ReferenceData!$D$2),"",ReferenceData!$D$2),"") -> Field Mnemonic | E2: =IFERROR(IF(0=LEN(ReferenceData!$E$2),"",ReferenceData!$E$2),"") -> Data State | F2: =IFERROR(IF(0=LEN(ReferenceData!$AG$2),"",ReferenceData!$AG$2),"") -> 2012 S1 | G2: =IFERROR(IF(0=LEN(ReferenceData!$AF$2),"",ReferenceData!$AF$2),"") -> 2012 S2 | H2: =IFERROR(IF(0=LEN(ReferenceData!$AE$2),"",ReferenceData!$AE$2),"") -> 2013 S1 | I2: =IFERROR(IF(0=LEN(ReferenceData!$AD$2),"",ReferenceData!$AD$2),"") -> 2013 S2 | J2: =IFERROR(IF(0=LEN(ReferenceData!$AC$2),"",ReferenceData!$AC$2),"") -> 2014 S1 | K2: =IFERROR(IF(0=LEN(ReferenceData!$AB$2),"",ReferenceData!$AB$2),"") -> 2014 S2 | L2: =IFERROR(IF(0=LEN(ReferenceData!$AA$2),"",ReferenceData!$AA$2),"") -> 2015 S1 | M2: =IFERROR(IF(0=LEN(ReferenceData!$Z$2),"",ReferenceData!$Z$2),"") -> 2015 S2 | N2: =IFERROR(IF(0=LEN(ReferenceData!$Y$2),"",ReferenceData!$Y$2),"") -> 2016 S1 | O2: =IFERROR(IF(0=LEN(ReferenceData!$X$2),"",ReferenceData!$X$2),"") -> 2016 S2 | P2: =IFERROR(IF(0=LEN(ReferenceData!$W$2),"",ReferenceData!$W$2),"") -> 2017 S1 | Q2: =IFERROR(IF(0=LEN(ReferenceData!$V$2),"",ReferenceData!$V$2),"") -> 2017 S2 | R2: =IFERROR(IF(0=LEN(ReferenceData!$U$2),"",ReferenceData!$U$2),"") -> 2018 S1 | S2: =IFERROR(IF(0=LEN(ReferenceData!$T$2),"",ReferenceData!$T$2),"") -> 2018 S2 | T2: =IFERROR(IF(0=LEN(ReferenceData!$S$2),"",ReferenceData!$S$2),"") -> 2019 S1 | U2: =IFERROR(IF(0=LEN(ReferenceData!$R$2),"",ReferenceData!$R$2),"") -> 2019 S2 | V2: =IFERROR(IF(0=LEN(ReferenceData!$Q$2),"",ReferenceData!$Q$2),"") -> 2020 S1 | W2: =IFERROR(IF(0=LEN(ReferenceData!$P$2),"",ReferenceData!$P$2),"") -> 2020 S2 | X2: =IFERROR(IF(0=LEN(ReferenceData!$O$2),"",ReferenceData!$O$2),"") -> 2021 S1 | Y2: =IFERROR(IF(0=LEN(ReferenceData!$N$2),"",ReferenceData!$N$2),"") -> 2021 S2 | Z2: =IFERROR(IF(0=LEN(ReferenceData!$M$2),"",ReferenceData!$M$2),"") -> 2022 S1 | AA2: =IFERROR(IF(0=LEN(ReferenceData!$L$2),"",ReferenceData!$L$2),"") -> 2022 S2 | AB2: =IFERROR(IF(0=LEN(ReferenceData!$K$2),"",ReferenceData!$K$2),"") -> 2023 S1 | AC2: =IFERROR(IF(0=LEN(ReferenceData!$J$2),"",ReferenceData!$J$2),"") -> 2023 S2 | AD2: =IFERROR(IF(0=LEN(ReferenceData!$I$2),"",ReferenceData!$I$2),"") -> 2024 S1 | AE2: =IFERROR(IF(0=LEN(ReferenceData!$H$2),"",ReferenceData!$H$2),"") -> 2024 S2 | AF2: =IFERROR(IF(0=LEN(ReferenceData!$G$2),"",ReferenceData!$G$2),"") -> 2025 S1 | AG2: =IFERROR(IF(0=LEN(ReferenceData!$F$2),"",ReferenceData!$F$2),"") -> 2025 S2
A3: =IFERROR(IF(0=LEN(ReferenceData!$A$3),"",ReferenceData!$A$3),"") -> ETFs as % Of Total Fund Assets (MF & ETF) | B3: =IFERROR(IF(0=LEN(ReferenceData!$B$3),"",ReferenceData!$B$3),"") | C3: =IFERROR(IF(0=LEN(ReferenceData!$C$3),"",ReferenceData!$C$3),"") | D3: =IFERROR(IF(0=LEN(ReferenceData!$D$3),"",ReferenceData!$D$3),"") | E3: =IFERROR(IF(0=LEN(ReferenceData!$E$3),"",ReferenceData!$E$3),"") -> Expression | F3: =IFERROR(IF(0=LEN(ReferenceData!$AG$3),"",ReferenceData!$AG$3),"") -> 13.217836 | G3: =IFERROR(IF(0=LEN(ReferenceData!$AF$3),"",ReferenceData!$AF$3),"") -> 13.609661 | H3: =IFERROR(IF(0=LEN(ReferenceData!$AE$3),"",ReferenceData!$AE$3),"") -> 13.716417 | I3: =IFERROR(IF(0=LEN(ReferenceData!$AD$3),"",ReferenceData!$AD$3),"") -> 14.260533 | J3: =IFERROR(IF(0=LEN(ReferenceData!$AC$3),"",ReferenceData!$AC$3),"") -> 14.370747 | K3: =IFERROR(IF(0=LEN(ReferenceData!$AB$3),"",ReferenceData!$AB$3),"") -> 15.224923 | L3: =IFERROR(IF(0=LEN(ReferenceData!$AA$3),"",ReferenceData!$AA$3),"") -> 15.785424 | M3: =IFERROR(IF(0=LEN(ReferenceData!$Z$3),"",ReferenceData!$Z$3),"") -> 16.102875 | N3: =IFERROR(IF(0=LEN(ReferenceData!$Y$3),"",ReferenceData!$Y$3),"") -> 16.673301 | O3: =IFERROR(IF(0=LEN(ReferenceData!$X$3),"",ReferenceData!$X$3),"") -> 18.051022 | P3: =IFERROR(IF(0=LEN(ReferenceData!$W$3),"",ReferenceData!$W$3),"") -> 18.871804 | Q3: =IFERROR(IF(0=LEN(ReferenceData!$V$3),"",ReferenceData!$V$3),"") -> 20.09652 | R3: =IFERROR(IF(0=LEN(ReferenceData!$U$3),"",ReferenceData!$U$3),"") -> 20.237705 | S3: =IFERROR(IF(0=LEN(ReferenceData!$T$3),"",ReferenceData!$T$3),"") -> 21.149005 | T3: =IFERROR(IF(0=LEN(ReferenceData!$S$3),"",ReferenceData!$S$3),"") -> 21.635465 | U3: =IFERROR(IF(0=LEN(ReferenceData!$R$3),"",ReferenceData!$R$3),"") -> 22.093074 | V3: =IFERROR(IF(0=LEN(ReferenceData!$Q$3),"",ReferenceData!$Q$3),"") -> 22.528549 | W3: =IFERROR(IF(0=LEN(ReferenceData!$P$3),"",ReferenceData!$P$3),"") -> 23.858694 | X3: =IFERROR(IF(0=LEN(ReferenceData!$O$3),"",ReferenceData!$O$3),"") -> 25.120084 | Y3: =IFERROR(IF(0=LEN(ReferenceData!$N$3),"",ReferenceData!$N$3),"") -> 26.221668 | Z3: =IFERROR(IF(0=LEN(ReferenceData!$M$3),"",ReferenceData!$M$3),"") -> 27.625432 | AA3: =IFERROR(IF(0=LEN(ReferenceData!$L$3),"",ReferenceData!$L$3),"") -> 29.068671 | AB3: =IFERROR(IF(0=LEN(ReferenceData!$K$3),"",ReferenceData!$K$3),"") -> 29.827034 | AC3: =IFERROR(IF(0=LEN(ReferenceData!$J$3),"",ReferenceData!$J$3),"") -> 31.031894 | AD3: =IFERROR(IF(0=LEN(ReferenceData!$I$3),"",ReferenceData!$I$3),"") -> 32.208543 | AE3: =IFERROR(IF(0=LEN(ReferenceData!$H$3),"",ReferenceData!$H$3),"") -> 34.105675 | AF3: =IFERROR(IF(0=LEN(ReferenceData!$G$3),"",ReferenceData!$G$3),"") -> 35.358068 | AG3: =IFERROR(IF(0=LEN(ReferenceData!$F$3),"",ReferenceData!$F$3),"") -> 37.078442
A4: =IFERROR(IF(0=LEN(ReferenceData!$A$4),"",ReferenceData!$A$4),"") -> ETFs as % Of Equity Fund Assets (MF & ETF) | B4: =IFERROR(IF(0=LEN(ReferenceData!$B$4),"",ReferenceData!$B$4),"") | C4: =IFERROR(IF(0=LEN(ReferenceData!$C$4),"",ReferenceData!$C$4),"") | D4: =IFERROR(IF(0=LEN(ReferenceData!$D$4),"",ReferenceData!$D$4),"") | E4: =IFERROR(IF(0=LEN(ReferenceData!$E$4),"",ReferenceData!$E$4),"") -> Expression | F4: =IFERROR(IF(0=LEN(ReferenceData!$AG$4),"",ReferenceData!$AG$4),"") -> 16.258832 | G4: =IFERROR(IF(0=LEN(ReferenceData!$AF$4),"",ReferenceData!$AF$4),"") -> 16.974729 | H4: =IFERROR(IF(0=LEN(ReferenceData!$AE$4),"",ReferenceData!$AE$4),"") -> 17.331619 | I4: =IFERROR(IF(0=LEN(ReferenceData!$AD$4),"",ReferenceData!$AD$4),"") -> 17.835893 | J4: =IFERROR(IF(0=LEN(ReferenceData!$AC$4),"",ReferenceData!$AC$4),"") -> 17.945907 | K4: =IFERROR(IF(0=LEN(ReferenceData!$AB$4),"",ReferenceData!$AB$4),"") -> 18.957734 | L4: =IFERROR(IF(0=LEN(ReferenceData!$AA$4),"",ReferenceData!$AA$4),"") -> 19.550153 | M4: =IFERROR(IF(0=LEN(ReferenceData!$Z$4),"",ReferenceData!$Z$4),"") -> 19.886805 | N4: =IFERROR(IF(0=LEN(ReferenceData!$Y$4),"",ReferenceData!$Y$4),"") -> 20.249502 | O4: =IFERROR(IF(0=LEN(ReferenceData!$X$4),"",ReferenceData!$X$4),"") -> 22.073154 | P4: =IFERROR(IF(0=LEN(ReferenceData!$W$4),"",ReferenceData!$W$4),"") -> 22.733653 | Q4: =IFERROR(IF(0=LEN(ReferenceData!$V$4),"",ReferenceData!$V$4),"") -> 24.075207 | R4: =IFERROR(IF(0=LEN(ReferenceData!$U$4),"",ReferenceData!$U$4),"") -> 24.1134 | S4: =IFERROR(IF(0=LEN(ReferenceData!$T$4),"",ReferenceData!$T$4),"") -> 25.357024 | T4: =IFERROR(IF(0=LEN(ReferenceData!$S$4),"",ReferenceData!$S$4),"") -> 25.510193 | U4: =IFERROR(IF(0=LEN(ReferenceData!$R$4),"",ReferenceData!$R$4),"") -> 25.914774 | V4: =IFERROR(IF(0=LEN(ReferenceData!$Q$4),"",ReferenceData!$Q$4),"") -> 25.835629 | W4: =IFERROR(IF(0=LEN(ReferenceData!$P$4),"",ReferenceData!$P$4),"") -> 27.335587 | X4: =IFERROR(IF(0=LEN(ReferenceData!$O$4),"",ReferenceData!$O$4),"") -> 28.927924 | Y4: =IFERROR(IF(0=LEN(ReferenceData!$N$4),"",ReferenceData!$N$4),"") -> 30.197149 | Z4: =IFERROR(IF(0=LEN(ReferenceData!$M$4),"",ReferenceData!$M$4),"") -> 31.845603 | AA4: =IFERROR(IF(0=LEN(ReferenceData!$L$4),"",ReferenceData!$L$4),"") -> 32.998992 | AB4: =IFERROR(IF(0=LEN(ReferenceData!$K$4),"",ReferenceData!$K$4),"") -> 33.307887 | AC4: =IFERROR(IF(0=LEN(ReferenceData!$J$4),"",ReferenceData!$J$4),"") -> 34.533582 | AD4: =IFERROR(IF(0=LEN(ReferenceData!$I$4),"",ReferenceData!$I$4),"") -> 35.565675 | AE4: =IFERROR(IF(0=LEN(ReferenceData!$H$4),"",ReferenceData!$H$4),"") -> 37.546944 | AF4: =IFERROR(IF(0=LEN(ReferenceData!$G$4),"",ReferenceData!$G$4),"") -> 38.517793 | AG4: =IFERROR(IF(0=LEN(ReferenceData!$F$4),"",ReferenceData!$F$4),"") -> 40.405625
A5: =IFERROR(IF(0=LEN(ReferenceData!$A$5),"",ReferenceData!$A$5),"") -> ETFs as % Of Bond Fund Assets (MF & ETF) | B5: =IFERROR(IF(0=LEN(ReferenceData!$B$5),"",ReferenceData!$B$5),"") | C5: =IFERROR(IF(0=LEN(ReferenceData!$C$5),"",ReferenceData!$C$5),"") | D5: =IFERROR(IF(0=LEN(ReferenceData!$D$5),"",ReferenceData!$D$5),"") | E5: =IFERROR(IF(0=LEN(ReferenceData!$E$5),"",ReferenceData!$E$5),"") -> Expression | F5: =IFERROR(IF(0=LEN(ReferenceData!$AG$5),"",ReferenceData!$AG$5),"") -> 8.1925826 | G5: =IFERROR(IF(0=LEN(ReferenceData!$AF$5),"",ReferenceData!$AF$5),"") -> 7.923056 | H5: =IFERROR(IF(0=LEN(ReferenceData!$AE$5),"",ReferenceData!$AE$5),"") -> 8.2138024 | I5: =IFERROR(IF(0=LEN(ReferenceData!$AD$5),"",ReferenceData!$AD$5),"") -> 8.2122219 | J5: =IFERROR(IF(0=LEN(ReferenceData!$AC$5),"",ReferenceData!$AC$5),"") -> 8.4660436 | K5: =IFERROR(IF(0=LEN(ReferenceData!$AB$5),"",ReferenceData!$AB$5),"") -> 9.2535089 | L5: =IFERROR(IF(0=LEN(ReferenceData!$AA$5),"",ReferenceData!$AA$5),"") -> 9.6919105 | M5: =IFERROR(IF(0=LEN(ReferenceData!$Z$5),"",ReferenceData!$Z$5),"") -> 10.622748 | N5: =IFERROR(IF(0=LEN(ReferenceData!$Y$5),"",ReferenceData!$Y$5),"") -> 11.58322 | O5: =IFERROR(IF(0=LEN(ReferenceData!$X$5),"",ReferenceData!$X$5),"") -> 12.216942 | P5: =IFERROR(IF(0=LEN(ReferenceData!$W$5),"",ReferenceData!$W$5),"") -> 13.180263 | Q5: =IFERROR(IF(0=LEN(ReferenceData!$V$5),"",ReferenceData!$V$5),"") -> 13.824428 | R5: =IFERROR(IF(0=LEN(ReferenceData!$U$5),"",ReferenceData!$U$5),"") -> 14.188845 | S5: =IFERROR(IF(0=LEN(ReferenceData!$T$5),"",ReferenceData!$T$5),"") -> 15.259093 | T5: =IFERROR(IF(0=LEN(ReferenceData!$S$5),"",ReferenceData!$S$5),"") -> 16.049755 | U5: =IFERROR(IF(0=LEN(ReferenceData!$R$5),"",ReferenceData!$R$5),"") -> 16.415011 | V5: =IFERROR(IF(0=LEN(ReferenceData!$Q$5),"",ReferenceData!$Q$5),"") -> 17.96908 | W5: =IFERROR(IF(0=LEN(ReferenceData!$P$5),"",ReferenceData!$P$5),"") -> 18.192209 | X5: =IFERROR(IF(0=LEN(ReferenceData!$O$5),"",ReferenceData!$O$5),"") -> 18.516782 | Y5: =IFERROR(IF(0=LEN(ReferenceData!$N$5),"",ReferenceData!$N$5),"") -> 19.089849 | Z5: =IFERROR(IF(0=LEN(ReferenceData!$M$5),"",ReferenceData!$M$5),"") -> 20.9858 | AA5: =IFERROR(IF(0=LEN(ReferenceData!$L$5),"",ReferenceData!$L$5),"") -> 23.275326 | AB5: =IFERROR(IF(0=LEN(ReferenceData!$K$5),"",ReferenceData!$K$5),"") -> 24.507879 | AC5: =IFERROR(IF(0=LEN(ReferenceData!$J$5),"",ReferenceData!$J$5),"") -> 25.469519 | AD5: =IFERROR(IF(0=LEN(ReferenceData!$I$5),"",ReferenceData!$I$5),"") -> 26.128748 | AE5: =IFERROR(IF(0=LEN(ReferenceData!$H$5),"",ReferenceData!$H$5),"") -> 27.24881 | AF5: =IFERROR(IF(0=LEN(ReferenceData!$G$5),"",ReferenceData!$G$5),"") -> 28.762254 | AG5: =IFERROR(IF(0=LEN(ReferenceData!$F$5),"",ReferenceData!$F$5),"") -> 29.70135
A6: =IFERROR(IF(0=LEN(ReferenceData!$A$6),"",ReferenceData!$A$6),"") -> ETFs & Mutual Funds Passive % | B6: =IFERROR(IF(0=LEN(ReferenceData!$B$6),"",ReferenceData!$B$6),"") | C6: =IFERROR(IF(0=LEN(ReferenceData!$C$6),"",ReferenceData!$C$6),"") | D6: =IFERROR(IF(0=LEN(ReferenceData!$D$6),"",ReferenceData!$D$6),"") | E6: =IFERROR(IF(0=LEN(ReferenceData!$E$6),"",ReferenceData!$E$6),"") -> Heading | F6: =IFERROR(IF(0=LEN(ReferenceData!$AG$6),"",ReferenceData!$AG$6),"") | G6: =IFERROR(IF(0=LEN(ReferenceData!$AF$6),"",ReferenceData!$AF$6),"") | H6: =IFERROR(IF(0=LEN(ReferenceData!$AE$6),"",ReferenceData!$AE$6),"") | I6: =IFERROR(IF(0=LEN(ReferenceData!$AD$6),"",ReferenceData!$AD$6),"") | J6: =IFERROR(IF(0=LEN(ReferenceData!$AC$6),"",ReferenceData!$AC$6),"") | K6: =IFERROR(IF(0=LEN(ReferenceData!$AB$6),"",ReferenceData!$AB$6),"") | L6: =IFERROR(IF(0=LEN(ReferenceData!$AA$6),"",ReferenceData!$AA$6),"") | M6: =IFERROR(IF(0=LEN(ReferenceData!$Z$6),"",ReferenceData!$Z$6),"") | N6: =IFERROR(IF(0=LEN(ReferenceData!$Y$6),"",ReferenceData!$Y$6),"") | O6: =IFERROR(IF(0=LEN(ReferenceData!$X$6),"",ReferenceData!$X$6),"") | P6: =IFERROR(IF(0=LEN(ReferenceData!$W$6),"",ReferenceData!$W$6),"") | Q6: =IFERROR(IF(0=LEN(ReferenceData!$V$6),"",ReferenceData!$V$6),"") | R6: =IFERROR(IF(0=LEN(ReferenceData!$U$6),"",ReferenceData!$U$6),"") | S6: =IFERROR(IF(0=LEN(ReferenceData!$T$6),"",ReferenceData!$T$6),"") | T6: =IFERROR(IF(0=LEN(ReferenceData!$S$6),"",ReferenceData!$S$6),"") | U6: =IFERROR(IF(0=LEN(ReferenceData!$R$6),"",ReferenceData!$R$6),"") | V6: =IFERROR(IF(0=LEN(ReferenceData!$Q$6),"",ReferenceData!$Q$6),"") | W6: =IFERROR(IF(0=LEN(ReferenceData!$P$6),"",ReferenceData!$P$6),"") | X6: =IFERROR(IF(0=LEN(ReferenceData!$O$6),"",ReferenceData!$O$6),"") | Y6: =IFERROR(IF(0=LEN(ReferenceData!$N$6),"",ReferenceData!$N$6),"") | Z6: =IFERROR(IF(0=LEN(ReferenceData!$M$6),"",ReferenceData!$M$6),"") | AA6: =IFERROR(IF(0=LEN(ReferenceData!$L$6),"",ReferenceData!$L$6),"") | AB6: =IFERROR(IF(0=LEN(ReferenceData!$K$6),"",ReferenceData!$K$6),"") | AC6: =IFERROR(IF(0=LEN(ReferenceData!$J$6),"",ReferenceData!$J$6),"") | AD6: =IFERROR(IF(0=LEN(ReferenceData!$I$6),"",ReferenceData!$I$6),"") | AE6: =IFERROR(IF(0=LEN(ReferenceData!$H$6),"",ReferenceData!$H$6),"") | AF6: =IFERROR(IF(0=LEN(ReferenceData!$G$6),"",ReferenceData!$G$6),"") | AG6: =IFERROR(IF(0=LEN(ReferenceData!$F$6),"",ReferenceData!$F$6),"")
A7: =IFERROR(IF(0=LEN(ReferenceData!$A$7),"",ReferenceData!$A$7),"") -> Passive % Of All ETFs & Mutual Funds | B7: =IFERROR(IF(0=LEN(ReferenceData!$B$7),"",ReferenceData!$B$7),"") | C7: =IFERROR(IF(0=LEN(ReferenceData!$C$7),"",ReferenceData!$C$7),"") | D7: =IFERROR(IF(0=LEN(ReferenceData!$D$7),"",ReferenceData!$D$7),"") | E7: =IFERROR(IF(0=LEN(ReferenceData!$E$7),"",ReferenceData!$E$7),"") -> Expression | F7: =IFERROR(IF(0=LEN(ReferenceData!$AG$7),"",ReferenceData!$AG$7),"") -> 25.019725 | G7: =IFERROR(IF(0=LEN(ReferenceData!$AF$7),"",ReferenceData!$AF$7),"") -> 25.482054 | H7: =IFERROR(IF(0=LEN(ReferenceData!$AE$7),"",ReferenceData!$AE$7),"") -> 26.094993 | I7: =IFERROR(IF(0=LEN(ReferenceData!$AD$7),"",ReferenceData!$AD$7),"") -> 27.224338 | J7: =IFERROR(IF(0=LEN(ReferenceData!$AC$7),"",ReferenceData!$AC$7),"") -> 27.712089 | K7: =IFERROR(IF(0=LEN(ReferenceData!$AB$7),"",ReferenceData!$AB$7),"") -> 29.426864 | L7: =IFERROR(IF(0=LEN(ReferenceData!$AA$7),"",ReferenceData!$AA$7),"") -> 30.417419 | M7: =IFERROR(IF(0=LEN(ReferenceData!$Z$7),"",ReferenceData!$Z$7),"") -> 31.409682 | N7: =IFERROR(IF(0=LEN(ReferenceData!$Y$7),"",ReferenceData!$Y$7),"") -> 32.505148 | O7: =IFERROR(IF(0=LEN(ReferenceData!$X$7),"",ReferenceData!$X$7),"") -> 34.352407 | P7: =IFERROR(IF(0=LEN(ReferenceData!$W$7),"",ReferenceData!$W$7),"") -> 36.026475 | Q7: =IFERROR(IF(0=LEN(ReferenceData!$V$7),"",ReferenceData!$V$7),"") -> 37.751042 | R7: =IFERROR(IF(0=LEN(ReferenceData!$U$7),"",ReferenceData!$U$7),"") -> 38.2237 | S7: =IFERROR(IF(0=LEN(ReferenceData!$T$7),"",ReferenceData!$T$7),"") -> 39.842111 | T7: =IFERROR(IF(0=LEN(ReferenceData!$S$7),"",ReferenceData!$S$7),"") -> 41.186121 | U7: =IFERROR(IF(0=LEN(ReferenceData!$R$7),"",ReferenceData!$R$7),"") -> 41.605093 | V7: =IFERROR(IF(0=LEN(ReferenceData!$Q$7),"",ReferenceData!$Q$7),"") -> 41.780188 | W7: =IFERROR(IF(0=LEN(ReferenceData!$P$7),"",ReferenceData!$P$7),"") -> 42.791783 | X7: =IFERROR(IF(0=LEN(ReferenceData!$O$7),"",ReferenceData!$O$7),"") -> 43.878492 | Y7: =IFERROR(IF(0=LEN(ReferenceData!$N$7),"",ReferenceData!$N$7),"") -> 45.328458 | Z7: =IFERROR(IF(0=LEN(ReferenceData!$M$7),"",ReferenceData!$M$7),"") -> 46.40419 | AA7: =IFERROR(IF(0=LEN(ReferenceData!$L$7),"",ReferenceData!$L$7),"") -> 47.964704 | AB7: =IFERROR(IF(0=LEN(ReferenceData!$K$7),"",ReferenceData!$K$7),"") -> 48.953407 | AC7: =IFERROR(IF(0=LEN(ReferenceData!$J$7),"",ReferenceData!$J$7),"") -> 50.136733 | AD7: =IFERROR(IF(0=LEN(ReferenceData!$I$7),"",ReferenceData!$I$7),"") -> 51.126709 | AE7: =IFERROR(IF(0=LEN(ReferenceData!$H$7),"",ReferenceData!$H$7),"") -> 52.638601 | AF7: =IFERROR(IF(0=LEN(ReferenceData!$G$7),"",ReferenceData!$G$7),"") -> 53.441266 | AG7: =IFERROR(IF(0=LEN(ReferenceData!$F$7),"",ReferenceData!$F$7),"") -> 54.081124
A8: =IFERROR(IF(0=LEN(ReferenceData!$A$8),"",ReferenceData!$A$8),"") -> Passive % Of All Fixed Income Funds | B8: =IFERROR(IF(0=LEN(ReferenceData!$B$8),"",ReferenceData!$B$8),"") | C8: =IFERROR(IF(0=LEN(ReferenceData!$C$8),"",ReferenceData!$C$8),"") | D8: =IFERROR(IF(0=LEN(ReferenceData!$D$8),"",ReferenceData!$D$8),"") | E8: =IFERROR(IF(0=LEN(ReferenceData!$E$8),"",ReferenceData!$E$8),"") -> Expression | F8: =IFERROR(IF(0=LEN(ReferenceData!$AG$8),"",ReferenceData!$AG$8),"") -> 15.79825 | G8: =IFERROR(IF(0=LEN(ReferenceData!$AF$8),"",ReferenceData!$AF$8),"") -> 15.511313 | H8: =IFERROR(IF(0=LEN(ReferenceData!$AE$8),"",ReferenceData!$AE$8),"") -> 15.865767 | I8: =IFERROR(IF(0=LEN(ReferenceData!$AD$8),"",ReferenceData!$AD$8),"") -> 16.241755 | J8: =IFERROR(IF(0=LEN(ReferenceData!$AC$8),"",ReferenceData!$AC$8),"") -> 16.767667 | K8: =IFERROR(IF(0=LEN(ReferenceData!$AB$8),"",ReferenceData!$AB$8),"") -> 18.517265 | L8: =IFERROR(IF(0=LEN(ReferenceData!$AA$8),"",ReferenceData!$AA$8),"") -> 19.511031 | M8: =IFERROR(IF(0=LEN(ReferenceData!$Z$8),"",ReferenceData!$Z$8),"") -> 20.954989 | N8: =IFERROR(IF(0=LEN(ReferenceData!$Y$8),"",ReferenceData!$Y$8),"") -> 22.318445 | O8: =IFERROR(IF(0=LEN(ReferenceData!$X$8),"",ReferenceData!$X$8),"") -> 23.272017 | P8: =IFERROR(IF(0=LEN(ReferenceData!$W$8),"",ReferenceData!$W$8),"") -> 24.783601 | Q8: =IFERROR(IF(0=LEN(ReferenceData!$V$8),"",ReferenceData!$V$8),"") -> 26.11505 | R8: =IFERROR(IF(0=LEN(ReferenceData!$U$8),"",ReferenceData!$U$8),"") -> 26.764075 | S8: =IFERROR(IF(0=LEN(ReferenceData!$T$8),"",ReferenceData!$T$8),"") -> 28.077709 | T8: =IFERROR(IF(0=LEN(ReferenceData!$S$8),"",ReferenceData!$S$8),"") -> 29.469729 | U8: =IFERROR(IF(0=LEN(ReferenceData!$R$8),"",ReferenceData!$R$8),"") -> 29.576187 | V8: =IFERROR(IF(0=LEN(ReferenceData!$Q$8),"",ReferenceData!$Q$8),"") -> 31.117414 | W8: =IFERROR(IF(0=LEN(ReferenceData!$P$8),"",ReferenceData!$P$8),"") -> 31.159512 | X8: =IFERROR(IF(0=LEN(ReferenceData!$O$8),"",ReferenceData!$O$8),"") -> 31.377922 | Y8: =IFERROR(IF(0=LEN(ReferenceData!$N$8),"",ReferenceData!$N$8),"") -> 31.896073 | Z8: =IFERROR(IF(0=LEN(ReferenceData!$M$8),"",ReferenceData!$M$8),"") -> 34.004146 | AA8: =IFERROR(IF(0=LEN(ReferenceData!$L$8),"",ReferenceData!$L$8),"") -> 36.325285 | AB8: =IFERROR(IF(0=LEN(ReferenceData!$K$8),"",ReferenceData!$K$8),"") -> 36.457365 | AC8: =IFERROR(IF(0=LEN(ReferenceData!$J$8),"",ReferenceData!$J$8),"") -> 37.408446 | AD8: =IFERROR(IF(0=LEN(ReferenceData!$I$8),"",ReferenceData!$I$8),"") -> 37.440026 | AE8: =IFERROR(IF(0=LEN(ReferenceData!$H$8),"",ReferenceData!$H$8),"") -> 37.551428 | AF8: =IFERROR(IF(0=LEN(ReferenceData!$G$8),"",ReferenceData!$G$8),"") -> 38.189375 | AG8: =IFERROR(IF(0=LEN(ReferenceData!$F$8),"",ReferenceData!$F$8),"") -> 38.508901
A9: =IFERROR(IF(0=LEN(ReferenceData!$A$9),"",ReferenceData!$A$9),"") -> Passive % Of All Equity Funds | B9: =IFERROR(IF(0=LEN(ReferenceData!$B$9),"",ReferenceData!$B$9),"") | C9: =IFERROR(IF(0=LEN(ReferenceData!$C$9),"",ReferenceData!$C$9),"") | D9: =IFERROR(IF(0=LEN(ReferenceData!$D$9),"",ReferenceData!$D$9),"") | E9: =IFERROR(IF(0=LEN(ReferenceData!$E$9),"",ReferenceData!$E$9),"") -> Expression | F9: =IFERROR(IF(0=LEN(ReferenceData!$AG$9),"",ReferenceData!$AG$9),"") -> 32.260807 | G9: =IFERROR(IF(0=LEN(ReferenceData!$AF$9),"",ReferenceData!$AF$9),"") -> 33.024504 | H9: =IFERROR(IF(0=LEN(ReferenceData!$AE$9),"",ReferenceData!$AE$9),"") -> 33.706485 | I9: =IFERROR(IF(0=LEN(ReferenceData!$AD$9),"",ReferenceData!$AD$9),"") -> 34.371796 | J9: =IFERROR(IF(0=LEN(ReferenceData!$AC$9),"",ReferenceData!$AC$9),"") -> 34.973911 | K9: =IFERROR(IF(0=LEN(ReferenceData!$AB$9),"",ReferenceData!$AB$9),"") -> 36.808456 | L9: =IFERROR(IF(0=LEN(ReferenceData!$AA$9),"",ReferenceData!$AA$9),"") -> 37.733408 | M9: =IFERROR(IF(0=LEN(ReferenceData!$Z$9),"",ReferenceData!$Z$9),"") -> 39.017128 | N9: =IFERROR(IF(0=LEN(ReferenceData!$Y$9),"",ReferenceData!$Y$9),"") -> 40.179994 | O9: =IFERROR(IF(0=LEN(ReferenceData!$X$9),"",ReferenceData!$X$9),"") -> 42.348753 | P9: =IFERROR(IF(0=LEN(ReferenceData!$W$9),"",ReferenceData!$W$9),"") -> 43.8448 | Q9: =IFERROR(IF(0=LEN(ReferenceData!$V$9),"",ReferenceData!$V$9),"") -> 45.449154 | R9: =IFERROR(IF(0=LEN(ReferenceData!$U$9),"",ReferenceData!$U$9),"") -> 45.835681 | S9: =IFERROR(IF(0=LEN(ReferenceData!$T$9),"",ReferenceData!$T$9),"") -> 48.345162 | T9: =IFERROR(IF(0=LEN(ReferenceData!$S$9),"",ReferenceData!$S$9),"") -> 49.255014 | U9: =IFERROR(IF(0=LEN(ReferenceData!$R$9),"",ReferenceData!$R$9),"") -> 49.626281 | V9: =IFERROR(IF(0=LEN(ReferenceData!$Q$9),"",ReferenceData!$Q$9),"") -> 49.461105 | W9: =IFERROR(IF(0=LEN(ReferenceData!$P$9),"",ReferenceData!$P$9),"") -> 50.207717 | X9: =IFERROR(IF(0=LEN(ReferenceData!$O$9),"",ReferenceData!$O$9),"") -> 51.397546 | Y9: =IFERROR(IF(0=LEN(ReferenceData!$N$9),"",ReferenceData!$N$9),"") -> 53.073346 | Z9: =IFERROR(IF(0=LEN(ReferenceData!$M$9),"",ReferenceData!$M$9),"") -> 54.656961 | AA9: =IFERROR(IF(0=LEN(ReferenceData!$L$9),"",ReferenceData!$L$9),"") -> 55.749346 | AB9: =IFERROR(IF(0=LEN(ReferenceData!$K$9),"",ReferenceData!$K$9),"") -> 56.394548 | AC9: =IFERROR(IF(0=LEN(ReferenceData!$J$9),"",ReferenceData!$J$9),"") -> 57.433797 | AD9: =IFERROR(IF(0=LEN(ReferenceData!$I$9),"",ReferenceData!$I$9),"") -> 58.220891 | AE9: =IFERROR(IF(0=LEN(ReferenceData!$H$9),"",ReferenceData!$H$9),"") -> 59.983843 | AF9: =IFERROR(IF(0=LEN(ReferenceData!$G$9),"",ReferenceData!$G$9),"") -> 60.580739 | AG9: =IFERROR(IF(0=LEN(ReferenceData!$F$9),"",ReferenceData!$F$9),"") -> 61.171637
A10: =IFERROR(IF(0=LEN(ReferenceData!$A$10),"",ReferenceData!$A$10),"") -> Passive % Of Domestic Equity Funds | B10: =IFERROR(IF(0=LEN(ReferenceData!$B$10),"",ReferenceData!$B$10),"") | C10: =IFERROR(IF(0=LEN(ReferenceData!$C$10),"",ReferenceData!$C$10),"") | D10: =IFERROR(IF(0=LEN(ReferenceData!$D$10),"",ReferenceData!$D$10),"") | E10: =IFERROR(IF(0=LEN(ReferenceData!$E$10),"",ReferenceData!$E$10),"") -> Expression | F10: =IFERROR(IF(0=LEN(ReferenceData!$AG$10),"",ReferenceData!$AG$10),"") -> 34.647602 | G10: =IFERROR(IF(0=LEN(ReferenceData!$AF$10),"",ReferenceData!$AF$10),"") -> 35.14822 | H10: =IFERROR(IF(0=LEN(ReferenceData!$AE$10),"",ReferenceData!$AE$10),"") -> 36.608365 | I10: =IFERROR(IF(0=LEN(ReferenceData!$AD$10),"",ReferenceData!$AD$10),"") -> 37.340625 | J10: =IFERROR(IF(0=LEN(ReferenceData!$AC$10),"",ReferenceData!$AC$10),"") -> 38.070971 | K10: =IFERROR(IF(0=LEN(ReferenceData!$AB$10),"",ReferenceData!$AB$10),"") -> 40.150037 | L10: =IFERROR(IF(0=LEN(ReferenceData!$AA$10),"",ReferenceData!$AA$10),"") -> 40.552479 | M10: =IFERROR(IF(0=LEN(ReferenceData!$Z$10),"",ReferenceData!$Z$10),"") -> 41.796638 | N10: =IFERROR(IF(0=LEN(ReferenceData!$Y$10),"",ReferenceData!$Y$10),"") -> 43.197555 | O10: =IFERROR(IF(0=LEN(ReferenceData!$X$10),"",ReferenceData!$X$10),"") -> 45.434496 | P10: =IFERROR(IF(0=LEN(ReferenceData!$W$10),"",ReferenceData!$W$10),"") -> 46.64149 | Q10: =IFERROR(IF(0=LEN(ReferenceData!$V$10),"",ReferenceData!$V$10),"") -> 48.355863 | R10: =IFERROR(IF(0=LEN(ReferenceData!$U$10),"",ReferenceData!$U$10),"") -> 48.591687 | S10: =IFERROR(IF(0=LEN(ReferenceData!$T$10),"",ReferenceData!$T$10),"") -> 50.829992 | T10: =IFERROR(IF(0=LEN(ReferenceData!$S$10),"",ReferenceData!$S$10),"") -> 51.778042 | U10: =IFERROR(IF(0=LEN(ReferenceData!$R$10),"",ReferenceData!$R$10),"") -> 52.420491 | V10: =IFERROR(IF(0=LEN(ReferenceData!$Q$10),"",ReferenceData!$Q$10),"") -> 52.268226 | W10: =IFERROR(IF(0=LEN(ReferenceData!$P$10),"",ReferenceData!$P$10),"") -> 53.332524 | X10: =IFERROR(IF(0=LEN(ReferenceData!$O$10),"",ReferenceData!$O$10),"") -> 54.525873 | Y10: =IFERROR(IF(0=LEN(ReferenceData!$N$10),"",ReferenceData!$N$10),"") -> 56.209454 | Z10: =IFERROR(IF(0=LEN(ReferenceData!$M$10),"",ReferenceData!$M$10),"") -> 57.703752 | AA10: =IFERROR(IF(0=LEN(ReferenceData!$L$10),"",ReferenceData!$L$10),"") -> 58.697585 | AB10: =IFERROR(IF(0=LEN(ReferenceData!$K$10),"",ReferenceData!$K$10),"") -> 59.402437 | AC10: =IFERROR(IF(0=LEN(ReferenceData!$J$10),"",ReferenceData!$J$10),"") -> 60.379999 | AD10: =IFERROR(IF(0=LEN(ReferenceData!$I$10),"",ReferenceData!$I$10),"") -> 61.174772 | AE10: =IFERROR(IF(0=LEN(ReferenceData!$H$10),"",ReferenceData!$H$10),"") -> 62.958835 | AF10: =IFERROR(IF(0=LEN(ReferenceData!$G$10),"",ReferenceData!$G$10),"") -> 63.665222 | AG10: =IFERROR(IF(0=LEN(ReferenceData!$F$10),"",ReferenceData!$F$10),"") -> 64.135501
A11: =IFERROR(IF(0=LEN(ReferenceData!$A$11),"",ReferenceData!$A$11),"") -> Passive % Of Non-Domestic Equity Funds | B11: =IFERROR(IF(0=LEN(ReferenceData!$B$11),"",ReferenceData!$B$11),"") | C11: =IFERROR(IF(0=LEN(ReferenceData!$C$11),"",ReferenceData!$C$11),"") | D11: =IFERROR(IF(0=LEN(ReferenceData!$D$11),"",ReferenceData!$D$11),"") | E11: =IFERROR(IF(0=LEN(ReferenceData!$E$11),"",ReferenceData!$E$11),"") -> Expression | F11: =IFERROR(IF(0=LEN(ReferenceData!$AG$11),"",ReferenceData!$AG$11),"") -> 26.117961 | G11: =IFERROR(IF(0=LEN(ReferenceData!$AF$11),"",ReferenceData!$AF$11),"") -> 28.061589 | H11: =IFERROR(IF(0=LEN(ReferenceData!$AE$11),"",ReferenceData!$AE$11),"") -> 26.284888 | I11: =IFERROR(IF(0=LEN(ReferenceData!$AD$11),"",ReferenceData!$AD$11),"") -> 26.847737 | J11: =IFERROR(IF(0=LEN(ReferenceData!$AC$11),"",ReferenceData!$AC$11),"") -> 27.454987 | K11: =IFERROR(IF(0=LEN(ReferenceData!$AB$11),"",ReferenceData!$AB$11),"") -> 27.828769 | L11: =IFERROR(IF(0=LEN(ReferenceData!$AA$11),"",ReferenceData!$AA$11),"") -> 30.77396 | M11: =IFERROR(IF(0=LEN(ReferenceData!$Z$11),"",ReferenceData!$Z$11),"") -> 31.853251 | N11: =IFERROR(IF(0=LEN(ReferenceData!$Y$11),"",ReferenceData!$Y$11),"") -> 32.269581 | O11: =IFERROR(IF(0=LEN(ReferenceData!$X$11),"",ReferenceData!$X$11),"") -> 33.87218 | P11: =IFERROR(IF(0=LEN(ReferenceData!$W$11),"",ReferenceData!$W$11),"") -> 36.722086 | Q11: =IFERROR(IF(0=LEN(ReferenceData!$V$11),"",ReferenceData!$V$11),"") -> 38.363707 | R11: =IFERROR(IF(0=LEN(ReferenceData!$U$11),"",ReferenceData!$U$11),"") -> 38.740654 | S11: =IFERROR(IF(0=LEN(ReferenceData!$T$11),"",ReferenceData!$T$11),"") -> 41.815125 | T11: =IFERROR(IF(0=LEN(ReferenceData!$S$11),"",ReferenceData!$S$11),"") -> 42.27947 | U11: =IFERROR(IF(0=LEN(ReferenceData!$R$11),"",ReferenceData!$R$11),"") -> 41.931891 | V11: =IFERROR(IF(0=LEN(ReferenceData!$Q$11),"",ReferenceData!$Q$11),"") -> 41.335169 | W11: =IFERROR(IF(0=LEN(ReferenceData!$P$11),"",ReferenceData!$P$11),"") -> 41.174712 | X11: =IFERROR(IF(0=LEN(ReferenceData!$O$11),"",ReferenceData!$O$11),"") -> 41.899836 | Y11: =IFERROR(IF(0=LEN(ReferenceData!$N$11),"",ReferenceData!$N$11),"") -> 42.887222 | Z11: =IFERROR(IF(0=LEN(ReferenceData!$M$11),"",ReferenceData!$M$11),"") -> 44.753116 | AA11: =IFERROR(IF(0=LEN(ReferenceData!$L$11),"",ReferenceData!$L$11),"") -> 46.06725 | AB11: =IFERROR(IF(0=LEN(ReferenceData!$K$11),"",ReferenceData!$K$11),"") -> 46.205745 | AC11: =IFERROR(IF(0=LEN(ReferenceData!$J$11),"",ReferenceData!$J$11),"") -> 46.981378 | AD11: =IFERROR(IF(0=LEN(ReferenceData!$I$11),"",ReferenceData!$I$11),"") -> 47.213647 | AE11: =IFERROR(IF(0=LEN(ReferenceData!$H$11),"",ReferenceData!$H$11),"") -> 47.850299 | AF11: =IFERROR(IF(0=LEN(ReferenceData!$G$11),"",ReferenceData!$G$11),"") -> 49.180854 | AG11: =IFERROR(IF(0=LEN(ReferenceData!$F$11),"",ReferenceData!$F$11),"") -> 50.503502
A12: =IFERROR(IF(0=LEN(ReferenceData!$A$12),"",ReferenceData!$A$12),"") -> ETF & Mutual fund AUM ($MM) | B12: =IFERROR(IF(0=LEN(ReferenceData!$B$12),"",ReferenceData!$B$12),"") | C12: =IFERROR(IF(0=LEN(ReferenceData!$C$12),"",ReferenceData!$C$12),"") | D12: =IFERROR(IF(0=LEN(ReferenceData!$D$12),"",ReferenceData!$D$12),"") | E12: =IFERROR(IF(0=LEN(ReferenceData!$E$12),"",ReferenceData!$E$12),"") -> Heading | F12: =IFERROR(IF(0=LEN(ReferenceData!$AG$12),"",ReferenceData!$AG$12),"") | G12: =IFERROR(IF(0=LEN(ReferenceData!$AF$12),"",ReferenceData!$AF$12),"") | H12: =IFERROR(IF(0=LEN(ReferenceData!$AE$12),"",ReferenceData!$AE$12),"") | I12: =IFERROR(IF(0=LEN(ReferenceData!$AD$12),"",ReferenceData!$AD$12),"") | J12: =IFERROR(IF(0=LEN(ReferenceData!$AC$12),"",ReferenceData!$AC$12),"") | K12: =IFERROR(IF(0=LEN(ReferenceData!$AB$12),"",ReferenceData!$AB$12),"") | L12: =IFERROR(IF(0=LEN(ReferenceData!$AA$12),"",ReferenceData!$AA$12),"") | M12: =IFERROR(IF(0=LEN(ReferenceData!$Z$12),"",ReferenceData!$Z$12),"") | N12: =IFERROR(IF(0=LEN(ReferenceData!$Y$12),"",ReferenceData!$Y$12),"") | O12: =IFERROR(IF(0=LEN(ReferenceData!$X$12),"",ReferenceData!$X$12),"") | P12: =IFERROR(IF(0=LEN(ReferenceData!$W$12),"",ReferenceData!$W$12),"") | Q12: =IFERROR(IF(0=LEN(ReferenceData!$V$12),"",ReferenceData!$V$12),"") | R12: =IFERROR(IF(0=LEN(ReferenceData!$U$12),"",ReferenceData!$U$12),"") | S12: =IFERROR(IF(0=LEN(ReferenceData!$T$12),"",ReferenceData!$T$12),"") | T12: =IFERROR(IF(0=LEN(ReferenceData!$S$12),"",ReferenceData!$S$12),"") | U12: =IFERROR(IF(0=LEN(ReferenceData!$R$12),"",ReferenceData!$R$12),"") | V12: =IFERROR(IF(0=LEN(ReferenceData!$Q$12),"",ReferenceData!$Q$12),"") | W12: =IFERROR(IF(0=LEN(ReferenceData!$P$12),"",ReferenceData!$P$12),"") | X12: =IFERROR(IF(0=LEN(ReferenceData!$O$12),"",ReferenceData!$O$12),"") | Y12: =IFERROR(IF(0=LEN(ReferenceData!$N$12),"",ReferenceData!$N$12),"") | Z12: =IFERROR(IF(0=LEN(ReferenceData!$M$12),"",ReferenceData!$M$12),"") | AA12: =IFERROR(IF(0=LEN(ReferenceData!$L$12),"",ReferenceData!$L$12),"") | AB12: =IFERROR(IF(0=LEN(ReferenceData!$K$12),"",ReferenceData!$K$12),"") | AC12: =IFERROR(IF(0=LEN(ReferenceData!$J$12),"",ReferenceData!$J$12),"") | AD12: =IFERROR(IF(0=LEN(ReferenceData!$I$12),"",ReferenceData!$I$12),"") | AE12: =IFERROR(IF(0=LEN(ReferenceData!$H$12),"",ReferenceData!$H$12),"") | AF12: =IFERROR(IF(0=LEN(ReferenceData!$G$12),"",ReferenceData!$G$12),"") | AG12: =IFERROR(IF(0=LEN(ReferenceData!$F$12),"",ReferenceData!$F$12),"")
A13: =IFERROR(IF(0=LEN(ReferenceData!$A$13),"",ReferenceData!$A$13),"") -> All ETFs & Mutual Funds | B13: =IFERROR(IF(0=LEN(ReferenceData!$B$13),"",ReferenceData!$B$13),"") | C13: =IFERROR(IF(0=LEN(ReferenceData!$C$13),"",ReferenceData!$C$13),"") | D13: =IFERROR(IF(0=LEN(ReferenceData!$D$13),"",ReferenceData!$D$13),"") | E13: =IFERROR(IF(0=LEN(ReferenceData!$E$13),"",ReferenceData!$E$13),"") -> Sum | F13: =IFERROR(IF(0=LEN(ReferenceData!$AG$13),"",ReferenceData!$AG$13),"") -> 8871800 | G13: =IFERROR(IF(0=LEN(ReferenceData!$AF$13),"",ReferenceData!$AF$13),"") -> 9709500 | H13: =IFERROR(IF(0=LEN(ReferenceData!$AE$13),"",ReferenceData!$AE$13),"") -> 10582720 | I13: =IFERROR(IF(0=LEN(ReferenceData!$AD$13),"",ReferenceData!$AD$13),"") -> 11805870 | J13: =IFERROR(IF(0=LEN(ReferenceData!$AC$13),"",ReferenceData!$AC$13),"") -> 12902600 | K13: =IFERROR(IF(0=LEN(ReferenceData!$AB$13),"",ReferenceData!$AB$13),"") -> 13019770 | L13: =IFERROR(IF(0=LEN(ReferenceData!$AA$13),"",ReferenceData!$AA$13),"") -> 13543950 | M13: =IFERROR(IF(0=LEN(ReferenceData!$Z$13),"",ReferenceData!$Z$13),"") -> 13029040 | N13: =IFERROR(IF(0=LEN(ReferenceData!$Y$13),"",ReferenceData!$Y$13),"") -> 13640670 | O13: =IFERROR(IF(0=LEN(ReferenceData!$X$13),"",ReferenceData!$X$13),"") -> 14324120 | P13: =IFERROR(IF(0=LEN(ReferenceData!$W$13),"",ReferenceData!$W$13),"") -> 15915490 | Q13: =IFERROR(IF(0=LEN(ReferenceData!$V$13),"",ReferenceData!$V$13),"") -> 17409930 | R13: =IFERROR(IF(0=LEN(ReferenceData!$U$13),"",ReferenceData!$U$13),"") -> 17807800 | S13: =IFERROR(IF(0=LEN(ReferenceData!$T$13),"",ReferenceData!$T$13),"") -> 16331690 | T13: =IFERROR(IF(0=LEN(ReferenceData!$S$13),"",ReferenceData!$S$13),"") -> 18590680 | U13: =IFERROR(IF(0=LEN(ReferenceData!$R$13),"",ReferenceData!$R$13),"") -> 20340130 | V13: =IFERROR(IF(0=LEN(ReferenceData!$Q$13),"",ReferenceData!$Q$13),"") -> 19828130 | W13: =IFERROR(IF(0=LEN(ReferenceData!$P$13),"",ReferenceData!$P$13),"") -> 23408700 | X13: =IFERROR(IF(0=LEN(ReferenceData!$O$13),"",ReferenceData!$O$13),"") -> 26256600 | Y13: =IFERROR(IF(0=LEN(ReferenceData!$N$13),"",ReferenceData!$N$13),"") -> 27592600 | Z13: =IFERROR(IF(0=LEN(ReferenceData!$M$13),"",ReferenceData!$M$13),"") -> 22719500 | AA13: =IFERROR(IF(0=LEN(ReferenceData!$L$13),"",ReferenceData!$L$13),"") -> 22642900 | AB13: =IFERROR(IF(0=LEN(ReferenceData!$K$13),"",ReferenceData!$K$13),"") -> 24675300 | AC13: =IFERROR(IF(0=LEN(ReferenceData!$J$13),"",ReferenceData!$J$13),"") -> 26255600 | AD13: =IFERROR(IF(0=LEN(ReferenceData!$I$13),"",ReferenceData!$I$13),"") -> 28836200 | AE13: =IFERROR(IF(0=LEN(ReferenceData!$H$13),"",ReferenceData!$H$13),"") -> 30580600 | AF13: =IFERROR(IF(0=LEN(ReferenceData!$G$13),"",ReferenceData!$G$13),"") -> 32637700 | AG13: =IFERROR(IF(0=LEN(ReferenceData!$F$13),"",ReferenceData!$F$13),"") -> 35084700
A14: =IFERROR(IF(0=LEN(ReferenceData!$A$14),"",ReferenceData!$A$14),"") -> Passive Funds | B14: =IFERROR(IF(0=LEN(ReferenceData!$B$14),"",ReferenceData!$B$14),"") -> .BIATPTT G Index | C14: =IFERROR(IF(0=LEN(ReferenceData!$C$14),"",ReferenceData!$C$14),"") -> PR005 | D14: =IFERROR(IF(0=LEN(ReferenceData!$D$14),"",ReferenceData!$D$14),"") -> PX_LAST | E14: =IFERROR(IF(0=LEN(ReferenceData!$E$14),"",ReferenceData!$E$14),"") -> Dynamic | F14: =IFERROR(IF(0=LEN(ReferenceData!$AG$14),"",ReferenceData!$AG$14),"") -> 2219700 | G14: =IFERROR(IF(0=LEN(ReferenceData!$AF$14),"",ReferenceData!$AF$14),"") -> 2474180 | H14: =IFERROR(IF(0=LEN(ReferenceData!$AE$14),"",ReferenceData!$AE$14),"") -> 2761560 | I14: =IFERROR(IF(0=LEN(ReferenceData!$AD$14),"",ReferenceData!$AD$14),"") -> 3214070 | J14: =IFERROR(IF(0=LEN(ReferenceData!$AC$14),"",ReferenceData!$AC$14),"") -> 3575580 | K14: =IFERROR(IF(0=LEN(ReferenceData!$AB$14),"",ReferenceData!$AB$14),"") -> 3831310 | L14: =IFERROR(IF(0=LEN(ReferenceData!$AA$14),"",ReferenceData!$AA$14),"") -> 4119720 | M14: =IFERROR(IF(0=LEN(ReferenceData!$Z$14),"",ReferenceData!$Z$14),"") -> 4092380 | N14: =IFERROR(IF(0=LEN(ReferenceData!$Y$14),"",ReferenceData!$Y$14),"") -> 4433920 | O14: =IFERROR(IF(0=LEN(ReferenceData!$X$14),"",ReferenceData!$X$14),"") -> 4920680 | P14: =IFERROR(IF(0=LEN(ReferenceData!$W$14),"",ReferenceData!$W$14),"") -> 5733790 | Q14: =IFERROR(IF(0=LEN(ReferenceData!$V$14),"",ReferenceData!$V$14),"") -> 6572430 | R14: =IFERROR(IF(0=LEN(ReferenceData!$U$14),"",ReferenceData!$U$14),"") -> 6806800 | S14: =IFERROR(IF(0=LEN(ReferenceData!$T$14),"",ReferenceData!$T$14),"") -> 6506890 | T14: =IFERROR(IF(0=LEN(ReferenceData!$S$14),"",ReferenceData!$S$14),"") -> 7656780 | U14: =IFERROR(IF(0=LEN(ReferenceData!$R$14),"",ReferenceData!$R$14),"") -> 8462530 | V14: =IFERROR(IF(0=LEN(ReferenceData!$Q$14),"",ReferenceData!$Q$14),"") -> 8284230 | W14: =IFERROR(IF(0=LEN(ReferenceData!$P$14),"",ReferenceData!$P$14),"") -> 10017000 | X14: =IFERROR(IF(0=LEN(ReferenceData!$O$14),"",ReferenceData!$O$14),"") -> 11521000 | Y14: =IFERROR(IF(0=LEN(ReferenceData!$N$14),"",ReferenceData!$N$14),"") -> 12507300 | Z14: =IFERROR(IF(0=LEN(ReferenceData!$M$14),"",ReferenceData!$M$14),"") -> 10542800 | AA14: =IFERROR(IF(0=LEN(ReferenceData!$L$14),"",ReferenceData!$L$14),"") -> 10860600 | AB14: =IFERROR(IF(0=LEN(ReferenceData!$K$14),"",ReferenceData!$K$14),"") -> 12079400 | AC14: =IFERROR(IF(0=LEN(ReferenceData!$J$14),"",ReferenceData!$J$14),"") -> 13163700 | AD14: =IFERROR(IF(0=LEN(ReferenceData!$I$14),"",ReferenceData!$I$14),"") -> 14743000 | AE14: =IFERROR(IF(0=LEN(ReferenceData!$H$14),"",ReferenceData!$H$14),"") -> 16097200 | AF14: =IFERROR(IF(0=LEN(ReferenceData!$G$14),"",ReferenceData!$G$14),"") -> 17442000 | AG14: =IFERROR(IF(0=LEN(ReferenceData!$F$14),"",ReferenceData!$F$14),"") -> 18974200
A15: =IFERROR(IF(0=LEN(ReferenceData!$A$15),"",ReferenceData!$A$15),"") -> Passive Mutual Funds | B15: =IFERROR(IF(0=LEN(ReferenceData!$B$15),"",ReferenceData!$B$15),"") -> .BIAMPTT G Index | C15: =IFERROR(IF(0=LEN(ReferenceData!$C$15),"",ReferenceData!$C$15),"") -> PR005 | D15: =IFERROR(IF(0=LEN(ReferenceData!$D$15),"",ReferenceData!$D$15),"") -> PX_LAST | E15: =IFERROR(IF(0=LEN(ReferenceData!$E$15),"",ReferenceData!$E$15),"") -> Dynamic | F15: =IFERROR(IF(0=LEN(ReferenceData!$AG$15),"",ReferenceData!$AG$15),"") -> 1073950 | G15: =IFERROR(IF(0=LEN(ReferenceData!$AF$15),"",ReferenceData!$AF$15),"") -> 1178570 | H15: =IFERROR(IF(0=LEN(ReferenceData!$AE$15),"",ReferenceData!$AE$15),"") -> 1349510 | I15: =IFERROR(IF(0=LEN(ReferenceData!$AD$15),"",ReferenceData!$AD$15),"") -> 1575100 | J15: =IFERROR(IF(0=LEN(ReferenceData!$AC$15),"",ReferenceData!$AC$15),"") -> 1772810 | K15: =IFERROR(IF(0=LEN(ReferenceData!$AB$15),"",ReferenceData!$AB$15),"") -> 1902020 | L15: =IFERROR(IF(0=LEN(ReferenceData!$AA$15),"",ReferenceData!$AA$15),"") -> 2042090 | M15: =IFERROR(IF(0=LEN(ReferenceData!$Z$15),"",ReferenceData!$Z$15),"") -> 2054650 | N15: =IFERROR(IF(0=LEN(ReferenceData!$Y$15),"",ReferenceData!$Y$15),"") -> 2227660 | O15: =IFERROR(IF(0=LEN(ReferenceData!$X$15),"",ReferenceData!$X$15),"") -> 2415390 | P15: =IFERROR(IF(0=LEN(ReferenceData!$W$15),"",ReferenceData!$W$15),"") -> 2822350 | Q15: =IFERROR(IF(0=LEN(ReferenceData!$V$15),"",ReferenceData!$V$15),"") -> 3184940 | R15: =IFERROR(IF(0=LEN(ReferenceData!$U$15),"",ReferenceData!$U$15),"") -> 3331210 | S15: =IFERROR(IF(0=LEN(ReferenceData!$T$15),"",ReferenceData!$T$15),"") -> 3182710 | T15: =IFERROR(IF(0=LEN(ReferenceData!$S$15),"",ReferenceData!$S$15),"") -> 3786900 | U15: =IFERROR(IF(0=LEN(ReferenceData!$R$15),"",ReferenceData!$R$15),"") -> 4144870 | V15: =IFERROR(IF(0=LEN(ReferenceData!$Q$15),"",ReferenceData!$Q$15),"") -> 3999840 | W15: =IFERROR(IF(0=LEN(ReferenceData!$P$15),"",ReferenceData!$P$15),"") -> 4687590 | X15: =IFERROR(IF(0=LEN(ReferenceData!$O$15),"",ReferenceData!$O$15),"") -> 5257020 | Y15: =IFERROR(IF(0=LEN(ReferenceData!$N$15),"",ReferenceData!$N$15),"") -> 5630760 | Z15: =IFERROR(IF(0=LEN(ReferenceData!$M$15),"",ReferenceData!$M$15),"") -> 4634540 | AA15: =IFERROR(IF(0=LEN(ReferenceData!$L$15),"",ReferenceData!$L$15),"") -> 4692710 | AB15: =IFERROR(IF(0=LEN(ReferenceData!$K$15),"",ReferenceData!$K$15),"") -> 5213990 | AC15: =IFERROR(IF(0=LEN(ReferenceData!$J$15),"",ReferenceData!$J$15),"") -> 5605390 | AD15: =IFERROR(IF(0=LEN(ReferenceData!$I$15),"",ReferenceData!$I$15),"") -> 6213380 | AE15: =IFERROR(IF(0=LEN(ReferenceData!$H$15),"",ReferenceData!$H$15),"") -> 6612880 | AF15: =IFERROR(IF(0=LEN(ReferenceData!$G$15),"",ReferenceData!$G$15),"") -> 7058640 | AG15: =IFERROR(IF(0=LEN(ReferenceData!$F$15),"",ReferenceData!$F$15),"") -> 7353540
A16: =IFERROR(IF(0=LEN(ReferenceData!$A$16),"",ReferenceData!$A$16),"") -> Passive ETFs | B16: =IFERROR(IF(0=LEN(ReferenceData!$B$16),"",ReferenceData!$B$16),"") | C16: =IFERROR(IF(0=LEN(ReferenceData!$C$16),"",ReferenceData!$C$16),"") | D16: =IFERROR(IF(0=LEN(ReferenceData!$D$16),"",ReferenceData!$D$16),"") | E16: =IFERROR(IF(0=LEN(ReferenceData!$E$16),"",ReferenceData!$E$16),"") -> Expression | F16: =IFERROR(IF(0=LEN(ReferenceData!$AG$16),"",ReferenceData!$AG$16),"") -> 1145750 | G16: =IFERROR(IF(0=LEN(ReferenceData!$AF$16),"",ReferenceData!$AF$16),"") -> 1295610 | H16: =IFERROR(IF(0=LEN(ReferenceData!$AE$16),"",ReferenceData!$AE$16),"") -> 1412050 | I16: =IFERROR(IF(0=LEN(ReferenceData!$AD$16),"",ReferenceData!$AD$16),"") -> 1638970 | J16: =IFERROR(IF(0=LEN(ReferenceData!$AC$16),"",ReferenceData!$AC$16),"") -> 1802770 | K16: =IFERROR(IF(0=LEN(ReferenceData!$AB$16),"",ReferenceData!$AB$16),"") -> 1929290 | L16: =IFERROR(IF(0=LEN(ReferenceData!$AA$16),"",ReferenceData!$AA$16),"") -> 2077630 | M16: =IFERROR(IF(0=LEN(ReferenceData!$Z$16),"",ReferenceData!$Z$16),"") -> 2037730 | N16: =IFERROR(IF(0=LEN(ReferenceData!$Y$16),"",ReferenceData!$Y$16),"") -> 2206260 | O16: =IFERROR(IF(0=LEN(ReferenceData!$X$16),"",ReferenceData!$X$16),"") -> 2505290 | P16: =IFERROR(IF(0=LEN(ReferenceData!$W$16),"",ReferenceData!$W$16),"") -> 2911440 | Q16: =IFERROR(IF(0=LEN(ReferenceData!$V$16),"",ReferenceData!$V$16),"") -> 3387490 | R16: =IFERROR(IF(0=LEN(ReferenceData!$U$16),"",ReferenceData!$U$16),"") -> 3475590 | S16: =IFERROR(IF(0=LEN(ReferenceData!$T$16),"",ReferenceData!$T$16),"") -> 3324180 | T16: =IFERROR(IF(0=LEN(ReferenceData!$S$16),"",ReferenceData!$S$16),"") -> 3869880 | U16: =IFERROR(IF(0=LEN(ReferenceData!$R$16),"",ReferenceData!$R$16),"") -> 4317660 | V16: =IFERROR(IF(0=LEN(ReferenceData!$Q$16),"",ReferenceData!$Q$16),"") -> 4284390 | W16: =IFERROR(IF(0=LEN(ReferenceData!$P$16),"",ReferenceData!$P$16),"") -> 5329410 | X16: =IFERROR(IF(0=LEN(ReferenceData!$O$16),"",ReferenceData!$O$16),"") -> 6263980 | Y16: =IFERROR(IF(0=LEN(ReferenceData!$N$16),"",ReferenceData!$N$16),"") -> 6876540 | Z16: =IFERROR(IF(0=LEN(ReferenceData!$M$16),"",ReferenceData!$M$16),"") -> 5908260 | AA16: =IFERROR(IF(0=LEN(ReferenceData!$L$16),"",ReferenceData!$L$16),"") -> 6167890 | AB16: =IFERROR(IF(0=LEN(ReferenceData!$K$16),"",ReferenceData!$K$16),"") -> 6865410 | AC16: =IFERROR(IF(0=LEN(ReferenceData!$J$16),"",ReferenceData!$J$16),"") -> 7558310 | AD16: =IFERROR(IF(0=LEN(ReferenceData!$I$16),"",ReferenceData!$I$16),"") -> 8529620 | AE16: =IFERROR(IF(0=LEN(ReferenceData!$H$16),"",ReferenceData!$H$16),"") -> 9484320 | AF16: =IFERROR(IF(0=LEN(ReferenceData!$G$16),"",ReferenceData!$G$16),"") -> 10383360 | AG16: =IFERROR(IF(0=LEN(ReferenceData!$F$16),"",ReferenceData!$F$16),"") -> 11620660
A17: =IFERROR(IF(0=LEN(ReferenceData!$A$17),"",ReferenceData!$A$17),"") -> Active Funds | B17: =IFERROR(IF(0=LEN(ReferenceData!$B$17),"",ReferenceData!$B$17),"") -> .BIATATT G Index | C17: =IFERROR(IF(0=LEN(ReferenceData!$C$17),"",ReferenceData!$C$17),"") -> PR005 | D17: =IFERROR(IF(0=LEN(ReferenceData!$D$17),"",ReferenceData!$D$17),"") -> PX_LAST | E17: =IFERROR(IF(0=LEN(ReferenceData!$E$17),"",ReferenceData!$E$17),"") -> Dynamic | F17: =IFERROR(IF(0=LEN(ReferenceData!$AG$17),"",ReferenceData!$AG$17),"") -> 6652100 | G17: =IFERROR(IF(0=LEN(ReferenceData!$AF$17),"",ReferenceData!$AF$17),"") -> 7235320 | H17: =IFERROR(IF(0=LEN(ReferenceData!$AE$17),"",ReferenceData!$AE$17),"") -> 7821160 | I17: =IFERROR(IF(0=LEN(ReferenceData!$AD$17),"",ReferenceData!$AD$17),"") -> 8591800 | J17: =IFERROR(IF(0=LEN(ReferenceData!$AC$17),"",ReferenceData!$AC$17),"") -> 9327020 | K17: =IFERROR(IF(0=LEN(ReferenceData!$AB$17),"",ReferenceData!$AB$17),"") -> 9188460 | L17: =IFERROR(IF(0=LEN(ReferenceData!$AA$17),"",ReferenceData!$AA$17),"") -> 9424230 | M17: =IFERROR(IF(0=LEN(ReferenceData!$Z$17),"",ReferenceData!$Z$17),"") -> 8936660 | N17: =IFERROR(IF(0=LEN(ReferenceData!$Y$17),"",ReferenceData!$Y$17),"") -> 9206750 | O17: =IFERROR(IF(0=LEN(ReferenceData!$X$17),"",ReferenceData!$X$17),"") -> 9403440 | P17: =IFERROR(IF(0=LEN(ReferenceData!$W$17),"",ReferenceData!$W$17),"") -> 10181700 | Q17: =IFERROR(IF(0=LEN(ReferenceData!$V$17),"",ReferenceData!$V$17),"") -> 10837500 | R17: =IFERROR(IF(0=LEN(ReferenceData!$U$17),"",ReferenceData!$U$17),"") -> 11001000 | S17: =IFERROR(IF(0=LEN(ReferenceData!$T$17),"",ReferenceData!$T$17),"") -> 9824800 | T17: =IFERROR(IF(0=LEN(ReferenceData!$S$17),"",ReferenceData!$S$17),"") -> 10933900 | U17: =IFERROR(IF(0=LEN(ReferenceData!$R$17),"",ReferenceData!$R$17),"") -> 11877600 | V17: =IFERROR(IF(0=LEN(ReferenceData!$Q$17),"",ReferenceData!$Q$17),"") -> 11543900 | W17: =IFERROR(IF(0=LEN(ReferenceData!$P$17),"",ReferenceData!$P$17),"") -> 13391700 | X17: =IFERROR(IF(0=LEN(ReferenceData!$O$17),"",ReferenceData!$O$17),"") -> 14735600 | Y17: =IFERROR(IF(0=LEN(ReferenceData!$N$17),"",ReferenceData!$N$17),"") -> 15085300 | Z17: =IFERROR(IF(0=LEN(ReferenceData!$M$17),"",ReferenceData!$M$17),"") -> 12176700 | AA17: =IFERROR(IF(0=LEN(ReferenceData!$L$17),"",ReferenceData!$L$17),"") -> 11782300 | AB17: =IFERROR(IF(0=LEN(ReferenceData!$K$17),"",ReferenceData!$K$17),"") -> 12595900 | AC17: =IFERROR(IF(0=LEN(ReferenceData!$J$17),"",ReferenceData!$J$17),"") -> 13091900 | AD17: =IFERROR(IF(0=LEN(ReferenceData!$I$17),"",ReferenceData!$I$17),"") -> 14093200 | AE17: =IFERROR(IF(0=LEN(ReferenceData!$H$17),"",ReferenceData!$H$17),"") -> 14483400 | AF17: =IFERROR(IF(0=LEN(ReferenceData!$G$17),"",ReferenceData!$G$17),"") -> 15195700 | AG17: =IFERROR(IF(0=LEN(ReferenceData!$F$17),"",ReferenceData!$F$17),"") -> 16110500
A18: =IFERROR(IF(0=LEN(ReferenceData!$A$18),"",ReferenceData!$A$18),"") -> Active Mutual Funds | B18: =IFERROR(IF(0=LEN(ReferenceData!$B$18),"",ReferenceData!$B$18),"") -> .BIAMATT G Index | C18: =IFERROR(IF(0=LEN(ReferenceData!$C$18),"",ReferenceData!$C$18),"") -> PR005 | D18: =IFERROR(IF(0=LEN(ReferenceData!$D$18),"",ReferenceData!$D$18),"") -> PX_LAST | E18: =IFERROR(IF(0=LEN(ReferenceData!$E$18),"",ReferenceData!$E$18),"") -> Dynamic | F18: =IFERROR(IF(0=LEN(ReferenceData!$AG$18),"",ReferenceData!$AG$18),"") -> 6625190 | G18: =IFERROR(IF(0=LEN(ReferenceData!$AF$18),"",ReferenceData!$AF$18),"") -> 7209500 | H18: =IFERROR(IF(0=LEN(ReferenceData!$AE$18),"",ReferenceData!$AE$18),"") -> 7781640 | I18: =IFERROR(IF(0=LEN(ReferenceData!$AD$18),"",ReferenceData!$AD$18),"") -> 8547190 | J18: =IFERROR(IF(0=LEN(ReferenceData!$AC$18),"",ReferenceData!$AC$18),"") -> 9275590 | K18: =IFERROR(IF(0=LEN(ReferenceData!$AB$18),"",ReferenceData!$AB$18),"") -> 9135500 | L18: =IFERROR(IF(0=LEN(ReferenceData!$AA$18),"",ReferenceData!$AA$18),"") -> 9363890 | M18: =IFERROR(IF(0=LEN(ReferenceData!$Z$18),"",ReferenceData!$Z$18),"") -> 8876340 | N18: =IFERROR(IF(0=LEN(ReferenceData!$Y$18),"",ReferenceData!$Y$18),"") -> 9138660 | O18: =IFERROR(IF(0=LEN(ReferenceData!$X$18),"",ReferenceData!$X$18),"") -> 9323080 | P18: =IFERROR(IF(0=LEN(ReferenceData!$W$18),"",ReferenceData!$W$18),"") -> 10089600 | Q18: =IFERROR(IF(0=LEN(ReferenceData!$V$18),"",ReferenceData!$V$18),"") -> 10726200 | R18: =IFERROR(IF(0=LEN(ReferenceData!$U$18),"",ReferenceData!$U$18),"") -> 10872700 | S18: =IFERROR(IF(0=LEN(ReferenceData!$T$18),"",ReferenceData!$T$18),"") -> 9694990 | T18: =IFERROR(IF(0=LEN(ReferenceData!$S$18),"",ReferenceData!$S$18),"") -> 10781600 | U18: =IFERROR(IF(0=LEN(ReferenceData!$R$18),"",ReferenceData!$R$18),"") -> 11701500 | V18: =IFERROR(IF(0=LEN(ReferenceData!$Q$18),"",ReferenceData!$Q$18),"") -> 11361300 | W18: =IFERROR(IF(0=LEN(ReferenceData!$P$18),"",ReferenceData!$P$18),"") -> 13136100 | X18: =IFERROR(IF(0=LEN(ReferenceData!$O$18),"",ReferenceData!$O$18),"") -> 14403900 | Y18: =IFERROR(IF(0=LEN(ReferenceData!$N$18),"",ReferenceData!$N$18),"") -> 14726600 | Z18: =IFERROR(IF(0=LEN(ReferenceData!$M$18),"",ReferenceData!$M$18),"") -> 11808600 | AA18: =IFERROR(IF(0=LEN(ReferenceData!$L$18),"",ReferenceData!$L$18),"") -> 11368200 | AB18: =IFERROR(IF(0=LEN(ReferenceData!$K$18),"",ReferenceData!$K$18),"") -> 12101400 | AC18: =IFERROR(IF(0=LEN(ReferenceData!$J$18),"",ReferenceData!$J$18),"") -> 12502600 | AD18: =IFERROR(IF(0=LEN(ReferenceData!$I$18),"",ReferenceData!$I$18),"") -> 13335100 | AE18: =IFERROR(IF(0=LEN(ReferenceData!$H$18),"",ReferenceData!$H$18),"") -> 13538000 | AF18: =IFERROR(IF(0=LEN(ReferenceData!$G$18),"",ReferenceData!$G$18),"") -> 14039000 | AG18: =IFERROR(IF(0=LEN(ReferenceData!$F$18),"",ReferenceData!$F$18),"") -> 14722300
A19: =IFERROR(IF(0=LEN(ReferenceData!$A$19),"",ReferenceData!$A$19),"") -> Active ETFs | B19: =IFERROR(IF(0=LEN(ReferenceData!$B$19),"",ReferenceData!$B$19),"") | C19: =IFERROR(IF(0=LEN(ReferenceData!$C$19),"",ReferenceData!$C$19),"") | D19: =IFERROR(IF(0=LEN(ReferenceData!$D$19),"",ReferenceData!$D$19),"") | E19: =IFERROR(IF(0=LEN(ReferenceData!$E$19),"",ReferenceData!$E$19),"") -> Expression | F19: =IFERROR(IF(0=LEN(ReferenceData!$AG$19),"",ReferenceData!$AG$19),"") -> 26910 | G19: =IFERROR(IF(0=LEN(ReferenceData!$AF$19),"",ReferenceData!$AF$19),"") -> 25820 | H19: =IFERROR(IF(0=LEN(ReferenceData!$AE$19),"",ReferenceData!$AE$19),"") -> 39520 | I19: =IFERROR(IF(0=LEN(ReferenceData!$AD$19),"",ReferenceData!$AD$19),"") -> 44610 | J19: =IFERROR(IF(0=LEN(ReferenceData!$AC$19),"",ReferenceData!$AC$19),"") -> 51430 | K19: =IFERROR(IF(0=LEN(ReferenceData!$AB$19),"",ReferenceData!$AB$19),"") -> 52960 | L19: =IFERROR(IF(0=LEN(ReferenceData!$AA$19),"",ReferenceData!$AA$19),"") -> 60340 | M19: =IFERROR(IF(0=LEN(ReferenceData!$Z$19),"",ReferenceData!$Z$19),"") -> 60320 | N19: =IFERROR(IF(0=LEN(ReferenceData!$Y$19),"",ReferenceData!$Y$19),"") -> 68090 | O19: =IFERROR(IF(0=LEN(ReferenceData!$X$19),"",ReferenceData!$X$19),"") -> 80360 | P19: =IFERROR(IF(0=LEN(ReferenceData!$W$19),"",ReferenceData!$W$19),"") -> 92100 | Q19: =IFERROR(IF(0=LEN(ReferenceData!$V$19),"",ReferenceData!$V$19),"") -> 111300 | R19: =IFERROR(IF(0=LEN(ReferenceData!$U$19),"",ReferenceData!$U$19),"") -> 128300 | S19: =IFERROR(IF(0=LEN(ReferenceData!$T$19),"",ReferenceData!$T$19),"") -> 129810 | T19: =IFERROR(IF(0=LEN(ReferenceData!$S$19),"",ReferenceData!$S$19),"") -> 152300 | U19: =IFERROR(IF(0=LEN(ReferenceData!$R$19),"",ReferenceData!$R$19),"") -> 176100 | V19: =IFERROR(IF(0=LEN(ReferenceData!$Q$19),"",ReferenceData!$Q$19),"") -> 182600 | W19: =IFERROR(IF(0=LEN(ReferenceData!$P$19),"",ReferenceData!$P$19),"") -> 255600 | X19: =IFERROR(IF(0=LEN(ReferenceData!$O$19),"",ReferenceData!$O$19),"") -> 331700 | Y19: =IFERROR(IF(0=LEN(ReferenceData!$N$19),"",ReferenceData!$N$19),"") -> 358700 | Z19: =IFERROR(IF(0=LEN(ReferenceData!$M$19),"",ReferenceData!$M$19),"") -> 368100 | AA19: =IFERROR(IF(0=LEN(ReferenceData!$L$19),"",ReferenceData!$L$19),"") -> 414100 | AB19: =IFERROR(IF(0=LEN(ReferenceData!$K$19),"",ReferenceData!$K$19),"") -> 494500 | AC19: =IFERROR(IF(0=LEN(ReferenceData!$J$19),"",ReferenceData!$J$19),"") -> 589300 | AD19: =IFERROR(IF(0=LEN(ReferenceData!$I$19),"",ReferenceData!$I$19),"") -> 758100 | AE19: =IFERROR(IF(0=LEN(ReferenceData!$H$19),"",ReferenceData!$H$19),"") -> 945400 | AF19: =IFERROR(IF(0=LEN(ReferenceData!$G$19),"",ReferenceData!$G$19),"") -> 1156700 | AG19: =IFERROR(IF(0=LEN(ReferenceData!$F$19),"",ReferenceData!$F$19),"") -> 1388200
A20: =IFERROR(IF(0=LEN(ReferenceData!$A$20),"",ReferenceData!$A$20),"") -> All Fixed Income Funds | B20: =IFERROR(IF(0=LEN(ReferenceData!$B$20),"",ReferenceData!$B$20),"") | C20: =IFERROR(IF(0=LEN(ReferenceData!$C$20),"",ReferenceData!$C$20),"") | D20: =IFERROR(IF(0=LEN(ReferenceData!$D$20),"",ReferenceData!$D$20),"") | E20: =IFERROR(IF(0=LEN(ReferenceData!$E$20),"",ReferenceData!$E$20),"") -> Sum | F20: =IFERROR(IF(0=LEN(ReferenceData!$AG$20),"",ReferenceData!$AG$20),"") -> 2826984 | G20: =IFERROR(IF(0=LEN(ReferenceData!$AF$20),"",ReferenceData!$AF$20),"") -> 3097681 | H20: =IFERROR(IF(0=LEN(ReferenceData!$AE$20),"",ReferenceData!$AE$20),"") -> 3111397 | I20: =IFERROR(IF(0=LEN(ReferenceData!$AD$20),"",ReferenceData!$AD$20),"") -> 3059854 | J20: =IFERROR(IF(0=LEN(ReferenceData!$AC$20),"",ReferenceData!$AC$20),"") -> 3285478 | K20: =IFERROR(IF(0=LEN(ReferenceData!$AB$20),"",ReferenceData!$AB$20),"") -> 3308345 | L20: =IFERROR(IF(0=LEN(ReferenceData!$AA$20),"",ReferenceData!$AA$20),"") -> 3370027 | M20: =IFERROR(IF(0=LEN(ReferenceData!$Z$20),"",ReferenceData!$Z$20),"") -> 3335201 | N20: =IFERROR(IF(0=LEN(ReferenceData!$Y$20),"",ReferenceData!$Y$20),"") -> 3619598 | O20: =IFERROR(IF(0=LEN(ReferenceData!$X$20),"",ReferenceData!$X$20),"") -> 3668062 | P20: =IFERROR(IF(0=LEN(ReferenceData!$W$20),"",ReferenceData!$W$20),"") -> 3988585 | Q20: =IFERROR(IF(0=LEN(ReferenceData!$V$20),"",ReferenceData!$V$20),"") -> 4203400 | R20: =IFERROR(IF(0=LEN(ReferenceData!$U$20),"",ReferenceData!$U$20),"") -> 4324080 | S20: =IFERROR(IF(0=LEN(ReferenceData!$T$20),"",ReferenceData!$T$20),"") -> 4315060 | T20: =IFERROR(IF(0=LEN(ReferenceData!$S$20),"",ReferenceData!$S$20),"") -> 4737200 | U20: =IFERROR(IF(0=LEN(ReferenceData!$R$20),"",ReferenceData!$R$20),"") -> 5192150 | V20: =IFERROR(IF(0=LEN(ReferenceData!$Q$20),"",ReferenceData!$Q$20),"") -> 5394600 | W20: =IFERROR(IF(0=LEN(ReferenceData!$P$20),"",ReferenceData!$P$20),"") -> 5999420 | X20: =IFERROR(IF(0=LEN(ReferenceData!$O$20),"",ReferenceData!$O$20),"") -> 6422860 | Y20: =IFERROR(IF(0=LEN(ReferenceData!$N$20),"",ReferenceData!$N$20),"") -> 6645050 | Z20: =IFERROR(IF(0=LEN(ReferenceData!$M$20),"",ReferenceData!$M$20),"") -> 5818320 | AA20: =IFERROR(IF(0=LEN(ReferenceData!$L$20),"",ReferenceData!$L$20),"") -> 5610830 | AB20: =IFERROR(IF(0=LEN(ReferenceData!$K$20),"",ReferenceData!$K$20),"") -> 5753570 | AC20: =IFERROR(IF(0=LEN(ReferenceData!$J$20),"",ReferenceData!$J$20),"") -> 6003270 | AD20: =IFERROR(IF(0=LEN(ReferenceData!$I$20),"",ReferenceData!$I$20),"") -> 6231860 | AE20: =IFERROR(IF(0=LEN(ReferenceData!$H$20),"",ReferenceData!$H$20),"") -> 6572320 | AF20: =IFERROR(IF(0=LEN(ReferenceData!$G$20),"",ReferenceData!$G$20),"") -> 6885580 | AG20: =IFERROR(IF(0=LEN(ReferenceData!$F$20),"",ReferenceData!$F$20),"") -> 7344380
A21: =IFERROR(IF(0=LEN(ReferenceData!$A$21),"",ReferenceData!$A$21),"") -> Passive Fixed Income | B21: =IFERROR(IF(0=LEN(ReferenceData!$B$21),"",ReferenceData!$B$21),"") -> .BIATPTF G Index | C21: =IFERROR(IF(0=LEN(ReferenceData!$C$21),"",ReferenceData!$C$21),"") -> PR005 | D21: =IFERROR(IF(0=LEN(ReferenceData!$D$21),"",ReferenceData!$D$21),"") -> PX_LAST | E21: =IFERROR(IF(0=LEN(ReferenceData!$E$21),"",ReferenceData!$E$21),"") -> Dynamic | F21: =IFERROR(IF(0=LEN(ReferenceData!$AG$21),"",ReferenceData!$AG$21),"") -> 446614 | G21: =IFERROR(IF(0=LEN(ReferenceData!$AF$21),"",ReferenceData!$AF$21),"") -> 480491 | H21: =IFERROR(IF(0=LEN(ReferenceData!$AE$21),"",ReferenceData!$AE$21),"") -> 493647 | I21: =IFERROR(IF(0=LEN(ReferenceData!$AD$21),"",ReferenceData!$AD$21),"") -> 496974 | J21: =IFERROR(IF(0=LEN(ReferenceData!$AC$21),"",ReferenceData!$AC$21),"") -> 550898 | K21: =IFERROR(IF(0=LEN(ReferenceData!$AB$21),"",ReferenceData!$AB$21),"") -> 612615 | L21: =IFERROR(IF(0=LEN(ReferenceData!$AA$21),"",ReferenceData!$AA$21),"") -> 657527 | M21: =IFERROR(IF(0=LEN(ReferenceData!$Z$21),"",ReferenceData!$Z$21),"") -> 698891 | N21: =IFERROR(IF(0=LEN(ReferenceData!$Y$21),"",ReferenceData!$Y$21),"") -> 807838 | O21: =IFERROR(IF(0=LEN(ReferenceData!$X$21),"",ReferenceData!$X$21),"") -> 853632 | P21: =IFERROR(IF(0=LEN(ReferenceData!$W$21),"",ReferenceData!$W$21),"") -> 988515 | Q21: =IFERROR(IF(0=LEN(ReferenceData!$V$21),"",ReferenceData!$V$21),"") -> 1097720 | R21: =IFERROR(IF(0=LEN(ReferenceData!$U$21),"",ReferenceData!$U$21),"") -> 1157300 | S21: =IFERROR(IF(0=LEN(ReferenceData!$T$21),"",ReferenceData!$T$21),"") -> 1211570 | T21: =IFERROR(IF(0=LEN(ReferenceData!$S$21),"",ReferenceData!$S$21),"") -> 1396040 | U21: =IFERROR(IF(0=LEN(ReferenceData!$R$21),"",ReferenceData!$R$21),"") -> 1535640 | V21: =IFERROR(IF(0=LEN(ReferenceData!$Q$21),"",ReferenceData!$Q$21),"") -> 1678660 | W21: =IFERROR(IF(0=LEN(ReferenceData!$P$21),"",ReferenceData!$P$21),"") -> 1869390 | X21: =IFERROR(IF(0=LEN(ReferenceData!$O$21),"",ReferenceData!$O$21),"") -> 2015360 | Y21: =IFERROR(IF(0=LEN(ReferenceData!$N$21),"",ReferenceData!$N$21),"") -> 2119510 | Z21: =IFERROR(IF(0=LEN(ReferenceData!$M$21),"",ReferenceData!$M$21),"") -> 1978470 | AA21: =IFERROR(IF(0=LEN(ReferenceData!$L$21),"",ReferenceData!$L$21),"") -> 2038150 | AB21: =IFERROR(IF(0=LEN(ReferenceData!$K$21),"",ReferenceData!$K$21),"") -> 2097600 | AC21: =IFERROR(IF(0=LEN(ReferenceData!$J$21),"",ReferenceData!$J$21),"") -> 2245730 | AD21: =IFERROR(IF(0=LEN(ReferenceData!$I$21),"",ReferenceData!$I$21),"") -> 2333210 | AE21: =IFERROR(IF(0=LEN(ReferenceData!$H$21),"",ReferenceData!$H$21),"") -> 2468000 | AF21: =IFERROR(IF(0=LEN(ReferenceData!$G$21),"",ReferenceData!$G$21),"") -> 2629560 | AG21: =IFERROR(IF(0=LEN(ReferenceData!$F$21),"",ReferenceData!$F$21),"") -> 2828240
A22: =IFERROR(IF(0=LEN(ReferenceData!$A$22),"",ReferenceData!$A$22),"") -> Passive Fixed Income Mutual Funds | B22: =IFERROR(IF(0=LEN(ReferenceData!$B$22),"",ReferenceData!$B$22),"") -> .BIAMPTF G Index | C22: =IFERROR(IF(0=LEN(ReferenceData!$C$22),"",ReferenceData!$C$22),"") -> PR005 | D22: =IFERROR(IF(0=LEN(ReferenceData!$D$22),"",ReferenceData!$D$22),"") -> PX_LAST | E22: =IFERROR(IF(0=LEN(ReferenceData!$E$22),"",ReferenceData!$E$22),"") -> Dynamic | F22: =IFERROR(IF(0=LEN(ReferenceData!$AG$22),"",ReferenceData!$AG$22),"") -> 220871 | G22: =IFERROR(IF(0=LEN(ReferenceData!$AF$22),"",ReferenceData!$AF$22),"") -> 237330 | H22: =IFERROR(IF(0=LEN(ReferenceData!$AE$22),"",ReferenceData!$AE$22),"") -> 249403 | I22: =IFERROR(IF(0=LEN(ReferenceData!$AD$22),"",ReferenceData!$AD$22),"") -> 256712 | J22: =IFERROR(IF(0=LEN(ReferenceData!$AC$22),"",ReferenceData!$AC$22),"") -> 285168 | K22: =IFERROR(IF(0=LEN(ReferenceData!$AB$22),"",ReferenceData!$AB$22),"") -> 317917 | L22: =IFERROR(IF(0=LEN(ReferenceData!$AA$22),"",ReferenceData!$AA$22),"") -> 344167 | M22: =IFERROR(IF(0=LEN(ReferenceData!$Z$22),"",ReferenceData!$Z$22),"") -> 361081 | N22: =IFERROR(IF(0=LEN(ReferenceData!$Y$22),"",ReferenceData!$Y$22),"") -> 407902 | O22: =IFERROR(IF(0=LEN(ReferenceData!$X$22),"",ReferenceData!$X$22),"") -> 428727 | P22: =IFERROR(IF(0=LEN(ReferenceData!$W$22),"",ReferenceData!$W$22),"") -> 491499 | Q22: =IFERROR(IF(0=LEN(ReferenceData!$V$22),"",ReferenceData!$V$22),"") -> 550444 | R22: =IFERROR(IF(0=LEN(ReferenceData!$U$22),"",ReferenceData!$U$22),"") -> 584933 | S22: =IFERROR(IF(0=LEN(ReferenceData!$T$22),"",ReferenceData!$T$22),"") -> 607361 | T22: =IFERROR(IF(0=LEN(ReferenceData!$S$22),"",ReferenceData!$S$22),"") -> 698961 | U22: =IFERROR(IF(0=LEN(ReferenceData!$R$22),"",ReferenceData!$R$22),"") -> 762238 | V22: =IFERROR(IF(0=LEN(ReferenceData!$Q$22),"",ReferenceData!$Q$22),"") -> 798710 | W22: =IFERROR(IF(0=LEN(ReferenceData!$P$22),"",ReferenceData!$P$22),"") -> 885143 | X22: =IFERROR(IF(0=LEN(ReferenceData!$O$22),"",ReferenceData!$O$22),"") -> 952353 | Y22: =IFERROR(IF(0=LEN(ReferenceData!$N$22),"",ReferenceData!$N$22),"") -> 988790 | Z22: =IFERROR(IF(0=LEN(ReferenceData!$M$22),"",ReferenceData!$M$22),"") -> 894269 | AA22: =IFERROR(IF(0=LEN(ReferenceData!$L$22),"",ReferenceData!$L$22),"") -> 873651 | AB22: =IFERROR(IF(0=LEN(ReferenceData!$K$22),"",ReferenceData!$K$22),"") -> 839082 | AC22: =IFERROR(IF(0=LEN(ReferenceData!$J$22),"",ReferenceData!$J$22),"") -> 894646 | AD22: =IFERROR(IF(0=LEN(ReferenceData!$I$22),"",ReferenceData!$I$22),"") -> 923523 | AE22: =IFERROR(IF(0=LEN(ReferenceData!$H$22),"",ReferenceData!$H$22),"") -> 959961 | AF22: =IFERROR(IF(0=LEN(ReferenceData!$G$22),"",ReferenceData!$G$22),"") -> 996272 | AG22: =IFERROR(IF(0=LEN(ReferenceData!$F$22),"",ReferenceData!$F$22),"") -> 1064430
A23: =IFERROR(IF(0=LEN(ReferenceData!$A$23),"",ReferenceData!$A$23),"") -> Passive Fixed Income ETFs | B23: =IFERROR(IF(0=LEN(ReferenceData!$B$23),"",ReferenceData!$B$23),"") | C23: =IFERROR(IF(0=LEN(ReferenceData!$C$23),"",ReferenceData!$C$23),"") | D23: =IFERROR(IF(0=LEN(ReferenceData!$D$23),"",ReferenceData!$D$23),"") | E23: =IFERROR(IF(0=LEN(ReferenceData!$E$23),"",ReferenceData!$E$23),"") -> Expression | F23: =IFERROR(IF(0=LEN(ReferenceData!$AG$23),"",ReferenceData!$AG$23),"") -> 225743 | G23: =IFERROR(IF(0=LEN(ReferenceData!$AF$23),"",ReferenceData!$AF$23),"") -> 243161 | H23: =IFERROR(IF(0=LEN(ReferenceData!$AE$23),"",ReferenceData!$AE$23),"") -> 244244 | I23: =IFERROR(IF(0=LEN(ReferenceData!$AD$23),"",ReferenceData!$AD$23),"") -> 240262 | J23: =IFERROR(IF(0=LEN(ReferenceData!$AC$23),"",ReferenceData!$AC$23),"") -> 265730 | K23: =IFERROR(IF(0=LEN(ReferenceData!$AB$23),"",ReferenceData!$AB$23),"") -> 294698 | L23: =IFERROR(IF(0=LEN(ReferenceData!$AA$23),"",ReferenceData!$AA$23),"") -> 313360 | M23: =IFERROR(IF(0=LEN(ReferenceData!$Z$23),"",ReferenceData!$Z$23),"") -> 337810 | N23: =IFERROR(IF(0=LEN(ReferenceData!$Y$23),"",ReferenceData!$Y$23),"") -> 399936 | O23: =IFERROR(IF(0=LEN(ReferenceData!$X$23),"",ReferenceData!$X$23),"") -> 424905 | P23: =IFERROR(IF(0=LEN(ReferenceData!$W$23),"",ReferenceData!$W$23),"") -> 497016 | Q23: =IFERROR(IF(0=LEN(ReferenceData!$V$23),"",ReferenceData!$V$23),"") -> 547276 | R23: =IFERROR(IF(0=LEN(ReferenceData!$U$23),"",ReferenceData!$U$23),"") -> 572367 | S23: =IFERROR(IF(0=LEN(ReferenceData!$T$23),"",ReferenceData!$T$23),"") -> 604209 | T23: =IFERROR(IF(0=LEN(ReferenceData!$S$23),"",ReferenceData!$S$23),"") -> 697079 | U23: =IFERROR(IF(0=LEN(ReferenceData!$R$23),"",ReferenceData!$R$23),"") -> 773402 | V23: =IFERROR(IF(0=LEN(ReferenceData!$Q$23),"",ReferenceData!$Q$23),"") -> 879950 | W23: =IFERROR(IF(0=LEN(ReferenceData!$P$23),"",ReferenceData!$P$23),"") -> 984247 | X23: =IFERROR(IF(0=LEN(ReferenceData!$O$23),"",ReferenceData!$O$23),"") -> 1063007 | Y23: =IFERROR(IF(0=LEN(ReferenceData!$N$23),"",ReferenceData!$N$23),"") -> 1130720 | Z23: =IFERROR(IF(0=LEN(ReferenceData!$M$23),"",ReferenceData!$M$23),"") -> 1084201 | AA23: =IFERROR(IF(0=LEN(ReferenceData!$L$23),"",ReferenceData!$L$23),"") -> 1164499 | AB23: =IFERROR(IF(0=LEN(ReferenceData!$K$23),"",ReferenceData!$K$23),"") -> 1258518 | AC23: =IFERROR(IF(0=LEN(ReferenceData!$J$23),"",ReferenceData!$J$23),"") -> 1351084 | AD23: =IFERROR(IF(0=LEN(ReferenceData!$I$23),"",ReferenceData!$I$23),"") -> 1409687 | AE23: =IFERROR(IF(0=LEN(ReferenceData!$H$23),"",ReferenceData!$H$23),"") -> 1508039 | AF23: =IFERROR(IF(0=LEN(ReferenceData!$G$23),"",ReferenceData!$G$23),"") -> 1633288 | AG23: =IFERROR(IF(0=LEN(ReferenceData!$F$23),"",ReferenceData!$F$23),"") -> 1763810
A24: =IFERROR(IF(0=LEN(ReferenceData!$A$24),"",ReferenceData!$A$24),"") -> Active Fixed Income | B24: =IFERROR(IF(0=LEN(ReferenceData!$B$24),"",ReferenceData!$B$24),"") -> .BIATATF G Index | C24: =IFERROR(IF(0=LEN(ReferenceData!$C$24),"",ReferenceData!$C$24),"") -> PR005 | D24: =IFERROR(IF(0=LEN(ReferenceData!$D$24),"",ReferenceData!$D$24),"") -> PX_LAST | E24: =IFERROR(IF(0=LEN(ReferenceData!$E$24),"",ReferenceData!$E$24),"") -> Dynamic | F24: =IFERROR(IF(0=LEN(ReferenceData!$AG$24),"",ReferenceData!$AG$24),"") -> 2380370 | G24: =IFERROR(IF(0=LEN(ReferenceData!$AF$24),"",ReferenceData!$AF$24),"") -> 2617190 | H24: =IFERROR(IF(0=LEN(ReferenceData!$AE$24),"",ReferenceData!$AE$24),"") -> 2617750 | I24: =IFERROR(IF(0=LEN(ReferenceData!$AD$24),"",ReferenceData!$AD$24),"") -> 2562880 | J24: =IFERROR(IF(0=LEN(ReferenceData!$AC$24),"",ReferenceData!$AC$24),"") -> 2734580 | K24: =IFERROR(IF(0=LEN(ReferenceData!$AB$24),"",ReferenceData!$AB$24),"") -> 2695730 | L24: =IFERROR(IF(0=LEN(ReferenceData!$AA$24),"",ReferenceData!$AA$24),"") -> 2712500 | M24: =IFERROR(IF(0=LEN(ReferenceData!$Z$24),"",ReferenceData!$Z$24),"") -> 2636310 | N24: =IFERROR(IF(0=LEN(ReferenceData!$Y$24),"",ReferenceData!$Y$24),"") -> 2811760 | O24: =IFERROR(IF(0=LEN(ReferenceData!$X$24),"",ReferenceData!$X$24),"") -> 2814430 | P24: =IFERROR(IF(0=LEN(ReferenceData!$W$24),"",ReferenceData!$W$24),"") -> 3000070 | Q24: =IFERROR(IF(0=LEN(ReferenceData!$V$24),"",ReferenceData!$V$24),"") -> 3105680 | R24: =IFERROR(IF(0=LEN(ReferenceData!$U$24),"",ReferenceData!$U$24),"") -> 3166780 | S24: =IFERROR(IF(0=LEN(ReferenceData!$T$24),"",ReferenceData!$T$24),"") -> 3103490 | T24: =IFERROR(IF(0=LEN(ReferenceData!$S$24),"",ReferenceData!$S$24),"") -> 3341160 | U24: =IFERROR(IF(0=LEN(ReferenceData!$R$24),"",ReferenceData!$R$24),"") -> 3656510 | V24: =IFERROR(IF(0=LEN(ReferenceData!$Q$24),"",ReferenceData!$Q$24),"") -> 3715940 | W24: =IFERROR(IF(0=LEN(ReferenceData!$P$24),"",ReferenceData!$P$24),"") -> 4130030 | X24: =IFERROR(IF(0=LEN(ReferenceData!$O$24),"",ReferenceData!$O$24),"") -> 4407500 | Y24: =IFERROR(IF(0=LEN(ReferenceData!$N$24),"",ReferenceData!$N$24),"") -> 4525540 | Z24: =IFERROR(IF(0=LEN(ReferenceData!$M$24),"",ReferenceData!$M$24),"") -> 3839850 | AA24: =IFERROR(IF(0=LEN(ReferenceData!$L$24),"",ReferenceData!$L$24),"") -> 3572680 | AB24: =IFERROR(IF(0=LEN(ReferenceData!$K$24),"",ReferenceData!$K$24),"") -> 3655970 | AC24: =IFERROR(IF(0=LEN(ReferenceData!$J$24),"",ReferenceData!$J$24),"") -> 3757540 | AD24: =IFERROR(IF(0=LEN(ReferenceData!$I$24),"",ReferenceData!$I$24),"") -> 3898650 | AE24: =IFERROR(IF(0=LEN(ReferenceData!$H$24),"",ReferenceData!$H$24),"") -> 4104320 | AF24: =IFERROR(IF(0=LEN(ReferenceData!$G$24),"",ReferenceData!$G$24),"") -> 4256020 | AG24: =IFERROR(IF(0=LEN(ReferenceData!$F$24),"",ReferenceData!$F$24),"") -> 4516140
A25: =IFERROR(IF(0=LEN(ReferenceData!$A$25),"",ReferenceData!$A$25),"") -> Active Fixed Income Mutual Funds | B25: =IFERROR(IF(0=LEN(ReferenceData!$B$25),"",ReferenceData!$B$25),"") -> .BIAMATF G Index | C25: =IFERROR(IF(0=LEN(ReferenceData!$C$25),"",ReferenceData!$C$25),"") -> PR005 | D25: =IFERROR(IF(0=LEN(ReferenceData!$D$25),"",ReferenceData!$D$25),"") -> PX_LAST | E25: =IFERROR(IF(0=LEN(ReferenceData!$E$25),"",ReferenceData!$E$25),"") -> Dynamic | F25: =IFERROR(IF(0=LEN(ReferenceData!$AG$25),"",ReferenceData!$AG$25),"") -> 2374510 | G25: =IFERROR(IF(0=LEN(ReferenceData!$AF$25),"",ReferenceData!$AF$25),"") -> 2614920 | H25: =IFERROR(IF(0=LEN(ReferenceData!$AE$25),"",ReferenceData!$AE$25),"") -> 2606430 | I25: =IFERROR(IF(0=LEN(ReferenceData!$AD$25),"",ReferenceData!$AD$25),"") -> 2551860 | J25: =IFERROR(IF(0=LEN(ReferenceData!$AC$25),"",ReferenceData!$AC$25),"") -> 2722160 | K25: =IFERROR(IF(0=LEN(ReferenceData!$AB$25),"",ReferenceData!$AB$25),"") -> 2684290 | L25: =IFERROR(IF(0=LEN(ReferenceData!$AA$25),"",ReferenceData!$AA$25),"") -> 2699240 | M25: =IFERROR(IF(0=LEN(ReferenceData!$Z$25),"",ReferenceData!$Z$25),"") -> 2619830 | N25: =IFERROR(IF(0=LEN(ReferenceData!$Y$25),"",ReferenceData!$Y$25),"") -> 2792430 | O25: =IFERROR(IF(0=LEN(ReferenceData!$X$25),"",ReferenceData!$X$25),"") -> 2791210 | P25: =IFERROR(IF(0=LEN(ReferenceData!$W$25),"",ReferenceData!$W$25),"") -> 2971380 | Q25: =IFERROR(IF(0=LEN(ReferenceData!$V$25),"",ReferenceData!$V$25),"") -> 3071860 | R25: =IFERROR(IF(0=LEN(ReferenceData!$U$25),"",ReferenceData!$U$25),"") -> 3125610 | S25: =IFERROR(IF(0=LEN(ReferenceData!$T$25),"",ReferenceData!$T$25),"") -> 3049260 | T25: =IFERROR(IF(0=LEN(ReferenceData!$S$25),"",ReferenceData!$S$25),"") -> 3277930 | U25: =IFERROR(IF(0=LEN(ReferenceData!$R$25),"",ReferenceData!$R$25),"") -> 3577620 | V25: =IFERROR(IF(0=LEN(ReferenceData!$Q$25),"",ReferenceData!$Q$25),"") -> 3626530 | W25: =IFERROR(IF(0=LEN(ReferenceData!$P$25),"",ReferenceData!$P$25),"") -> 4022850 | X25: =IFERROR(IF(0=LEN(ReferenceData!$O$25),"",ReferenceData!$O$25),"") -> 4281200 | Y25: =IFERROR(IF(0=LEN(ReferenceData!$N$25),"",ReferenceData!$N$25),"") -> 4387730 | Z25: =IFERROR(IF(0=LEN(ReferenceData!$M$25),"",ReferenceData!$M$25),"") -> 3703030 | AA25: =IFERROR(IF(0=LEN(ReferenceData!$L$25),"",ReferenceData!$L$25),"") -> 3431240 | AB25: =IFERROR(IF(0=LEN(ReferenceData!$K$25),"",ReferenceData!$K$25),"") -> 3504410 | AC25: =IFERROR(IF(0=LEN(ReferenceData!$J$25),"",ReferenceData!$J$25),"") -> 3579620 | AD25: =IFERROR(IF(0=LEN(ReferenceData!$I$25),"",ReferenceData!$I$25),"") -> 3680030 | AE25: =IFERROR(IF(0=LEN(ReferenceData!$H$25),"",ReferenceData!$H$25),"") -> 3821480 | AF25: =IFERROR(IF(0=LEN(ReferenceData!$G$25),"",ReferenceData!$G$25),"") -> 3908860 | AG25: =IFERROR(IF(0=LEN(ReferenceData!$F$25),"",ReferenceData!$F$25),"") -> 4098570
A26: =IFERROR(IF(0=LEN(ReferenceData!$A$26),"",ReferenceData!$A$26),"") -> Active Fixed Income ETFs | B26: =IFERROR(IF(0=LEN(ReferenceData!$B$26),"",ReferenceData!$B$26),"") | C26: =IFERROR(IF(0=LEN(ReferenceData!$C$26),"",ReferenceData!$C$26),"") | D26: =IFERROR(IF(0=LEN(ReferenceData!$D$26),"",ReferenceData!$D$26),"") | E26: =IFERROR(IF(0=LEN(ReferenceData!$E$26),"",ReferenceData!$E$26),"") -> Expression | F26: =IFERROR(IF(0=LEN(ReferenceData!$AG$26),"",ReferenceData!$AG$26),"") -> 5860 | G26: =IFERROR(IF(0=LEN(ReferenceData!$AF$26),"",ReferenceData!$AF$26),"") -> 2270 | H26: =IFERROR(IF(0=LEN(ReferenceData!$AE$26),"",ReferenceData!$AE$26),"") -> 11320 | I26: =IFERROR(IF(0=LEN(ReferenceData!$AD$26),"",ReferenceData!$AD$26),"") -> 11020 | J26: =IFERROR(IF(0=LEN(ReferenceData!$AC$26),"",ReferenceData!$AC$26),"") -> 12420 | K26: =IFERROR(IF(0=LEN(ReferenceData!$AB$26),"",ReferenceData!$AB$26),"") -> 11440 | L26: =IFERROR(IF(0=LEN(ReferenceData!$AA$26),"",ReferenceData!$AA$26),"") -> 13260 | M26: =IFERROR(IF(0=LEN(ReferenceData!$Z$26),"",ReferenceData!$Z$26),"") -> 16480 | N26: =IFERROR(IF(0=LEN(ReferenceData!$Y$26),"",ReferenceData!$Y$26),"") -> 19330 | O26: =IFERROR(IF(0=LEN(ReferenceData!$X$26),"",ReferenceData!$X$26),"") -> 23220 | P26: =IFERROR(IF(0=LEN(ReferenceData!$W$26),"",ReferenceData!$W$26),"") -> 28690 | Q26: =IFERROR(IF(0=LEN(ReferenceData!$V$26),"",ReferenceData!$V$26),"") -> 33820 | R26: =IFERROR(IF(0=LEN(ReferenceData!$U$26),"",ReferenceData!$U$26),"") -> 41170 | S26: =IFERROR(IF(0=LEN(ReferenceData!$T$26),"",ReferenceData!$T$26),"") -> 54230 | T26: =IFERROR(IF(0=LEN(ReferenceData!$S$26),"",ReferenceData!$S$26),"") -> 63230 | U26: =IFERROR(IF(0=LEN(ReferenceData!$R$26),"",ReferenceData!$R$26),"") -> 78890 | V26: =IFERROR(IF(0=LEN(ReferenceData!$Q$26),"",ReferenceData!$Q$26),"") -> 89410 | W26: =IFERROR(IF(0=LEN(ReferenceData!$P$26),"",ReferenceData!$P$26),"") -> 107180 | X26: =IFERROR(IF(0=LEN(ReferenceData!$O$26),"",ReferenceData!$O$26),"") -> 126300 | Y26: =IFERROR(IF(0=LEN(ReferenceData!$N$26),"",ReferenceData!$N$26),"") -> 137810 | Z26: =IFERROR(IF(0=LEN(ReferenceData!$M$26),"",ReferenceData!$M$26),"") -> 136820 | AA26: =IFERROR(IF(0=LEN(ReferenceData!$L$26),"",ReferenceData!$L$26),"") -> 141440 | AB26: =IFERROR(IF(0=LEN(ReferenceData!$K$26),"",ReferenceData!$K$26),"") -> 151560 | AC26: =IFERROR(IF(0=LEN(ReferenceData!$J$26),"",ReferenceData!$J$26),"") -> 177920 | AD26: =IFERROR(IF(0=LEN(ReferenceData!$I$26),"",ReferenceData!$I$26),"") -> 218620 | AE26: =IFERROR(IF(0=LEN(ReferenceData!$H$26),"",ReferenceData!$H$26),"") -> 282840 | AF26: =IFERROR(IF(0=LEN(ReferenceData!$G$26),"",ReferenceData!$G$26),"") -> 347160 | AG26: =IFERROR(IF(0=LEN(ReferenceData!$F$26),"",ReferenceData!$F$26),"") -> 417570
A27: =IFERROR(IF(0=LEN(ReferenceData!$A$27),"",ReferenceData!$A$27),"") -> All Equity Funds | B27: =IFERROR(IF(0=LEN(ReferenceData!$B$27),"",ReferenceData!$B$27),"") | C27: =IFERROR(IF(0=LEN(ReferenceData!$C$27),"",ReferenceData!$C$27),"") | D27: =IFERROR(IF(0=LEN(ReferenceData!$D$27),"",ReferenceData!$D$27),"") | E27: =IFERROR(IF(0=LEN(ReferenceData!$E$27),"",ReferenceData!$E$27),"") -> Sum | F27: =IFERROR(IF(0=LEN(ReferenceData!$AG$27),"",ReferenceData!$AG$27),"") -> 5092340 | G27: =IFERROR(IF(0=LEN(ReferenceData!$AF$27),"",ReferenceData!$AF$27),"") -> 5603960 | H27: =IFERROR(IF(0=LEN(ReferenceData!$AE$27),"",ReferenceData!$AE$27),"") -> 6422770 | I27: =IFERROR(IF(0=LEN(ReferenceData!$AD$27),"",ReferenceData!$AD$27),"") -> 7626980 | J27: =IFERROR(IF(0=LEN(ReferenceData!$AC$27),"",ReferenceData!$AC$27),"") -> 8356000 | K27: =IFERROR(IF(0=LEN(ReferenceData!$AB$27),"",ReferenceData!$AB$27),"") -> 8488620 | L27: =IFERROR(IF(0=LEN(ReferenceData!$AA$27),"",ReferenceData!$AA$27),"") -> 8919470 | M27: =IFERROR(IF(0=LEN(ReferenceData!$Z$27),"",ReferenceData!$Z$27),"") -> 8466820 | N27: =IFERROR(IF(0=LEN(ReferenceData!$Y$27),"",ReferenceData!$Y$27),"") -> 8726980 | O27: =IFERROR(IF(0=LEN(ReferenceData!$X$27),"",ReferenceData!$X$27),"") -> 9345470 | P27: =IFERROR(IF(0=LEN(ReferenceData!$W$27),"",ReferenceData!$W$27),"") -> 10557740 | Q27: =IFERROR(IF(0=LEN(ReferenceData!$V$27),"",ReferenceData!$V$27),"") -> 11768580 | R27: =IFERROR(IF(0=LEN(ReferenceData!$U$27),"",ReferenceData!$U$27),"") -> 12052510 | S27: =IFERROR(IF(0=LEN(ReferenceData!$T$27),"",ReferenceData!$T$27),"") -> 10701650 | T27: =IFERROR(IF(0=LEN(ReferenceData!$S$27),"",ReferenceData!$S$27),"") -> 12436480 | U27: =IFERROR(IF(0=LEN(ReferenceData!$R$27),"",ReferenceData!$R$27),"") -> 13649280 | V27: =IFERROR(IF(0=LEN(ReferenceData!$Q$27),"",ReferenceData!$Q$27),"") -> 12955210 | W27: =IFERROR(IF(0=LEN(ReferenceData!$P$27),"",ReferenceData!$P$27),"") -> 15744970 | X27: =IFERROR(IF(0=LEN(ReferenceData!$O$27),"",ReferenceData!$O$27),"") -> 18009070 | Y27: =IFERROR(IF(0=LEN(ReferenceData!$N$27),"",ReferenceData!$N$27),"") -> 19086040 | Z27: =IFERROR(IF(0=LEN(ReferenceData!$M$27),"",ReferenceData!$M$27),"") -> 15231930 | AA27: =IFERROR(IF(0=LEN(ReferenceData!$L$27),"",ReferenceData!$L$27),"") -> 15431320 | AB27: =IFERROR(IF(0=LEN(ReferenceData!$K$27),"",ReferenceData!$K$27),"") -> 17290980 | AC27: =IFERROR(IF(0=LEN(ReferenceData!$J$27),"",ReferenceData!$J$27),"") -> 18593930 | AD27: =IFERROR(IF(0=LEN(ReferenceData!$I$27),"",ReferenceData!$I$27),"") -> 20835820 | AE27: =IFERROR(IF(0=LEN(ReferenceData!$H$27),"",ReferenceData!$H$27),"") -> 22132960 | AF27: =IFERROR(IF(0=LEN(ReferenceData!$G$27),"",ReferenceData!$G$27),"") -> 23719090 | AG27: =IFERROR(IF(0=LEN(ReferenceData!$F$27),"",ReferenceData!$F$27),"") -> 25530950
A28: =IFERROR(IF(0=LEN(ReferenceData!$A$28),"",ReferenceData!$A$28),"") -> Passive Equity | B28: =IFERROR(IF(0=LEN(ReferenceData!$B$28),"",ReferenceData!$B$28),"") -> .BIATPTE G Index | C28: =IFERROR(IF(0=LEN(ReferenceData!$C$28),"",ReferenceData!$C$28),"") -> PR005 | D28: =IFERROR(IF(0=LEN(ReferenceData!$D$28),"",ReferenceData!$D$28),"") -> PX_LAST | E28: =IFERROR(IF(0=LEN(ReferenceData!$E$28),"",ReferenceData!$E$28),"") -> Dynamic | F28: =IFERROR(IF(0=LEN(ReferenceData!$AG$28),"",ReferenceData!$AG$28),"") -> 1642830 | G28: =IFERROR(IF(0=LEN(ReferenceData!$AF$28),"",ReferenceData!$AF$28),"") -> 1850680 | H28: =IFERROR(IF(0=LEN(ReferenceData!$AE$28),"",ReferenceData!$AE$28),"") -> 2164890 | I28: =IFERROR(IF(0=LEN(ReferenceData!$AD$28),"",ReferenceData!$AD$28),"") -> 2621530 | J28: =IFERROR(IF(0=LEN(ReferenceData!$AC$28),"",ReferenceData!$AC$28),"") -> 2922420 | K28: =IFERROR(IF(0=LEN(ReferenceData!$AB$28),"",ReferenceData!$AB$28),"") -> 3124530 | L28: =IFERROR(IF(0=LEN(ReferenceData!$AA$28),"",ReferenceData!$AA$28),"") -> 3365620 | M28: =IFERROR(IF(0=LEN(ReferenceData!$Z$28),"",ReferenceData!$Z$28),"") -> 3303510 | N28: =IFERROR(IF(0=LEN(ReferenceData!$Y$28),"",ReferenceData!$Y$28),"") -> 3506500 | O28: =IFERROR(IF(0=LEN(ReferenceData!$X$28),"",ReferenceData!$X$28),"") -> 3957690 | P28: =IFERROR(IF(0=LEN(ReferenceData!$W$28),"",ReferenceData!$W$28),"") -> 4629020 | Q28: =IFERROR(IF(0=LEN(ReferenceData!$V$28),"",ReferenceData!$V$28),"") -> 5348720 | R28: =IFERROR(IF(0=LEN(ReferenceData!$U$28),"",ReferenceData!$U$28),"") -> 5524350 | S28: =IFERROR(IF(0=LEN(ReferenceData!$T$28),"",ReferenceData!$T$28),"") -> 5173730 | T28: =IFERROR(IF(0=LEN(ReferenceData!$S$28),"",ReferenceData!$S$28),"") -> 6125590 | U28: =IFERROR(IF(0=LEN(ReferenceData!$R$28),"",ReferenceData!$R$28),"") -> 6773630 | V28: =IFERROR(IF(0=LEN(ReferenceData!$Q$28),"",ReferenceData!$Q$28),"") -> 6407790 | W28: =IFERROR(IF(0=LEN(ReferenceData!$P$28),"",ReferenceData!$P$28),"") -> 7905190 | X28: =IFERROR(IF(0=LEN(ReferenceData!$O$28),"",ReferenceData!$O$28),"") -> 9256220 | Y28: =IFERROR(IF(0=LEN(ReferenceData!$N$28),"",ReferenceData!$N$28),"") -> 10129600 | Z28: =IFERROR(IF(0=LEN(ReferenceData!$M$28),"",ReferenceData!$M$28),"") -> 8325310 | AA28: =IFERROR(IF(0=LEN(ReferenceData!$L$28),"",ReferenceData!$L$28),"") -> 8602860 | AB28: =IFERROR(IF(0=LEN(ReferenceData!$K$28),"",ReferenceData!$K$28),"") -> 9751170 | AC28: =IFERROR(IF(0=LEN(ReferenceData!$J$28),"",ReferenceData!$J$28),"") -> 10679200 | AD28: =IFERROR(IF(0=LEN(ReferenceData!$I$28),"",ReferenceData!$I$28),"") -> 12130800 | AE28: =IFERROR(IF(0=LEN(ReferenceData!$H$28),"",ReferenceData!$H$28),"") -> 13276200 | AF28: =IFERROR(IF(0=LEN(ReferenceData!$G$28),"",ReferenceData!$G$28),"") -> 14369200 | AG28: =IFERROR(IF(0=LEN(ReferenceData!$F$28),"",ReferenceData!$F$28),"") -> 15617700
A29: =IFERROR(IF(0=LEN(ReferenceData!$A$29),"",ReferenceData!$A$29),"") -> Passive Equity Mutual Funds | B29: =IFERROR(IF(0=LEN(ReferenceData!$B$29),"",ReferenceData!$B$29),"") -> .BIAMPTE G Index | C29: =IFERROR(IF(0=LEN(ReferenceData!$C$29),"",ReferenceData!$C$29),"") -> PR005 | D29: =IFERROR(IF(0=LEN(ReferenceData!$D$29),"",ReferenceData!$D$29),"") -> PX_LAST | E29: =IFERROR(IF(0=LEN(ReferenceData!$E$29),"",ReferenceData!$E$29),"") -> Dynamic | F29: =IFERROR(IF(0=LEN(ReferenceData!$AG$29),"",ReferenceData!$AG$29),"") -> 834945 | G29: =IFERROR(IF(0=LEN(ReferenceData!$AF$29),"",ReferenceData!$AF$29),"") -> 921973 | H29: =IFERROR(IF(0=LEN(ReferenceData!$AE$29),"",ReferenceData!$AE$29),"") -> 1078760 | I29: =IFERROR(IF(0=LEN(ReferenceData!$AD$29),"",ReferenceData!$AD$29),"") -> 1293670 | J29: =IFERROR(IF(0=LEN(ReferenceData!$AC$29),"",ReferenceData!$AC$29),"") -> 1460530 | K29: =IFERROR(IF(0=LEN(ReferenceData!$AB$29),"",ReferenceData!$AB$29),"") -> 1554910 | L29: =IFERROR(IF(0=LEN(ReferenceData!$AA$29),"",ReferenceData!$AA$29),"") -> 1666640 | M29: =IFERROR(IF(0=LEN(ReferenceData!$Z$29),"",ReferenceData!$Z$29),"") -> 1661420 | N29: =IFERROR(IF(0=LEN(ReferenceData!$Y$29),"",ReferenceData!$Y$29),"") -> 1785370 | O29: =IFERROR(IF(0=LEN(ReferenceData!$X$29),"",ReferenceData!$X$29),"") -> 1949350 | P29: =IFERROR(IF(0=LEN(ReferenceData!$W$29),"",ReferenceData!$W$29),"") -> 2289600 | Q29: =IFERROR(IF(0=LEN(ReferenceData!$V$29),"",ReferenceData!$V$29),"") -> 2589410 | R29: =IFERROR(IF(0=LEN(ReferenceData!$U$29),"",ReferenceData!$U$29),"") -> 2700240 | S29: =IFERROR(IF(0=LEN(ReferenceData!$T$29),"",ReferenceData!$T$29),"") -> 2530790 | T29: =IFERROR(IF(0=LEN(ReferenceData!$S$29),"",ReferenceData!$S$29),"") -> 3036650 | U29: =IFERROR(IF(0=LEN(ReferenceData!$R$29),"",ReferenceData!$R$29),"") -> 3328280 | V29: =IFERROR(IF(0=LEN(ReferenceData!$Q$29),"",ReferenceData!$Q$29),"") -> 3147480 | W29: =IFERROR(IF(0=LEN(ReferenceData!$P$29),"",ReferenceData!$P$29),"") -> 3739780 | X29: =IFERROR(IF(0=LEN(ReferenceData!$O$29),"",ReferenceData!$O$29),"") -> 4234630 | Y29: =IFERROR(IF(0=LEN(ReferenceData!$N$29),"",ReferenceData!$N$29),"") -> 4567400 | Z29: =IFERROR(IF(0=LEN(ReferenceData!$M$29),"",ReferenceData!$M$29),"") -> 3679920 | AA29: =IFERROR(IF(0=LEN(ReferenceData!$L$29),"",ReferenceData!$L$29),"") -> 3760390 | AB29: =IFERROR(IF(0=LEN(ReferenceData!$K$29),"",ReferenceData!$K$29),"") -> 4313160 | AC29: =IFERROR(IF(0=LEN(ReferenceData!$J$29),"",ReferenceData!$J$29),"") -> 4646020 | AD29: =IFERROR(IF(0=LEN(ReferenceData!$I$29),"",ReferenceData!$I$29),"") -> 5220670 | AE29: =IFERROR(IF(0=LEN(ReferenceData!$H$29),"",ReferenceData!$H$29),"") -> 5581050 | AF29: =IFERROR(IF(0=LEN(ReferenceData!$G$29),"",ReferenceData!$G$29),"") -> 5989360 | AG29: =IFERROR(IF(0=LEN(ReferenceData!$F$29),"",ReferenceData!$F$29),"") -> 6211410
A30: =IFERROR(IF(0=LEN(ReferenceData!$A$30),"",ReferenceData!$A$30),"") -> Passive Equity ETFs | B30: =IFERROR(IF(0=LEN(ReferenceData!$B$30),"",ReferenceData!$B$30),"") | C30: =IFERROR(IF(0=LEN(ReferenceData!$C$30),"",ReferenceData!$C$30),"") | D30: =IFERROR(IF(0=LEN(ReferenceData!$D$30),"",ReferenceData!$D$30),"") | E30: =IFERROR(IF(0=LEN(ReferenceData!$E$30),"",ReferenceData!$E$30),"") -> Expression | F30: =IFERROR(IF(0=LEN(ReferenceData!$AG$30),"",ReferenceData!$AG$30),"") -> 807885 | G30: =IFERROR(IF(0=LEN(ReferenceData!$AF$30),"",ReferenceData!$AF$30),"") -> 928707 | H30: =IFERROR(IF(0=LEN(ReferenceData!$AE$30),"",ReferenceData!$AE$30),"") -> 1086130 | I30: =IFERROR(IF(0=LEN(ReferenceData!$AD$30),"",ReferenceData!$AD$30),"") -> 1327860 | J30: =IFERROR(IF(0=LEN(ReferenceData!$AC$30),"",ReferenceData!$AC$30),"") -> 1461890 | K30: =IFERROR(IF(0=LEN(ReferenceData!$AB$30),"",ReferenceData!$AB$30),"") -> 1569620 | L30: =IFERROR(IF(0=LEN(ReferenceData!$AA$30),"",ReferenceData!$AA$30),"") -> 1698980 | M30: =IFERROR(IF(0=LEN(ReferenceData!$Z$30),"",ReferenceData!$Z$30),"") -> 1642090 | N30: =IFERROR(IF(0=LEN(ReferenceData!$Y$30),"",ReferenceData!$Y$30),"") -> 1721130 | O30: =IFERROR(IF(0=LEN(ReferenceData!$X$30),"",ReferenceData!$X$30),"") -> 2008340 | P30: =IFERROR(IF(0=LEN(ReferenceData!$W$30),"",ReferenceData!$W$30),"") -> 2339420 | Q30: =IFERROR(IF(0=LEN(ReferenceData!$V$30),"",ReferenceData!$V$30),"") -> 2759310 | R30: =IFERROR(IF(0=LEN(ReferenceData!$U$30),"",ReferenceData!$U$30),"") -> 2824110 | S30: =IFERROR(IF(0=LEN(ReferenceData!$T$30),"",ReferenceData!$T$30),"") -> 2642940 | T30: =IFERROR(IF(0=LEN(ReferenceData!$S$30),"",ReferenceData!$S$30),"") -> 3088940 | U30: =IFERROR(IF(0=LEN(ReferenceData!$R$30),"",ReferenceData!$R$30),"") -> 3445350 | V30: =IFERROR(IF(0=LEN(ReferenceData!$Q$30),"",ReferenceData!$Q$30),"") -> 3260310 | W30: =IFERROR(IF(0=LEN(ReferenceData!$P$30),"",ReferenceData!$P$30),"") -> 4165410 | X30: =IFERROR(IF(0=LEN(ReferenceData!$O$30),"",ReferenceData!$O$30),"") -> 5021590 | Y30: =IFERROR(IF(0=LEN(ReferenceData!$N$30),"",ReferenceData!$N$30),"") -> 5562200 | Z30: =IFERROR(IF(0=LEN(ReferenceData!$M$30),"",ReferenceData!$M$30),"") -> 4645390 | AA30: =IFERROR(IF(0=LEN(ReferenceData!$L$30),"",ReferenceData!$L$30),"") -> 4842470 | AB30: =IFERROR(IF(0=LEN(ReferenceData!$K$30),"",ReferenceData!$K$30),"") -> 5438010 | AC30: =IFERROR(IF(0=LEN(ReferenceData!$J$30),"",ReferenceData!$J$30),"") -> 6033180 | AD30: =IFERROR(IF(0=LEN(ReferenceData!$I$30),"",ReferenceData!$I$30),"") -> 6910130 | AE30: =IFERROR(IF(0=LEN(ReferenceData!$H$30),"",ReferenceData!$H$30),"") -> 7695150 | AF30: =IFERROR(IF(0=LEN(ReferenceData!$G$30),"",ReferenceData!$G$30),"") -> 8379840 | AG30: =IFERROR(IF(0=LEN(ReferenceData!$F$30),"",ReferenceData!$F$30),"") -> 9406290
A31: =IFERROR(IF(0=LEN(ReferenceData!$A$31),"",ReferenceData!$A$31),"") -> Active Equity | B31: =IFERROR(IF(0=LEN(ReferenceData!$B$31),"",ReferenceData!$B$31),"") -> .BIATATE G Index | C31: =IFERROR(IF(0=LEN(ReferenceData!$C$31),"",ReferenceData!$C$31),"") -> PR005 | D31: =IFERROR(IF(0=LEN(ReferenceData!$D$31),"",ReferenceData!$D$31),"") -> PX_LAST | E31: =IFERROR(IF(0=LEN(ReferenceData!$E$31),"",ReferenceData!$E$31),"") -> Dynamic | F31: =IFERROR(IF(0=LEN(ReferenceData!$AG$31),"",ReferenceData!$AG$31),"") -> 3449510 | G31: =IFERROR(IF(0=LEN(ReferenceData!$AF$31),"",ReferenceData!$AF$31),"") -> 3753280 | H31: =IFERROR(IF(0=LEN(ReferenceData!$AE$31),"",ReferenceData!$AE$31),"") -> 4257880 | I31: =IFERROR(IF(0=LEN(ReferenceData!$AD$31),"",ReferenceData!$AD$31),"") -> 5005450 | J31: =IFERROR(IF(0=LEN(ReferenceData!$AC$31),"",ReferenceData!$AC$31),"") -> 5433580 | K31: =IFERROR(IF(0=LEN(ReferenceData!$AB$31),"",ReferenceData!$AB$31),"") -> 5364090 | L31: =IFERROR(IF(0=LEN(ReferenceData!$AA$31),"",ReferenceData!$AA$31),"") -> 5553850 | M31: =IFERROR(IF(0=LEN(ReferenceData!$Z$31),"",ReferenceData!$Z$31),"") -> 5163310 | N31: =IFERROR(IF(0=LEN(ReferenceData!$Y$31),"",ReferenceData!$Y$31),"") -> 5220480 | O31: =IFERROR(IF(0=LEN(ReferenceData!$X$31),"",ReferenceData!$X$31),"") -> 5387780 | P31: =IFERROR(IF(0=LEN(ReferenceData!$W$31),"",ReferenceData!$W$31),"") -> 5928720 | Q31: =IFERROR(IF(0=LEN(ReferenceData!$V$31),"",ReferenceData!$V$31),"") -> 6419860 | R31: =IFERROR(IF(0=LEN(ReferenceData!$U$31),"",ReferenceData!$U$31),"") -> 6528160 | S31: =IFERROR(IF(0=LEN(ReferenceData!$T$31),"",ReferenceData!$T$31),"") -> 5527920 | T31: =IFERROR(IF(0=LEN(ReferenceData!$S$31),"",ReferenceData!$S$31),"") -> 6310890 | U31: =IFERROR(IF(0=LEN(ReferenceData!$R$31),"",ReferenceData!$R$31),"") -> 6875650 | V31: =IFERROR(IF(0=LEN(ReferenceData!$Q$31),"",ReferenceData!$Q$31),"") -> 6547420 | W31: =IFERROR(IF(0=LEN(ReferenceData!$P$31),"",ReferenceData!$P$31),"") -> 7839780 | X31: =IFERROR(IF(0=LEN(ReferenceData!$O$31),"",ReferenceData!$O$31),"") -> 8752850 | Y31: =IFERROR(IF(0=LEN(ReferenceData!$N$31),"",ReferenceData!$N$31),"") -> 8956440 | Z31: =IFERROR(IF(0=LEN(ReferenceData!$M$31),"",ReferenceData!$M$31),"") -> 6906620 | AA31: =IFERROR(IF(0=LEN(ReferenceData!$L$31),"",ReferenceData!$L$31),"") -> 6828460 | AB31: =IFERROR(IF(0=LEN(ReferenceData!$K$31),"",ReferenceData!$K$31),"") -> 7539810 | AC31: =IFERROR(IF(0=LEN(ReferenceData!$J$31),"",ReferenceData!$J$31),"") -> 7914730 | AD31: =IFERROR(IF(0=LEN(ReferenceData!$I$31),"",ReferenceData!$I$31),"") -> 8705020 | AE31: =IFERROR(IF(0=LEN(ReferenceData!$H$31),"",ReferenceData!$H$31),"") -> 8856760 | AF31: =IFERROR(IF(0=LEN(ReferenceData!$G$31),"",ReferenceData!$G$31),"") -> 9349890 | AG31: =IFERROR(IF(0=LEN(ReferenceData!$F$31),"",ReferenceData!$F$31),"") -> 9913250
A32: =IFERROR(IF(0=LEN(ReferenceData!$A$32),"",ReferenceData!$A$32),"") -> Active Equity Mutual Funds | B32: =IFERROR(IF(0=LEN(ReferenceData!$B$32),"",ReferenceData!$B$32),"") -> .BIAMATE G Index | C32: =IFERROR(IF(0=LEN(ReferenceData!$C$32),"",ReferenceData!$C$32),"") -> PR005 | D32: =IFERROR(IF(0=LEN(ReferenceData!$D$32),"",ReferenceData!$D$32),"") -> PX_LAST | E32: =IFERROR(IF(0=LEN(ReferenceData!$E$32),"",ReferenceData!$E$32),"") -> Dynamic | F32: =IFERROR(IF(0=LEN(ReferenceData!$AG$32),"",ReferenceData!$AG$32),"") -> 3429440 | G32: =IFERROR(IF(0=LEN(ReferenceData!$AF$32),"",ReferenceData!$AF$32),"") -> 3730730 | H32: =IFERROR(IF(0=LEN(ReferenceData!$AE$32),"",ReferenceData!$AE$32),"") -> 4230840 | I32: =IFERROR(IF(0=LEN(ReferenceData!$AD$32),"",ReferenceData!$AD$32),"") -> 4972970 | J32: =IFERROR(IF(0=LEN(ReferenceData!$AC$32),"",ReferenceData!$AC$32),"") -> 5395910 | K32: =IFERROR(IF(0=LEN(ReferenceData!$AB$32),"",ReferenceData!$AB$32),"") -> 5324460 | L32: =IFERROR(IF(0=LEN(ReferenceData!$AA$32),"",ReferenceData!$AA$32),"") -> 5509060 | M32: =IFERROR(IF(0=LEN(ReferenceData!$Z$32),"",ReferenceData!$Z$32),"") -> 5121620 | N32: =IFERROR(IF(0=LEN(ReferenceData!$Y$32),"",ReferenceData!$Y$32),"") -> 5174440 | O32: =IFERROR(IF(0=LEN(ReferenceData!$X$32),"",ReferenceData!$X$32),"") -> 5333280 | P32: =IFERROR(IF(0=LEN(ReferenceData!$W$32),"",ReferenceData!$W$32),"") -> 5867980 | Q32: =IFERROR(IF(0=LEN(ReferenceData!$V$32),"",ReferenceData!$V$32),"") -> 6345860 | R32: =IFERROR(IF(0=LEN(ReferenceData!$U$32),"",ReferenceData!$U$32),"") -> 6446000 | S32: =IFERROR(IF(0=LEN(ReferenceData!$T$32),"",ReferenceData!$T$32),"") -> 5457240 | T32: =IFERROR(IF(0=LEN(ReferenceData!$S$32),"",ReferenceData!$S$32),"") -> 6227260 | U32: =IFERROR(IF(0=LEN(ReferenceData!$R$32),"",ReferenceData!$R$32),"") -> 6783820 | V32: =IFERROR(IF(0=LEN(ReferenceData!$Q$32),"",ReferenceData!$Q$32),"") -> 6460670 | W32: =IFERROR(IF(0=LEN(ReferenceData!$P$32),"",ReferenceData!$P$32),"") -> 7701210 | X32: =IFERROR(IF(0=LEN(ReferenceData!$O$32),"",ReferenceData!$O$32),"") -> 8564790 | Y32: =IFERROR(IF(0=LEN(ReferenceData!$N$32),"",ReferenceData!$N$32),"") -> 8755200 | Z32: =IFERROR(IF(0=LEN(ReferenceData!$M$32),"",ReferenceData!$M$32),"") -> 6701310 | AA32: =IFERROR(IF(0=LEN(ReferenceData!$L$32),"",ReferenceData!$L$32),"") -> 6578750 | AB32: =IFERROR(IF(0=LEN(ReferenceData!$K$32),"",ReferenceData!$K$32),"") -> 7218560 | AC32: =IFERROR(IF(0=LEN(ReferenceData!$J$32),"",ReferenceData!$J$32),"") -> 7526760 | AD32: =IFERROR(IF(0=LEN(ReferenceData!$I$32),"",ReferenceData!$I$32),"") -> 8204750 | AE32: =IFERROR(IF(0=LEN(ReferenceData!$H$32),"",ReferenceData!$H$32),"") -> 8241660 | AF32: =IFERROR(IF(0=LEN(ReferenceData!$G$32),"",ReferenceData!$G$32),"") -> 8593660 | AG32: =IFERROR(IF(0=LEN(ReferenceData!$F$32),"",ReferenceData!$F$32),"") -> 9003600
A33: =IFERROR(IF(0=LEN(ReferenceData!$A$33),"",ReferenceData!$A$33),"") -> Active Equity ETFs | B33: =IFERROR(IF(0=LEN(ReferenceData!$B$33),"",ReferenceData!$B$33),"") | C33: =IFERROR(IF(0=LEN(ReferenceData!$C$33),"",ReferenceData!$C$33),"") | D33: =IFERROR(IF(0=LEN(ReferenceData!$D$33),"",ReferenceData!$D$33),"") | E33: =IFERROR(IF(0=LEN(ReferenceData!$E$33),"",ReferenceData!$E$33),"") -> Expression | F33: =IFERROR(IF(0=LEN(ReferenceData!$AG$33),"",ReferenceData!$AG$33),"") -> 20070 | G33: =IFERROR(IF(0=LEN(ReferenceData!$AF$33),"",ReferenceData!$AF$33),"") -> 22550 | H33: =IFERROR(IF(0=LEN(ReferenceData!$AE$33),"",ReferenceData!$AE$33),"") -> 27040 | I33: =IFERROR(IF(0=LEN(ReferenceData!$AD$33),"",ReferenceData!$AD$33),"") -> 32480 | J33: =IFERROR(IF(0=LEN(ReferenceData!$AC$33),"",ReferenceData!$AC$33),"") -> 37670 | K33: =IFERROR(IF(0=LEN(ReferenceData!$AB$33),"",ReferenceData!$AB$33),"") -> 39630 | L33: =IFERROR(IF(0=LEN(ReferenceData!$AA$33),"",ReferenceData!$AA$33),"") -> 44790 | M33: =IFERROR(IF(0=LEN(ReferenceData!$Z$33),"",ReferenceData!$Z$33),"") -> 41690 | N33: =IFERROR(IF(0=LEN(ReferenceData!$Y$33),"",ReferenceData!$Y$33),"") -> 46040 | O33: =IFERROR(IF(0=LEN(ReferenceData!$X$33),"",ReferenceData!$X$33),"") -> 54500 | P33: =IFERROR(IF(0=LEN(ReferenceData!$W$33),"",ReferenceData!$W$33),"") -> 60740 | Q33: =IFERROR(IF(0=LEN(ReferenceData!$V$33),"",ReferenceData!$V$33),"") -> 74000 | R33: =IFERROR(IF(0=LEN(ReferenceData!$U$33),"",ReferenceData!$U$33),"") -> 82160 | S33: =IFERROR(IF(0=LEN(ReferenceData!$T$33),"",ReferenceData!$T$33),"") -> 70680 | T33: =IFERROR(IF(0=LEN(ReferenceData!$S$33),"",ReferenceData!$S$33),"") -> 83630 | U33: =IFERROR(IF(0=LEN(ReferenceData!$R$33),"",ReferenceData!$R$33),"") -> 91830 | V33: =IFERROR(IF(0=LEN(ReferenceData!$Q$33),"",ReferenceData!$Q$33),"") -> 86750 | W33: =IFERROR(IF(0=LEN(ReferenceData!$P$33),"",ReferenceData!$P$33),"") -> 138570 | X33: =IFERROR(IF(0=LEN(ReferenceData!$O$33),"",ReferenceData!$O$33),"") -> 188060 | Y33: =IFERROR(IF(0=LEN(ReferenceData!$N$33),"",ReferenceData!$N$33),"") -> 201240 | Z33: =IFERROR(IF(0=LEN(ReferenceData!$M$33),"",ReferenceData!$M$33),"") -> 205310 | AA33: =IFERROR(IF(0=LEN(ReferenceData!$L$33),"",ReferenceData!$L$33),"") -> 249710 | AB33: =IFERROR(IF(0=LEN(ReferenceData!$K$33),"",ReferenceData!$K$33),"") -> 321250 | AC33: =IFERROR(IF(0=LEN(ReferenceData!$J$33),"",ReferenceData!$J$33),"") -> 387970 | AD33: =IFERROR(IF(0=LEN(ReferenceData!$I$33),"",ReferenceData!$I$33),"") -> 500270 | AE33: =IFERROR(IF(0=LEN(ReferenceData!$H$33),"",ReferenceData!$H$33),"") -> 615100 | AF33: =IFERROR(IF(0=LEN(ReferenceData!$G$33),"",ReferenceData!$G$33),"") -> 756230 | AG33: =IFERROR(IF(0=LEN(ReferenceData!$F$33),"",ReferenceData!$F$33),"") -> 909650
A34: =IFERROR(IF(0=LEN(ReferenceData!$A$34),"",ReferenceData!$A$34),"") -> Domestic Equity Funds | B34: =IFERROR(IF(0=LEN(ReferenceData!$B$34),"",ReferenceData!$B$34),"") | C34: =IFERROR(IF(0=LEN(ReferenceData!$C$34),"",ReferenceData!$C$34),"") | D34: =IFERROR(IF(0=LEN(ReferenceData!$D$34),"",ReferenceData!$D$34),"") | E34: =IFERROR(IF(0=LEN(ReferenceData!$E$34),"",ReferenceData!$E$34),"") -> Sum | F34: =IFERROR(IF(0=LEN(ReferenceData!$AG$34),"",ReferenceData!$AG$34),"") -> 3667440 | G34: =IFERROR(IF(0=LEN(ReferenceData!$AF$34),"",ReferenceData!$AF$34),"") -> 3924580 | H34: =IFERROR(IF(0=LEN(ReferenceData!$AE$34),"",ReferenceData!$AE$34),"") -> 4617360 | I34: =IFERROR(IF(0=LEN(ReferenceData!$AD$34),"",ReferenceData!$AD$34),"") -> 5469030 | J34: =IFERROR(IF(0=LEN(ReferenceData!$AC$34),"",ReferenceData!$AC$34),"") -> 5918210 | K34: =IFERROR(IF(0=LEN(ReferenceData!$AB$34),"",ReferenceData!$AB$34),"") -> 6186470 | L34: =IFERROR(IF(0=LEN(ReferenceData!$AA$34),"",ReferenceData!$AA$34),"") -> 6348120 | M34: =IFERROR(IF(0=LEN(ReferenceData!$Z$34),"",ReferenceData!$Z$34),"") -> 6100060 | N34: =IFERROR(IF(0=LEN(ReferenceData!$Y$34),"",ReferenceData!$Y$34),"") -> 6317140 | O34: =IFERROR(IF(0=LEN(ReferenceData!$X$34),"",ReferenceData!$X$34),"") -> 6851380 | P34: =IFERROR(IF(0=LEN(ReferenceData!$W$34),"",ReferenceData!$W$34),"") -> 7581040 | Q34: =IFERROR(IF(0=LEN(ReferenceData!$V$34),"",ReferenceData!$V$34),"") -> 8345110 | R34: =IFERROR(IF(0=LEN(ReferenceData!$U$34),"",ReferenceData!$U$34),"") -> 8680600 | S34: =IFERROR(IF(0=LEN(ReferenceData!$T$34),"",ReferenceData!$T$34),"") -> 7751880 | T34: =IFERROR(IF(0=LEN(ReferenceData!$S$34),"",ReferenceData!$S$34),"") -> 9133080 | U34: =IFERROR(IF(0=LEN(ReferenceData!$R$34),"",ReferenceData!$R$34),"") -> 10013050 | V34: =IFERROR(IF(0=LEN(ReferenceData!$Q$34),"",ReferenceData!$Q$34),"") -> 9628890 | W34: =IFERROR(IF(0=LEN(ReferenceData!$P$34),"",ReferenceData!$P$34),"") -> 11698190 | X34: =IFERROR(IF(0=LEN(ReferenceData!$O$34),"",ReferenceData!$O$34),"") -> 13547000 | Y34: =IFERROR(IF(0=LEN(ReferenceData!$N$34),"",ReferenceData!$N$34),"") -> 14593150 | Z34: =IFERROR(IF(0=LEN(ReferenceData!$M$34),"",ReferenceData!$M$34),"") -> 11648480 | AA34: =IFERROR(IF(0=LEN(ReferenceData!$L$34),"",ReferenceData!$L$34),"") -> 11829260 | AB34: =IFERROR(IF(0=LEN(ReferenceData!$K$34),"",ReferenceData!$K$34),"") -> 13349890 | AC34: =IFERROR(IF(0=LEN(ReferenceData!$J$34),"",ReferenceData!$J$34),"") -> 14505300 | AD34: =IFERROR(IF(0=LEN(ReferenceData!$I$34),"",ReferenceData!$I$34),"") -> 16427360 | AE34: =IFERROR(IF(0=LEN(ReferenceData!$H$34),"",ReferenceData!$H$34),"") -> 17774630 | AF34: =IFERROR(IF(0=LEN(ReferenceData!$G$34),"",ReferenceData!$G$34),"") -> 18668120 | AG34: =IFERROR(IF(0=LEN(ReferenceData!$F$34),"",ReferenceData!$F$34),"") -> 19979730
A35: =IFERROR(IF(0=LEN(ReferenceData!$A$35),"",ReferenceData!$A$35),"") -> Passive Domestic Equity | B35: =IFERROR(IF(0=LEN(ReferenceData!$B$35),"",ReferenceData!$B$35),"") -> .BIATPDE G Index | C35: =IFERROR(IF(0=LEN(ReferenceData!$C$35),"",ReferenceData!$C$35),"") -> PR005 | D35: =IFERROR(IF(0=LEN(ReferenceData!$D$35),"",ReferenceData!$D$35),"") -> PX_LAST | E35: =IFERROR(IF(0=LEN(ReferenceData!$E$35),"",ReferenceData!$E$35),"") -> Dynamic | F35: =IFERROR(IF(0=LEN(ReferenceData!$AG$35),"",ReferenceData!$AG$35),"") -> 1270680 | G35: =IFERROR(IF(0=LEN(ReferenceData!$AF$35),"",ReferenceData!$AF$35),"") -> 1379420 | H35: =IFERROR(IF(0=LEN(ReferenceData!$AE$35),"",ReferenceData!$AE$35),"") -> 1690340 | I35: =IFERROR(IF(0=LEN(ReferenceData!$AD$35),"",ReferenceData!$AD$35),"") -> 2042170 | J35: =IFERROR(IF(0=LEN(ReferenceData!$AC$35),"",ReferenceData!$AC$35),"") -> 2253120 | K35: =IFERROR(IF(0=LEN(ReferenceData!$AB$35),"",ReferenceData!$AB$35),"") -> 2483870 | L35: =IFERROR(IF(0=LEN(ReferenceData!$AA$35),"",ReferenceData!$AA$35),"") -> 2574320 | M35: =IFERROR(IF(0=LEN(ReferenceData!$Z$35),"",ReferenceData!$Z$35),"") -> 2549620 | N35: =IFERROR(IF(0=LEN(ReferenceData!$Y$35),"",ReferenceData!$Y$35),"") -> 2728850 | O35: =IFERROR(IF(0=LEN(ReferenceData!$X$35),"",ReferenceData!$X$35),"") -> 3112890 | P35: =IFERROR(IF(0=LEN(ReferenceData!$W$35),"",ReferenceData!$W$35),"") -> 3535910 | Q35: =IFERROR(IF(0=LEN(ReferenceData!$V$35),"",ReferenceData!$V$35),"") -> 4035350 | R35: =IFERROR(IF(0=LEN(ReferenceData!$U$35),"",ReferenceData!$U$35),"") -> 4218050 | S35: =IFERROR(IF(0=LEN(ReferenceData!$T$35),"",ReferenceData!$T$35),"") -> 3940280 | T35: =IFERROR(IF(0=LEN(ReferenceData!$S$35),"",ReferenceData!$S$35),"") -> 4728930 | U35: =IFERROR(IF(0=LEN(ReferenceData!$R$35),"",ReferenceData!$R$35),"") -> 5248890 | V35: =IFERROR(IF(0=LEN(ReferenceData!$Q$35),"",ReferenceData!$Q$35),"") -> 5032850 | W35: =IFERROR(IF(0=LEN(ReferenceData!$P$35),"",ReferenceData!$P$35),"") -> 6238940 | X35: =IFERROR(IF(0=LEN(ReferenceData!$O$35),"",ReferenceData!$O$35),"") -> 7386620 | Y35: =IFERROR(IF(0=LEN(ReferenceData!$N$35),"",ReferenceData!$N$35),"") -> 8202730 | Z35: =IFERROR(IF(0=LEN(ReferenceData!$M$35),"",ReferenceData!$M$35),"") -> 6721610 | AA35: =IFERROR(IF(0=LEN(ReferenceData!$L$35),"",ReferenceData!$L$35),"") -> 6943490 | AB35: =IFERROR(IF(0=LEN(ReferenceData!$K$35),"",ReferenceData!$K$35),"") -> 7930160 | AC35: =IFERROR(IF(0=LEN(ReferenceData!$J$35),"",ReferenceData!$J$35),"") -> 8758300 | AD35: =IFERROR(IF(0=LEN(ReferenceData!$I$35),"",ReferenceData!$I$35),"") -> 10049400 | AE35: =IFERROR(IF(0=LEN(ReferenceData!$H$35),"",ReferenceData!$H$35),"") -> 11190700 | AF35: =IFERROR(IF(0=LEN(ReferenceData!$G$35),"",ReferenceData!$G$35),"") -> 11885100 | AG35: =IFERROR(IF(0=LEN(ReferenceData!$F$35),"",ReferenceData!$F$35),"") -> 12814100
A36: =IFERROR(IF(0=LEN(ReferenceData!$A$36),"",ReferenceData!$A$36),"") -> Passive Domestic Equity Mutual Funds | B36: =IFERROR(IF(0=LEN(ReferenceData!$B$36),"",ReferenceData!$B$36),"") -> .BIAMPDE G Index | C36: =IFERROR(IF(0=LEN(ReferenceData!$C$36),"",ReferenceData!$C$36),"") -> PR005 | D36: =IFERROR(IF(0=LEN(ReferenceData!$D$36),"",ReferenceData!$D$36),"") -> PX_LAST | E36: =IFERROR(IF(0=LEN(ReferenceData!$E$36),"",ReferenceData!$E$36),"") -> Dynamic | F36: =IFERROR(IF(0=LEN(ReferenceData!$AG$36),"",ReferenceData!$AG$36),"") -> 717046 | G36: =IFERROR(IF(0=LEN(ReferenceData!$AF$36),"",ReferenceData!$AF$36),"") -> 779408 | H36: =IFERROR(IF(0=LEN(ReferenceData!$AE$36),"",ReferenceData!$AE$36),"") -> 922778 | I36: =IFERROR(IF(0=LEN(ReferenceData!$AD$36),"",ReferenceData!$AD$36),"") -> 1103640 | J36: =IFERROR(IF(0=LEN(ReferenceData!$AC$36),"",ReferenceData!$AC$36),"") -> 1226410 | K36: =IFERROR(IF(0=LEN(ReferenceData!$AB$36),"",ReferenceData!$AB$36),"") -> 1320160 | L36: =IFERROR(IF(0=LEN(ReferenceData!$AA$36),"",ReferenceData!$AA$36),"") -> 1384710 | M36: =IFERROR(IF(0=LEN(ReferenceData!$Z$36),"",ReferenceData!$Z$36),"") -> 1366790 | N36: =IFERROR(IF(0=LEN(ReferenceData!$Y$36),"",ReferenceData!$Y$36),"") -> 1466350 | O36: =IFERROR(IF(0=LEN(ReferenceData!$X$36),"",ReferenceData!$X$36),"") -> 1603580 | P36: =IFERROR(IF(0=LEN(ReferenceData!$W$36),"",ReferenceData!$W$36),"") -> 1849700 | Q36: =IFERROR(IF(0=LEN(ReferenceData!$V$36),"",ReferenceData!$V$36),"") -> 2068520 | R36: =IFERROR(IF(0=LEN(ReferenceData!$U$36),"",ReferenceData!$U$36),"") -> 2166230 | S36: =IFERROR(IF(0=LEN(ReferenceData!$T$36),"",ReferenceData!$T$36),"") -> 2021960 | T36: =IFERROR(IF(0=LEN(ReferenceData!$S$36),"",ReferenceData!$S$36),"") -> 2445380 | U36: =IFERROR(IF(0=LEN(ReferenceData!$R$36),"",ReferenceData!$R$36),"") -> 2677600 | V36: =IFERROR(IF(0=LEN(ReferenceData!$Q$36),"",ReferenceData!$Q$36),"") -> 2540500 | W36: =IFERROR(IF(0=LEN(ReferenceData!$P$36),"",ReferenceData!$P$36),"") -> 3079170 | X36: =IFERROR(IF(0=LEN(ReferenceData!$O$36),"",ReferenceData!$O$36),"") -> 3553700 | Y36: =IFERROR(IF(0=LEN(ReferenceData!$N$36),"",ReferenceData!$N$36),"") -> 3851880 | Z36: =IFERROR(IF(0=LEN(ReferenceData!$M$36),"",ReferenceData!$M$36),"") -> 3094730 | AA36: =IFERROR(IF(0=LEN(ReferenceData!$L$36),"",ReferenceData!$L$36),"") -> 3161320 | AB36: =IFERROR(IF(0=LEN(ReferenceData!$K$36),"",ReferenceData!$K$36),"") -> 3655000 | AC36: =IFERROR(IF(0=LEN(ReferenceData!$J$36),"",ReferenceData!$J$36),"") -> 3943510 | AD36: =IFERROR(IF(0=LEN(ReferenceData!$I$36),"",ReferenceData!$I$36),"") -> 4467590 | AE36: =IFERROR(IF(0=LEN(ReferenceData!$H$36),"",ReferenceData!$H$36),"") -> 4818500 | AF36: =IFERROR(IF(0=LEN(ReferenceData!$G$36),"",ReferenceData!$G$36),"") -> 5099340 | AG36: =IFERROR(IF(0=LEN(ReferenceData!$F$36),"",ReferenceData!$F$36),"") -> 5240690
A37: =IFERROR(IF(0=LEN(ReferenceData!$A$37),"",ReferenceData!$A$37),"") -> Passive Domestic Equity ETFs | B37: =IFERROR(IF(0=LEN(ReferenceData!$B$37),"",ReferenceData!$B$37),"") | C37: =IFERROR(IF(0=LEN(ReferenceData!$C$37),"",ReferenceData!$C$37),"") | D37: =IFERROR(IF(0=LEN(ReferenceData!$D$37),"",ReferenceData!$D$37),"") | E37: =IFERROR(IF(0=LEN(ReferenceData!$E$37),"",ReferenceData!$E$37),"") -> Expression | F37: =IFERROR(IF(0=LEN(ReferenceData!$AG$37),"",ReferenceData!$AG$37),"") -> 553634 | G37: =IFERROR(IF(0=LEN(ReferenceData!$AF$37),"",ReferenceData!$AF$37),"") -> 600012 | H37: =IFERROR(IF(0=LEN(ReferenceData!$AE$37),"",ReferenceData!$AE$37),"") -> 767562 | I37: =IFERROR(IF(0=LEN(ReferenceData!$AD$37),"",ReferenceData!$AD$37),"") -> 938530 | J37: =IFERROR(IF(0=LEN(ReferenceData!$AC$37),"",ReferenceData!$AC$37),"") -> 1026710 | K37: =IFERROR(IF(0=LEN(ReferenceData!$AB$37),"",ReferenceData!$AB$37),"") -> 1163710 | L37: =IFERROR(IF(0=LEN(ReferenceData!$AA$37),"",ReferenceData!$AA$37),"") -> 1189610 | M37: =IFERROR(IF(0=LEN(ReferenceData!$Z$37),"",ReferenceData!$Z$37),"") -> 1182830 | N37: =IFERROR(IF(0=LEN(ReferenceData!$Y$37),"",ReferenceData!$Y$37),"") -> 1262500 | O37: =IFERROR(IF(0=LEN(ReferenceData!$X$37),"",ReferenceData!$X$37),"") -> 1509310 | P37: =IFERROR(IF(0=LEN(ReferenceData!$W$37),"",ReferenceData!$W$37),"") -> 1686210 | Q37: =IFERROR(IF(0=LEN(ReferenceData!$V$37),"",ReferenceData!$V$37),"") -> 1966830 | R37: =IFERROR(IF(0=LEN(ReferenceData!$U$37),"",ReferenceData!$U$37),"") -> 2051820 | S37: =IFERROR(IF(0=LEN(ReferenceData!$T$37),"",ReferenceData!$T$37),"") -> 1918320 | T37: =IFERROR(IF(0=LEN(ReferenceData!$S$37),"",ReferenceData!$S$37),"") -> 2283550 | U37: =IFERROR(IF(0=LEN(ReferenceData!$R$37),"",ReferenceData!$R$37),"") -> 2571290 | V37: =IFERROR(IF(0=LEN(ReferenceData!$Q$37),"",ReferenceData!$Q$37),"") -> 2492350 | W37: =IFERROR(IF(0=LEN(ReferenceData!$P$37),"",ReferenceData!$P$37),"") -> 3159770 | X37: =IFERROR(IF(0=LEN(ReferenceData!$O$37),"",ReferenceData!$O$37),"") -> 3832920 | Y37: =IFERROR(IF(0=LEN(ReferenceData!$N$37),"",ReferenceData!$N$37),"") -> 4350850 | Z37: =IFERROR(IF(0=LEN(ReferenceData!$M$37),"",ReferenceData!$M$37),"") -> 3626880 | AA37: =IFERROR(IF(0=LEN(ReferenceData!$L$37),"",ReferenceData!$L$37),"") -> 3782170 | AB37: =IFERROR(IF(0=LEN(ReferenceData!$K$37),"",ReferenceData!$K$37),"") -> 4275160 | AC37: =IFERROR(IF(0=LEN(ReferenceData!$J$37),"",ReferenceData!$J$37),"") -> 4814790 | AD37: =IFERROR(IF(0=LEN(ReferenceData!$I$37),"",ReferenceData!$I$37),"") -> 5581810 | AE37: =IFERROR(IF(0=LEN(ReferenceData!$H$37),"",ReferenceData!$H$37),"") -> 6372200 | AF37: =IFERROR(IF(0=LEN(ReferenceData!$G$37),"",ReferenceData!$G$37),"") -> 6785760 | AG37: =IFERROR(IF(0=LEN(ReferenceData!$F$37),"",ReferenceData!$F$37),"") -> 7573410
A38: =IFERROR(IF(0=LEN(ReferenceData!$A$38),"",ReferenceData!$A$38),"") -> Active Domestic Equity | B38: =IFERROR(IF(0=LEN(ReferenceData!$B$38),"",ReferenceData!$B$38),"") -> .BIATADE G Index | C38: =IFERROR(IF(0=LEN(ReferenceData!$C$38),"",ReferenceData!$C$38),"") -> PR005 | D38: =IFERROR(IF(0=LEN(ReferenceData!$D$38),"",ReferenceData!$D$38),"") -> PX_LAST | E38: =IFERROR(IF(0=LEN(ReferenceData!$E$38),"",ReferenceData!$E$38),"") -> Dynamic | F38: =IFERROR(IF(0=LEN(ReferenceData!$AG$38),"",ReferenceData!$AG$38),"") -> 2396760 | G38: =IFERROR(IF(0=LEN(ReferenceData!$AF$38),"",ReferenceData!$AF$38),"") -> 2545160 | H38: =IFERROR(IF(0=LEN(ReferenceData!$AE$38),"",ReferenceData!$AE$38),"") -> 2927020 | I38: =IFERROR(IF(0=LEN(ReferenceData!$AD$38),"",ReferenceData!$AD$38),"") -> 3426860 | J38: =IFERROR(IF(0=LEN(ReferenceData!$AC$38),"",ReferenceData!$AC$38),"") -> 3665090 | K38: =IFERROR(IF(0=LEN(ReferenceData!$AB$38),"",ReferenceData!$AB$38),"") -> 3702600 | L38: =IFERROR(IF(0=LEN(ReferenceData!$AA$38),"",ReferenceData!$AA$38),"") -> 3773800 | M38: =IFERROR(IF(0=LEN(ReferenceData!$Z$38),"",ReferenceData!$Z$38),"") -> 3550440 | N38: =IFERROR(IF(0=LEN(ReferenceData!$Y$38),"",ReferenceData!$Y$38),"") -> 3588290 | O38: =IFERROR(IF(0=LEN(ReferenceData!$X$38),"",ReferenceData!$X$38),"") -> 3738490 | P38: =IFERROR(IF(0=LEN(ReferenceData!$W$38),"",ReferenceData!$W$38),"") -> 4045130 | Q38: =IFERROR(IF(0=LEN(ReferenceData!$V$38),"",ReferenceData!$V$38),"") -> 4309760 | R38: =IFERROR(IF(0=LEN(ReferenceData!$U$38),"",ReferenceData!$U$38),"") -> 4462550 | S38: =IFERROR(IF(0=LEN(ReferenceData!$T$38),"",ReferenceData!$T$38),"") -> 3811600 | T38: =IFERROR(IF(0=LEN(ReferenceData!$S$38),"",ReferenceData!$S$38),"") -> 4404150 | U38: =IFERROR(IF(0=LEN(ReferenceData!$R$38),"",ReferenceData!$R$38),"") -> 4764160 | V38: =IFERROR(IF(0=LEN(ReferenceData!$Q$38),"",ReferenceData!$Q$38),"") -> 4596040 | W38: =IFERROR(IF(0=LEN(ReferenceData!$P$38),"",ReferenceData!$P$38),"") -> 5459250 | X38: =IFERROR(IF(0=LEN(ReferenceData!$O$38),"",ReferenceData!$O$38),"") -> 6160380 | Y38: =IFERROR(IF(0=LEN(ReferenceData!$N$38),"",ReferenceData!$N$38),"") -> 6390420 | Z38: =IFERROR(IF(0=LEN(ReferenceData!$M$38),"",ReferenceData!$M$38),"") -> 4926870 | AA38: =IFERROR(IF(0=LEN(ReferenceData!$L$38),"",ReferenceData!$L$38),"") -> 4885770 | AB38: =IFERROR(IF(0=LEN(ReferenceData!$K$38),"",ReferenceData!$K$38),"") -> 5419730 | AC38: =IFERROR(IF(0=LEN(ReferenceData!$J$38),"",ReferenceData!$J$38),"") -> 5747000 | AD38: =IFERROR(IF(0=LEN(ReferenceData!$I$38),"",ReferenceData!$I$38),"") -> 6377960 | AE38: =IFERROR(IF(0=LEN(ReferenceData!$H$38),"",ReferenceData!$H$38),"") -> 6583930 | AF38: =IFERROR(IF(0=LEN(ReferenceData!$G$38),"",ReferenceData!$G$38),"") -> 6783020 | AG38: =IFERROR(IF(0=LEN(ReferenceData!$F$38),"",ReferenceData!$F$38),"") -> 7165630
A39: =IFERROR(IF(0=LEN(ReferenceData!$A$39),"",ReferenceData!$A$39),"") -> Active Domestic Equity Mutual Funds | B39: =IFERROR(IF(0=LEN(ReferenceData!$B$39),"",ReferenceData!$B$39),"") -> .BIAMADE G Index | C39: =IFERROR(IF(0=LEN(ReferenceData!$C$39),"",ReferenceData!$C$39),"") -> PR005 | D39: =IFERROR(IF(0=LEN(ReferenceData!$D$39),"",ReferenceData!$D$39),"") -> PX_LAST | E39: =IFERROR(IF(0=LEN(ReferenceData!$E$39),"",ReferenceData!$E$39),"") -> Dynamic | F39: =IFERROR(IF(0=LEN(ReferenceData!$AG$39),"",ReferenceData!$AG$39),"") -> 2380790 | G39: =IFERROR(IF(0=LEN(ReferenceData!$AF$39),"",ReferenceData!$AF$39),"") -> 2527520 | H39: =IFERROR(IF(0=LEN(ReferenceData!$AE$39),"",ReferenceData!$AE$39),"") -> 2905830 | I39: =IFERROR(IF(0=LEN(ReferenceData!$AD$39),"",ReferenceData!$AD$39),"") -> 3401960 | J39: =IFERROR(IF(0=LEN(ReferenceData!$AC$39),"",ReferenceData!$AC$39),"") -> 3637220 | K39: =IFERROR(IF(0=LEN(ReferenceData!$AB$39),"",ReferenceData!$AB$39),"") -> 3673680 | L39: =IFERROR(IF(0=LEN(ReferenceData!$AA$39),"",ReferenceData!$AA$39),"") -> 3742320 | M39: =IFERROR(IF(0=LEN(ReferenceData!$Z$39),"",ReferenceData!$Z$39),"") -> 3521710 | N39: =IFERROR(IF(0=LEN(ReferenceData!$Y$39),"",ReferenceData!$Y$39),"") -> 3556620 | O39: =IFERROR(IF(0=LEN(ReferenceData!$X$39),"",ReferenceData!$X$39),"") -> 3701450 | P39: =IFERROR(IF(0=LEN(ReferenceData!$W$39),"",ReferenceData!$W$39),"") -> 4005170 | Q39: =IFERROR(IF(0=LEN(ReferenceData!$V$39),"",ReferenceData!$V$39),"") -> 4261780 | R39: =IFERROR(IF(0=LEN(ReferenceData!$U$39),"",ReferenceData!$U$39),"") -> 4409170 | S39: =IFERROR(IF(0=LEN(ReferenceData!$T$39),"",ReferenceData!$T$39),"") -> 3765390 | T39: =IFERROR(IF(0=LEN(ReferenceData!$S$39),"",ReferenceData!$S$39),"") -> 4348510 | U39: =IFERROR(IF(0=LEN(ReferenceData!$R$39),"",ReferenceData!$R$39),"") -> 4702860 | V39: =IFERROR(IF(0=LEN(ReferenceData!$Q$39),"",ReferenceData!$Q$39),"") -> 4534540 | W39: =IFERROR(IF(0=LEN(ReferenceData!$P$39),"",ReferenceData!$P$39),"") -> 5355340 | X39: =IFERROR(IF(0=LEN(ReferenceData!$O$39),"",ReferenceData!$O$39),"") -> 6023210 | Y39: =IFERROR(IF(0=LEN(ReferenceData!$N$39),"",ReferenceData!$N$39),"") -> 6244090 | Z39: =IFERROR(IF(0=LEN(ReferenceData!$M$39),"",ReferenceData!$M$39),"") -> 4780260 | AA39: =IFERROR(IF(0=LEN(ReferenceData!$L$39),"",ReferenceData!$L$39),"") -> 4708720 | AB39: =IFERROR(IF(0=LEN(ReferenceData!$K$39),"",ReferenceData!$K$39),"") -> 5188460 | AC39: =IFERROR(IF(0=LEN(ReferenceData!$J$39),"",ReferenceData!$J$39),"") -> 5453020 | AD39: =IFERROR(IF(0=LEN(ReferenceData!$I$39),"",ReferenceData!$I$39),"") -> 5997400 | AE39: =IFERROR(IF(0=LEN(ReferenceData!$H$39),"",ReferenceData!$H$39),"") -> 6111570 | AF39: =IFERROR(IF(0=LEN(ReferenceData!$G$39),"",ReferenceData!$G$39),"") -> 6215450 | AG39: =IFERROR(IF(0=LEN(ReferenceData!$F$39),"",ReferenceData!$F$39),"") -> 6491070
A40: =IFERROR(IF(0=LEN(ReferenceData!$A$40),"",ReferenceData!$A$40),"") -> Active Domestic Equity ETFs | B40: =IFERROR(IF(0=LEN(ReferenceData!$B$40),"",ReferenceData!$B$40),"") | C40: =IFERROR(IF(0=LEN(ReferenceData!$C$40),"",ReferenceData!$C$40),"") | D40: =IFERROR(IF(0=LEN(ReferenceData!$D$40),"",ReferenceData!$D$40),"") | E40: =IFERROR(IF(0=LEN(ReferenceData!$E$40),"",ReferenceData!$E$40),"") -> Expression | F40: =IFERROR(IF(0=LEN(ReferenceData!$AG$40),"",ReferenceData!$AG$40),"") -> 15970 | G40: =IFERROR(IF(0=LEN(ReferenceData!$AF$40),"",ReferenceData!$AF$40),"") -> 17640 | H40: =IFERROR(IF(0=LEN(ReferenceData!$AE$40),"",ReferenceData!$AE$40),"") -> 21190 | I40: =IFERROR(IF(0=LEN(ReferenceData!$AD$40),"",ReferenceData!$AD$40),"") -> 24900 | J40: =IFERROR(IF(0=LEN(ReferenceData!$AC$40),"",ReferenceData!$AC$40),"") -> 27870 | K40: =IFERROR(IF(0=LEN(ReferenceData!$AB$40),"",ReferenceData!$AB$40),"") -> 28920 | L40: =IFERROR(IF(0=LEN(ReferenceData!$AA$40),"",ReferenceData!$AA$40),"") -> 31480 | M40: =IFERROR(IF(0=LEN(ReferenceData!$Z$40),"",ReferenceData!$Z$40),"") -> 28730 | N40: =IFERROR(IF(0=LEN(ReferenceData!$Y$40),"",ReferenceData!$Y$40),"") -> 31670 | O40: =IFERROR(IF(0=LEN(ReferenceData!$X$40),"",ReferenceData!$X$40),"") -> 37040 | P40: =IFERROR(IF(0=LEN(ReferenceData!$W$40),"",ReferenceData!$W$40),"") -> 39960 | Q40: =IFERROR(IF(0=LEN(ReferenceData!$V$40),"",ReferenceData!$V$40),"") -> 47980 | R40: =IFERROR(IF(0=LEN(ReferenceData!$U$40),"",ReferenceData!$U$40),"") -> 53380 | S40: =IFERROR(IF(0=LEN(ReferenceData!$T$40),"",ReferenceData!$T$40),"") -> 46210 | T40: =IFERROR(IF(0=LEN(ReferenceData!$S$40),"",ReferenceData!$S$40),"") -> 55640 | U40: =IFERROR(IF(0=LEN(ReferenceData!$R$40),"",ReferenceData!$R$40),"") -> 61300 | V40: =IFERROR(IF(0=LEN(ReferenceData!$Q$40),"",ReferenceData!$Q$40),"") -> 61500 | W40: =IFERROR(IF(0=LEN(ReferenceData!$P$40),"",ReferenceData!$P$40),"") -> 103910 | X40: =IFERROR(IF(0=LEN(ReferenceData!$O$40),"",ReferenceData!$O$40),"") -> 137170 | Y40: =IFERROR(IF(0=LEN(ReferenceData!$N$40),"",ReferenceData!$N$40),"") -> 146330 | Z40: =IFERROR(IF(0=LEN(ReferenceData!$M$40),"",ReferenceData!$M$40),"") -> 146610 | AA40: =IFERROR(IF(0=LEN(ReferenceData!$L$40),"",ReferenceData!$L$40),"") -> 177050 | AB40: =IFERROR(IF(0=LEN(ReferenceData!$K$40),"",ReferenceData!$K$40),"") -> 231270 | AC40: =IFERROR(IF(0=LEN(ReferenceData!$J$40),"",ReferenceData!$J$40),"") -> 293980 | AD40: =IFERROR(IF(0=LEN(ReferenceData!$I$40),"",ReferenceData!$I$40),"") -> 380560 | AE40: =IFERROR(IF(0=LEN(ReferenceData!$H$40),"",ReferenceData!$H$40),"") -> 472360 | AF40: =IFERROR(IF(0=LEN(ReferenceData!$G$40),"",ReferenceData!$G$40),"") -> 567570 | AG40: =IFERROR(IF(0=LEN(ReferenceData!$F$40),"",ReferenceData!$F$40),"") -> 674560
A41: =IFERROR(IF(0=LEN(ReferenceData!$A$41),"",ReferenceData!$A$41),"") -> Non-Domestic Equity Funds | B41: =IFERROR(IF(0=LEN(ReferenceData!$B$41),"",ReferenceData!$B$41),"") | C41: =IFERROR(IF(0=LEN(ReferenceData!$C$41),"",ReferenceData!$C$41),"") | D41: =IFERROR(IF(0=LEN(ReferenceData!$D$41),"",ReferenceData!$D$41),"") | E41: =IFERROR(IF(0=LEN(ReferenceData!$E$41),"",ReferenceData!$E$41),"") -> Sum | F41: =IFERROR(IF(0=LEN(ReferenceData!$AG$41),"",ReferenceData!$AG$41),"") -> 1424893 | G41: =IFERROR(IF(0=LEN(ReferenceData!$AF$41),"",ReferenceData!$AF$41),"") -> 1679381 | H41: =IFERROR(IF(0=LEN(ReferenceData!$AE$41),"",ReferenceData!$AE$41),"") -> 1805410 | I41: =IFERROR(IF(0=LEN(ReferenceData!$AD$41),"",ReferenceData!$AD$41),"") -> 2157951 | J41: =IFERROR(IF(0=LEN(ReferenceData!$AC$41),"",ReferenceData!$AC$41),"") -> 2437783 | K41: =IFERROR(IF(0=LEN(ReferenceData!$AB$41),"",ReferenceData!$AB$41),"") -> 2302150 | L41: =IFERROR(IF(0=LEN(ReferenceData!$AA$41),"",ReferenceData!$AA$41),"") -> 2571359 | M41: =IFERROR(IF(0=LEN(ReferenceData!$Z$41),"",ReferenceData!$Z$41),"") -> 2366760 | N41: =IFERROR(IF(0=LEN(ReferenceData!$Y$41),"",ReferenceData!$Y$41),"") -> 2409833 | O41: =IFERROR(IF(0=LEN(ReferenceData!$X$41),"",ReferenceData!$X$41),"") -> 2494094 | P41: =IFERROR(IF(0=LEN(ReferenceData!$W$41),"",ReferenceData!$W$41),"") -> 2976710 | Q41: =IFERROR(IF(0=LEN(ReferenceData!$V$41),"",ReferenceData!$V$41),"") -> 3423470 | R41: =IFERROR(IF(0=LEN(ReferenceData!$U$41),"",ReferenceData!$U$41),"") -> 3371910 | S41: =IFERROR(IF(0=LEN(ReferenceData!$T$41),"",ReferenceData!$T$41),"") -> 2949770 | T41: =IFERROR(IF(0=LEN(ReferenceData!$S$41),"",ReferenceData!$S$41),"") -> 3303400 | U41: =IFERROR(IF(0=LEN(ReferenceData!$R$41),"",ReferenceData!$R$41),"") -> 3636230 | V41: =IFERROR(IF(0=LEN(ReferenceData!$Q$41),"",ReferenceData!$Q$41),"") -> 3326320 | W41: =IFERROR(IF(0=LEN(ReferenceData!$P$41),"",ReferenceData!$P$41),"") -> 4046780 | X41: =IFERROR(IF(0=LEN(ReferenceData!$O$41),"",ReferenceData!$O$41),"") -> 4462070 | Y41: =IFERROR(IF(0=LEN(ReferenceData!$N$41),"",ReferenceData!$N$41),"") -> 4492900 | Z41: =IFERROR(IF(0=LEN(ReferenceData!$M$41),"",ReferenceData!$M$41),"") -> 3583460 | AA41: =IFERROR(IF(0=LEN(ReferenceData!$L$41),"",ReferenceData!$L$41),"") -> 3602060 | AB41: =IFERROR(IF(0=LEN(ReferenceData!$K$41),"",ReferenceData!$K$41),"") -> 3941090 | AC41: =IFERROR(IF(0=LEN(ReferenceData!$J$41),"",ReferenceData!$J$41),"") -> 4088620 | AD41: =IFERROR(IF(0=LEN(ReferenceData!$I$41),"",ReferenceData!$I$41),"") -> 4408450 | AE41: =IFERROR(IF(0=LEN(ReferenceData!$H$41),"",ReferenceData!$H$41),"") -> 4358280 | AF41: =IFERROR(IF(0=LEN(ReferenceData!$G$41),"",ReferenceData!$G$41),"") -> 5050990 | AG41: =IFERROR(IF(0=LEN(ReferenceData!$F$41),"",ReferenceData!$F$41),"") -> 5551120
A42: =IFERROR(IF(0=LEN(ReferenceData!$A$42),"",ReferenceData!$A$42),"") -> Passive Non-Domestic Equity | B42: =IFERROR(IF(0=LEN(ReferenceData!$B$42),"",ReferenceData!$B$42),"") -> .BIATPNE G Index | C42: =IFERROR(IF(0=LEN(ReferenceData!$C$42),"",ReferenceData!$C$42),"") -> PR005 | D42: =IFERROR(IF(0=LEN(ReferenceData!$D$42),"",ReferenceData!$D$42),"") -> PX_LAST | E42: =IFERROR(IF(0=LEN(ReferenceData!$E$42),"",ReferenceData!$E$42),"") -> Dynamic | F42: =IFERROR(IF(0=LEN(ReferenceData!$AG$42),"",ReferenceData!$AG$42),"") -> 372153 | G42: =IFERROR(IF(0=LEN(ReferenceData!$AF$42),"",ReferenceData!$AF$42),"") -> 471261 | H42: =IFERROR(IF(0=LEN(ReferenceData!$AE$42),"",ReferenceData!$AE$42),"") -> 474550 | I42: =IFERROR(IF(0=LEN(ReferenceData!$AD$42),"",ReferenceData!$AD$42),"") -> 579361 | J42: =IFERROR(IF(0=LEN(ReferenceData!$AC$42),"",ReferenceData!$AC$42),"") -> 669293 | K42: =IFERROR(IF(0=LEN(ReferenceData!$AB$42),"",ReferenceData!$AB$42),"") -> 640660 | L42: =IFERROR(IF(0=LEN(ReferenceData!$AA$42),"",ReferenceData!$AA$42),"") -> 791309 | M42: =IFERROR(IF(0=LEN(ReferenceData!$Z$42),"",ReferenceData!$Z$42),"") -> 753890 | N42: =IFERROR(IF(0=LEN(ReferenceData!$Y$42),"",ReferenceData!$Y$42),"") -> 777643 | O42: =IFERROR(IF(0=LEN(ReferenceData!$X$42),"",ReferenceData!$X$42),"") -> 844804 | P42: =IFERROR(IF(0=LEN(ReferenceData!$W$42),"",ReferenceData!$W$42),"") -> 1093110 | Q42: =IFERROR(IF(0=LEN(ReferenceData!$V$42),"",ReferenceData!$V$42),"") -> 1313370 | R42: =IFERROR(IF(0=LEN(ReferenceData!$U$42),"",ReferenceData!$U$42),"") -> 1306300 | S42: =IFERROR(IF(0=LEN(ReferenceData!$T$42),"",ReferenceData!$T$42),"") -> 1233450 | T42: =IFERROR(IF(0=LEN(ReferenceData!$S$42),"",ReferenceData!$S$42),"") -> 1396660 | U42: =IFERROR(IF(0=LEN(ReferenceData!$R$42),"",ReferenceData!$R$42),"") -> 1524740 | V42: =IFERROR(IF(0=LEN(ReferenceData!$Q$42),"",ReferenceData!$Q$42),"") -> 1374940 | W42: =IFERROR(IF(0=LEN(ReferenceData!$P$42),"",ReferenceData!$P$42),"") -> 1666250 | X42: =IFERROR(IF(0=LEN(ReferenceData!$O$42),"",ReferenceData!$O$42),"") -> 1869600 | Y42: =IFERROR(IF(0=LEN(ReferenceData!$N$42),"",ReferenceData!$N$42),"") -> 1926880 | Z42: =IFERROR(IF(0=LEN(ReferenceData!$M$42),"",ReferenceData!$M$42),"") -> 1603710 | AA42: =IFERROR(IF(0=LEN(ReferenceData!$L$42),"",ReferenceData!$L$42),"") -> 1659370 | AB42: =IFERROR(IF(0=LEN(ReferenceData!$K$42),"",ReferenceData!$K$42),"") -> 1821010 | AC42: =IFERROR(IF(0=LEN(ReferenceData!$J$42),"",ReferenceData!$J$42),"") -> 1920890 | AD42: =IFERROR(IF(0=LEN(ReferenceData!$I$42),"",ReferenceData!$I$42),"") -> 2081390 | AE42: =IFERROR(IF(0=LEN(ReferenceData!$H$42),"",ReferenceData!$H$42),"") -> 2085450 | AF42: =IFERROR(IF(0=LEN(ReferenceData!$G$42),"",ReferenceData!$G$42),"") -> 2484120 | AG42: =IFERROR(IF(0=LEN(ReferenceData!$F$42),"",ReferenceData!$F$42),"") -> 2803510
A43: =IFERROR(IF(0=LEN(ReferenceData!$A$43),"",ReferenceData!$A$43),"") -> Passive Non-Domestic Equity Mutual Funds | B43: =IFERROR(IF(0=LEN(ReferenceData!$B$43),"",ReferenceData!$B$43),"") -> .BIAMPNE G Index | C43: =IFERROR(IF(0=LEN(ReferenceData!$C$43),"",ReferenceData!$C$43),"") -> PR005 | D43: =IFERROR(IF(0=LEN(ReferenceData!$D$43),"",ReferenceData!$D$43),"") -> PX_LAST | E43: =IFERROR(IF(0=LEN(ReferenceData!$E$43),"",ReferenceData!$E$43),"") -> Dynamic | F43: =IFERROR(IF(0=LEN(ReferenceData!$AG$43),"",ReferenceData!$AG$43),"") -> 117899 | G43: =IFERROR(IF(0=LEN(ReferenceData!$AF$43),"",ReferenceData!$AF$43),"") -> 142564 | H43: =IFERROR(IF(0=LEN(ReferenceData!$AE$43),"",ReferenceData!$AE$43),"") -> 155984 | I43: =IFERROR(IF(0=LEN(ReferenceData!$AD$43),"",ReferenceData!$AD$43),"") -> 190022 | J43: =IFERROR(IF(0=LEN(ReferenceData!$AC$43),"",ReferenceData!$AC$43),"") -> 234128 | K43: =IFERROR(IF(0=LEN(ReferenceData!$AB$43),"",ReferenceData!$AB$43),"") -> 234741 | L43: =IFERROR(IF(0=LEN(ReferenceData!$AA$43),"",ReferenceData!$AA$43),"") -> 281937 | M43: =IFERROR(IF(0=LEN(ReferenceData!$Z$43),"",ReferenceData!$Z$43),"") -> 294634 | N43: =IFERROR(IF(0=LEN(ReferenceData!$Y$43),"",ReferenceData!$Y$43),"") -> 319017 | O43: =IFERROR(IF(0=LEN(ReferenceData!$X$43),"",ReferenceData!$X$43),"") -> 345767 | P43: =IFERROR(IF(0=LEN(ReferenceData!$W$43),"",ReferenceData!$W$43),"") -> 439903 | Q43: =IFERROR(IF(0=LEN(ReferenceData!$V$43),"",ReferenceData!$V$43),"") -> 520891 | R43: =IFERROR(IF(0=LEN(ReferenceData!$U$43),"",ReferenceData!$U$43),"") -> 534015 | S43: =IFERROR(IF(0=LEN(ReferenceData!$T$43),"",ReferenceData!$T$43),"") -> 508835 | T43: =IFERROR(IF(0=LEN(ReferenceData!$S$43),"",ReferenceData!$S$43),"") -> 591267 | U43: =IFERROR(IF(0=LEN(ReferenceData!$R$43),"",ReferenceData!$R$43),"") -> 650677 | V43: =IFERROR(IF(0=LEN(ReferenceData!$Q$43),"",ReferenceData!$Q$43),"") -> 606971 | W43: =IFERROR(IF(0=LEN(ReferenceData!$P$43),"",ReferenceData!$P$43),"") -> 660607 | X43: =IFERROR(IF(0=LEN(ReferenceData!$O$43),"",ReferenceData!$O$43),"") -> 680939 | Y43: =IFERROR(IF(0=LEN(ReferenceData!$N$43),"",ReferenceData!$N$43),"") -> 715520 | Z43: =IFERROR(IF(0=LEN(ReferenceData!$M$43),"",ReferenceData!$M$43),"") -> 585191 | AA43: =IFERROR(IF(0=LEN(ReferenceData!$L$43),"",ReferenceData!$L$43),"") -> 599071 | AB43: =IFERROR(IF(0=LEN(ReferenceData!$K$43),"",ReferenceData!$K$43),"") -> 658159 | AC43: =IFERROR(IF(0=LEN(ReferenceData!$J$43),"",ReferenceData!$J$43),"") -> 702504 | AD43: =IFERROR(IF(0=LEN(ReferenceData!$I$43),"",ReferenceData!$I$43),"") -> 753077 | AE43: =IFERROR(IF(0=LEN(ReferenceData!$H$43),"",ReferenceData!$H$43),"") -> 762550 | AF43: =IFERROR(IF(0=LEN(ReferenceData!$G$43),"",ReferenceData!$G$43),"") -> 890019 | AG43: =IFERROR(IF(0=LEN(ReferenceData!$F$43),"",ReferenceData!$F$43),"") -> 970725
A44: =IFERROR(IF(0=LEN(ReferenceData!$A$44),"",ReferenceData!$A$44),"") -> Passive Non-Domestic Equity ETFs | B44: =IFERROR(IF(0=LEN(ReferenceData!$B$44),"",ReferenceData!$B$44),"") | C44: =IFERROR(IF(0=LEN(ReferenceData!$C$44),"",ReferenceData!$C$44),"") | D44: =IFERROR(IF(0=LEN(ReferenceData!$D$44),"",ReferenceData!$D$44),"") | E44: =IFERROR(IF(0=LEN(ReferenceData!$E$44),"",ReferenceData!$E$44),"") -> Expression | F44: =IFERROR(IF(0=LEN(ReferenceData!$AG$44),"",ReferenceData!$AG$44),"") -> 254254 | G44: =IFERROR(IF(0=LEN(ReferenceData!$AF$44),"",ReferenceData!$AF$44),"") -> 328697 | H44: =IFERROR(IF(0=LEN(ReferenceData!$AE$44),"",ReferenceData!$AE$44),"") -> 318566 | I44: =IFERROR(IF(0=LEN(ReferenceData!$AD$44),"",ReferenceData!$AD$44),"") -> 389339 | J44: =IFERROR(IF(0=LEN(ReferenceData!$AC$44),"",ReferenceData!$AC$44),"") -> 435165 | K44: =IFERROR(IF(0=LEN(ReferenceData!$AB$44),"",ReferenceData!$AB$44),"") -> 405919 | L44: =IFERROR(IF(0=LEN(ReferenceData!$AA$44),"",ReferenceData!$AA$44),"") -> 509372 | M44: =IFERROR(IF(0=LEN(ReferenceData!$Z$44),"",ReferenceData!$Z$44),"") -> 459256 | N44: =IFERROR(IF(0=LEN(ReferenceData!$Y$44),"",ReferenceData!$Y$44),"") -> 458626 | O44: =IFERROR(IF(0=LEN(ReferenceData!$X$44),"",ReferenceData!$X$44),"") -> 499037 | P44: =IFERROR(IF(0=LEN(ReferenceData!$W$44),"",ReferenceData!$W$44),"") -> 653207 | Q44: =IFERROR(IF(0=LEN(ReferenceData!$V$44),"",ReferenceData!$V$44),"") -> 792479 | R44: =IFERROR(IF(0=LEN(ReferenceData!$U$44),"",ReferenceData!$U$44),"") -> 772285 | S44: =IFERROR(IF(0=LEN(ReferenceData!$T$44),"",ReferenceData!$T$44),"") -> 724615 | T44: =IFERROR(IF(0=LEN(ReferenceData!$S$44),"",ReferenceData!$S$44),"") -> 805393 | U44: =IFERROR(IF(0=LEN(ReferenceData!$R$44),"",ReferenceData!$R$44),"") -> 874063 | V44: =IFERROR(IF(0=LEN(ReferenceData!$Q$44),"",ReferenceData!$Q$44),"") -> 767969 | W44: =IFERROR(IF(0=LEN(ReferenceData!$P$44),"",ReferenceData!$P$44),"") -> 1005643 | X44: =IFERROR(IF(0=LEN(ReferenceData!$O$44),"",ReferenceData!$O$44),"") -> 1188661 | Y44: =IFERROR(IF(0=LEN(ReferenceData!$N$44),"",ReferenceData!$N$44),"") -> 1211360 | Z44: =IFERROR(IF(0=LEN(ReferenceData!$M$44),"",ReferenceData!$M$44),"") -> 1018519 | AA44: =IFERROR(IF(0=LEN(ReferenceData!$L$44),"",ReferenceData!$L$44),"") -> 1060299 | AB44: =IFERROR(IF(0=LEN(ReferenceData!$K$44),"",ReferenceData!$K$44),"") -> 1162851 | AC44: =IFERROR(IF(0=LEN(ReferenceData!$J$44),"",ReferenceData!$J$44),"") -> 1218386 | AD44: =IFERROR(IF(0=LEN(ReferenceData!$I$44),"",ReferenceData!$I$44),"") -> 1328313 | AE44: =IFERROR(IF(0=LEN(ReferenceData!$H$44),"",ReferenceData!$H$44),"") -> 1322900 | AF44: =IFERROR(IF(0=LEN(ReferenceData!$G$44),"",ReferenceData!$G$44),"") -> 1594101 | AG44: =IFERROR(IF(0=LEN(ReferenceData!$F$44),"",ReferenceData!$F$44),"") -> 1832785
A45: =IFERROR(IF(0=LEN(ReferenceData!$A$45),"",ReferenceData!$A$45),"") -> Active Non-Domestic Equity | B45: =IFERROR(IF(0=LEN(ReferenceData!$B$45),"",ReferenceData!$B$45),"") -> .BIATANE G Index | C45: =IFERROR(IF(0=LEN(ReferenceData!$C$45),"",ReferenceData!$C$45),"") -> PR005 | D45: =IFERROR(IF(0=LEN(ReferenceData!$D$45),"",ReferenceData!$D$45),"") -> PX_LAST | E45: =IFERROR(IF(0=LEN(ReferenceData!$E$45),"",ReferenceData!$E$45),"") -> Dynamic | F45: =IFERROR(IF(0=LEN(ReferenceData!$AG$45),"",ReferenceData!$AG$45),"") -> 1052740 | G45: =IFERROR(IF(0=LEN(ReferenceData!$AF$45),"",ReferenceData!$AF$45),"") -> 1208120 | H45: =IFERROR(IF(0=LEN(ReferenceData!$AE$45),"",ReferenceData!$AE$45),"") -> 1330860 | I45: =IFERROR(IF(0=LEN(ReferenceData!$AD$45),"",ReferenceData!$AD$45),"") -> 1578590 | J45: =IFERROR(IF(0=LEN(ReferenceData!$AC$45),"",ReferenceData!$AC$45),"") -> 1768490 | K45: =IFERROR(IF(0=LEN(ReferenceData!$AB$45),"",ReferenceData!$AB$45),"") -> 1661490 | L45: =IFERROR(IF(0=LEN(ReferenceData!$AA$45),"",ReferenceData!$AA$45),"") -> 1780050 | M45: =IFERROR(IF(0=LEN(ReferenceData!$Z$45),"",ReferenceData!$Z$45),"") -> 1612870 | N45: =IFERROR(IF(0=LEN(ReferenceData!$Y$45),"",ReferenceData!$Y$45),"") -> 1632190 | O45: =IFERROR(IF(0=LEN(ReferenceData!$X$45),"",ReferenceData!$X$45),"") -> 1649290 | P45: =IFERROR(IF(0=LEN(ReferenceData!$W$45),"",ReferenceData!$W$45),"") -> 1883600 | Q45: =IFERROR(IF(0=LEN(ReferenceData!$V$45),"",ReferenceData!$V$45),"") -> 2110100 | R45: =IFERROR(IF(0=LEN(ReferenceData!$U$45),"",ReferenceData!$U$45),"") -> 2065610 | S45: =IFERROR(IF(0=LEN(ReferenceData!$T$45),"",ReferenceData!$T$45),"") -> 1716320 | T45: =IFERROR(IF(0=LEN(ReferenceData!$S$45),"",ReferenceData!$S$45),"") -> 1906740 | U45: =IFERROR(IF(0=LEN(ReferenceData!$R$45),"",ReferenceData!$R$45),"") -> 2111490 | V45: =IFERROR(IF(0=LEN(ReferenceData!$Q$45),"",ReferenceData!$Q$45),"") -> 1951380 | W45: =IFERROR(IF(0=LEN(ReferenceData!$P$45),"",ReferenceData!$P$45),"") -> 2380530 | X45: =IFERROR(IF(0=LEN(ReferenceData!$O$45),"",ReferenceData!$O$45),"") -> 2592470 | Y45: =IFERROR(IF(0=LEN(ReferenceData!$N$45),"",ReferenceData!$N$45),"") -> 2566020 | Z45: =IFERROR(IF(0=LEN(ReferenceData!$M$45),"",ReferenceData!$M$45),"") -> 1979750 | AA45: =IFERROR(IF(0=LEN(ReferenceData!$L$45),"",ReferenceData!$L$45),"") -> 1942690 | AB45: =IFERROR(IF(0=LEN(ReferenceData!$K$45),"",ReferenceData!$K$45),"") -> 2120080 | AC45: =IFERROR(IF(0=LEN(ReferenceData!$J$45),"",ReferenceData!$J$45),"") -> 2167730 | AD45: =IFERROR(IF(0=LEN(ReferenceData!$I$45),"",ReferenceData!$I$45),"") -> 2327060 | AE45: =IFERROR(IF(0=LEN(ReferenceData!$H$45),"",ReferenceData!$H$45),"") -> 2272830 | AF45: =IFERROR(IF(0=LEN(ReferenceData!$G$45),"",ReferenceData!$G$45),"") -> 2566870 | AG45: =IFERROR(IF(0=LEN(ReferenceData!$F$45),"",ReferenceData!$F$45),"") -> 2747610
A46: =IFERROR(IF(0=LEN(ReferenceData!$A$46),"",ReferenceData!$A$46),"") -> Active Non-Domestic Equity Mutual Funds | B46: =IFERROR(IF(0=LEN(ReferenceData!$B$46),"",ReferenceData!$B$46),"") -> .BIAMANE G Index | C46: =IFERROR(IF(0=LEN(ReferenceData!$C$46),"",ReferenceData!$C$46),"") -> PR005 | D46: =IFERROR(IF(0=LEN(ReferenceData!$D$46),"",ReferenceData!$D$46),"") -> PX_LAST | E46: =IFERROR(IF(0=LEN(ReferenceData!$E$46),"",ReferenceData!$E$46),"") -> Dynamic | F46: =IFERROR(IF(0=LEN(ReferenceData!$AG$46),"",ReferenceData!$AG$46),"") -> 1048650 | G46: =IFERROR(IF(0=LEN(ReferenceData!$AF$46),"",ReferenceData!$AF$46),"") -> 1203210 | H46: =IFERROR(IF(0=LEN(ReferenceData!$AE$46),"",ReferenceData!$AE$46),"") -> 1325010 | I46: =IFERROR(IF(0=LEN(ReferenceData!$AD$46),"",ReferenceData!$AD$46),"") -> 1571010 | J46: =IFERROR(IF(0=LEN(ReferenceData!$AC$46),"",ReferenceData!$AC$46),"") -> 1758700 | K46: =IFERROR(IF(0=LEN(ReferenceData!$AB$46),"",ReferenceData!$AB$46),"") -> 1650780 | L46: =IFERROR(IF(0=LEN(ReferenceData!$AA$46),"",ReferenceData!$AA$46),"") -> 1766740 | M46: =IFERROR(IF(0=LEN(ReferenceData!$Z$46),"",ReferenceData!$Z$46),"") -> 1599910 | N46: =IFERROR(IF(0=LEN(ReferenceData!$Y$46),"",ReferenceData!$Y$46),"") -> 1617830 | O46: =IFERROR(IF(0=LEN(ReferenceData!$X$46),"",ReferenceData!$X$46),"") -> 1631830 | P46: =IFERROR(IF(0=LEN(ReferenceData!$W$46),"",ReferenceData!$W$46),"") -> 1862810 | Q46: =IFERROR(IF(0=LEN(ReferenceData!$V$46),"",ReferenceData!$V$46),"") -> 2084070 | R46: =IFERROR(IF(0=LEN(ReferenceData!$U$46),"",ReferenceData!$U$46),"") -> 2036830 | S46: =IFERROR(IF(0=LEN(ReferenceData!$T$46),"",ReferenceData!$T$46),"") -> 1691840 | T46: =IFERROR(IF(0=LEN(ReferenceData!$S$46),"",ReferenceData!$S$46),"") -> 1878750 | U46: =IFERROR(IF(0=LEN(ReferenceData!$R$46),"",ReferenceData!$R$46),"") -> 2080960 | V46: =IFERROR(IF(0=LEN(ReferenceData!$Q$46),"",ReferenceData!$Q$46),"") -> 1926130 | W46: =IFERROR(IF(0=LEN(ReferenceData!$P$46),"",ReferenceData!$P$46),"") -> 2345860 | X46: =IFERROR(IF(0=LEN(ReferenceData!$O$46),"",ReferenceData!$O$46),"") -> 2541580 | Y46: =IFERROR(IF(0=LEN(ReferenceData!$N$46),"",ReferenceData!$N$46),"") -> 2511110 | Z46: =IFERROR(IF(0=LEN(ReferenceData!$M$46),"",ReferenceData!$M$46),"") -> 1921050 | AA46: =IFERROR(IF(0=LEN(ReferenceData!$L$46),"",ReferenceData!$L$46),"") -> 1870030 | AB46: =IFERROR(IF(0=LEN(ReferenceData!$K$46),"",ReferenceData!$K$46),"") -> 2030110 | AC46: =IFERROR(IF(0=LEN(ReferenceData!$J$46),"",ReferenceData!$J$46),"") -> 2073740 | AD46: =IFERROR(IF(0=LEN(ReferenceData!$I$46),"",ReferenceData!$I$46),"") -> 2207350 | AE46: =IFERROR(IF(0=LEN(ReferenceData!$H$46),"",ReferenceData!$H$46),"") -> 2130090 | AF46: =IFERROR(IF(0=LEN(ReferenceData!$G$46),"",ReferenceData!$G$46),"") -> 2378210 | AG46: =IFERROR(IF(0=LEN(ReferenceData!$F$46),"",ReferenceData!$F$46),"") -> 2512530
A47: =IFERROR(IF(0=LEN(ReferenceData!$A$47),"",ReferenceData!$A$47),"") -> Active Non-Domestic Equity ETFs | B47: =IFERROR(IF(0=LEN(ReferenceData!$B$47),"",ReferenceData!$B$47),"") | C47: =IFERROR(IF(0=LEN(ReferenceData!$C$47),"",ReferenceData!$C$47),"") | D47: =IFERROR(IF(0=LEN(ReferenceData!$D$47),"",ReferenceData!$D$47),"") | E47: =IFERROR(IF(0=LEN(ReferenceData!$E$47),"",ReferenceData!$E$47),"") -> Expression | F47: =IFERROR(IF(0=LEN(ReferenceData!$AG$47),"",ReferenceData!$AG$47),"") -> 4090 | G47: =IFERROR(IF(0=LEN(ReferenceData!$AF$47),"",ReferenceData!$AF$47),"") -> 4910 | H47: =IFERROR(IF(0=LEN(ReferenceData!$AE$47),"",ReferenceData!$AE$47),"") -> 5850 | I47: =IFERROR(IF(0=LEN(ReferenceData!$AD$47),"",ReferenceData!$AD$47),"") -> 7580 | J47: =IFERROR(IF(0=LEN(ReferenceData!$AC$47),"",ReferenceData!$AC$47),"") -> 9790 | K47: =IFERROR(IF(0=LEN(ReferenceData!$AB$47),"",ReferenceData!$AB$47),"") -> 10710 | L47: =IFERROR(IF(0=LEN(ReferenceData!$AA$47),"",ReferenceData!$AA$47),"") -> 13310 | M47: =IFERROR(IF(0=LEN(ReferenceData!$Z$47),"",ReferenceData!$Z$47),"") -> 12960 | N47: =IFERROR(IF(0=LEN(ReferenceData!$Y$47),"",ReferenceData!$Y$47),"") -> 14360 | O47: =IFERROR(IF(0=LEN(ReferenceData!$X$47),"",ReferenceData!$X$47),"") -> 17460 | P47: =IFERROR(IF(0=LEN(ReferenceData!$W$47),"",ReferenceData!$W$47),"") -> 20790 | Q47: =IFERROR(IF(0=LEN(ReferenceData!$V$47),"",ReferenceData!$V$47),"") -> 26030 | R47: =IFERROR(IF(0=LEN(ReferenceData!$U$47),"",ReferenceData!$U$47),"") -> 28780 | S47: =IFERROR(IF(0=LEN(ReferenceData!$T$47),"",ReferenceData!$T$47),"") -> 24480 | T47: =IFERROR(IF(0=LEN(ReferenceData!$S$47),"",ReferenceData!$S$47),"") -> 27990 | U47: =IFERROR(IF(0=LEN(ReferenceData!$R$47),"",ReferenceData!$R$47),"") -> 30530 | V47: =IFERROR(IF(0=LEN(ReferenceData!$Q$47),"",ReferenceData!$Q$47),"") -> 25250 | W47: =IFERROR(IF(0=LEN(ReferenceData!$P$47),"",ReferenceData!$P$47),"") -> 34670 | X47: =IFERROR(IF(0=LEN(ReferenceData!$O$47),"",ReferenceData!$O$47),"") -> 50890 | Y47: =IFERROR(IF(0=LEN(ReferenceData!$N$47),"",ReferenceData!$N$47),"") -> 54910 | Z47: =IFERROR(IF(0=LEN(ReferenceData!$M$47),"",ReferenceData!$M$47),"") -> 58700 | AA47: =IFERROR(IF(0=LEN(ReferenceData!$L$47),"",ReferenceData!$L$47),"") -> 72660 | AB47: =IFERROR(IF(0=LEN(ReferenceData!$K$47),"",ReferenceData!$K$47),"") -> 89970 | AC47: =IFERROR(IF(0=LEN(ReferenceData!$J$47),"",ReferenceData!$J$47),"") -> 93990 | AD47: =IFERROR(IF(0=LEN(ReferenceData!$I$47),"",ReferenceData!$I$47),"") -> 119710 | AE47: =IFERROR(IF(0=LEN(ReferenceData!$H$47),"",ReferenceData!$H$47),"") -> 142740 | AF47: =IFERROR(IF(0=LEN(ReferenceData!$G$47),"",ReferenceData!$G$47),"") -> 188660 | AG47: =IFERROR(IF(0=LEN(ReferenceData!$F$47),"",ReferenceData!$F$47),"") -> 235080
A48: =IFERROR(IF(0=LEN(ReferenceData!$A$48),"",ReferenceData!$A$48),"") -> Money Market Fund Assets | B48: =IFERROR(IF(0=LEN(ReferenceData!$B$48),"",ReferenceData!$B$48),"") -> .BIATMMF G Index | C48: =IFERROR(IF(0=LEN(ReferenceData!$C$48),"",ReferenceData!$C$48),"") -> PR005 | D48: =IFERROR(IF(0=LEN(ReferenceData!$D$48),"",ReferenceData!$D$48),"") -> PX_LAST | E48: =IFERROR(IF(0=LEN(ReferenceData!$E$48),"",ReferenceData!$E$48),"") -> Dynamic | F48: =IFERROR(IF(0=LEN(ReferenceData!$AG$48),"",ReferenceData!$AG$48),"") -> 2259310 | G48: =IFERROR(IF(0=LEN(ReferenceData!$AF$48),"",ReferenceData!$AF$48),"") -> 2455210 | H48: =IFERROR(IF(0=LEN(ReferenceData!$AE$48),"",ReferenceData!$AE$48),"") -> 2374490 | I48: =IFERROR(IF(0=LEN(ReferenceData!$AD$48),"",ReferenceData!$AD$48),"") -> 2468760 | J48: =IFERROR(IF(0=LEN(ReferenceData!$AC$48),"",ReferenceData!$AC$48),"") -> 2345900 | K48: =IFERROR(IF(0=LEN(ReferenceData!$AB$48),"",ReferenceData!$AB$48),"") -> 2496190 | L48: =IFERROR(IF(0=LEN(ReferenceData!$AA$48),"",ReferenceData!$AA$48),"") -> 2403080 | M48: =IFERROR(IF(0=LEN(ReferenceData!$Z$48),"",ReferenceData!$Z$48),"") -> 2528710 | N48: =IFERROR(IF(0=LEN(ReferenceData!$Y$48),"",ReferenceData!$Y$48),"") -> 2573040 | O48: =IFERROR(IF(0=LEN(ReferenceData!$X$48),"",ReferenceData!$X$48),"") -> 2576040 | P48: =IFERROR(IF(0=LEN(ReferenceData!$W$48),"",ReferenceData!$W$48),"") -> 2535130 | Q48: =IFERROR(IF(0=LEN(ReferenceData!$V$48),"",ReferenceData!$V$48),"") -> 2711750 | R48: =IFERROR(IF(0=LEN(ReferenceData!$U$48),"",ReferenceData!$U$48),"") -> 2805100 | S48: =IFERROR(IF(0=LEN(ReferenceData!$T$48),"",ReferenceData!$T$48),"") -> 3101110 | T48: =IFERROR(IF(0=LEN(ReferenceData!$S$48),"",ReferenceData!$S$48),"") -> 3301810 | U48: =IFERROR(IF(0=LEN(ReferenceData!$R$48),"",ReferenceData!$R$48),"") -> 3653580 | V48: =IFERROR(IF(0=LEN(ReferenceData!$Q$48),"",ReferenceData!$Q$48),"") -> 4700780 | W48: =IFERROR(IF(0=LEN(ReferenceData!$P$48),"",ReferenceData!$P$48),"") -> 4333570 | X48: =IFERROR(IF(0=LEN(ReferenceData!$O$48),"",ReferenceData!$O$48),"") -> 4520180 | Y48: =IFERROR(IF(0=LEN(ReferenceData!$N$48),"",ReferenceData!$N$48),"") -> 4746740 | Z48: =IFERROR(IF(0=LEN(ReferenceData!$M$48),"",ReferenceData!$M$48),"") -> 4525330 | AA48: =IFERROR(IF(0=LEN(ReferenceData!$L$48),"",ReferenceData!$L$48),"") -> 4836920 | AB48: =IFERROR(IF(0=LEN(ReferenceData!$K$48),"",ReferenceData!$K$48),"") -> 5489180 | AC48: =IFERROR(IF(0=LEN(ReferenceData!$J$48),"",ReferenceData!$J$48),"") -> 5935110 | AD48: =IFERROR(IF(0=LEN(ReferenceData!$I$48),"",ReferenceData!$I$48),"") -> 6134540 | AE48: =IFERROR(IF(0=LEN(ReferenceData!$H$48),"",ReferenceData!$H$48),"") -> 6896160 | AF48: =IFERROR(IF(0=LEN(ReferenceData!$G$48),"",ReferenceData!$G$48),"") -> 7053280 | AG48: =IFERROR(IF(0=LEN(ReferenceData!$F$48),"",ReferenceData!$F$48),"") -> 7804590
A49: =IFERROR(IF(0=LEN(ReferenceData!$A$49),"",ReferenceData!$A$49),"") -> Ratio of Money Mkt Fund Assets to Traditional Fund Assets | B49: =IFERROR(IF(0=LEN(ReferenceData!$B$49),"",ReferenceData!$B$49),"") | C49: =IFERROR(IF(0=LEN(ReferenceData!$C$49),"",ReferenceData!$C$49),"") | D49: =IFERROR(IF(0=LEN(ReferenceData!$D$49),"",ReferenceData!$D$49),"") | E49: =IFERROR(IF(0=LEN(ReferenceData!$E$49),"",ReferenceData!$E$49),"") -> Expression | F49: =IFERROR(IF(0=LEN(ReferenceData!$AG$49),"",ReferenceData!$AG$49),"") -> 25.466196 | G49: =IFERROR(IF(0=LEN(ReferenceData!$AF$49),"",ReferenceData!$AF$49),"") -> 25.286678 | H49: =IFERROR(IF(0=LEN(ReferenceData!$AE$49),"",ReferenceData!$AE$49),"") -> 22.437426 | I49: =IFERROR(IF(0=LEN(ReferenceData!$AD$49),"",ReferenceData!$AD$49),"") -> 20.911292 | J49: =IFERROR(IF(0=LEN(ReferenceData!$AC$49),"",ReferenceData!$AC$49),"") -> 18.181607 | K49: =IFERROR(IF(0=LEN(ReferenceData!$AB$49),"",ReferenceData!$AB$49),"") -> 19.172305 | L49: =IFERROR(IF(0=LEN(ReferenceData!$AA$49),"",ReferenceData!$AA$49),"") -> 17.74283 | M49: =IFERROR(IF(0=LEN(ReferenceData!$Z$49),"",ReferenceData!$Z$49),"") -> 19.40826 | N49: =IFERROR(IF(0=LEN(ReferenceData!$Y$49),"",ReferenceData!$Y$49),"") -> 18.863003 | O49: =IFERROR(IF(0=LEN(ReferenceData!$X$49),"",ReferenceData!$X$49),"") -> 17.983932 | P49: =IFERROR(IF(0=LEN(ReferenceData!$W$49),"",ReferenceData!$W$49),"") -> 15.928696 | Q49: =IFERROR(IF(0=LEN(ReferenceData!$V$49),"",ReferenceData!$V$49),"") -> 15.575881 | R49: =IFERROR(IF(0=LEN(ReferenceData!$U$49),"",ReferenceData!$U$49),"") -> 15.752086 | S49: =IFERROR(IF(0=LEN(ReferenceData!$T$49),"",ReferenceData!$T$49),"") -> 18.988298 | T49: =IFERROR(IF(0=LEN(ReferenceData!$S$49),"",ReferenceData!$S$49),"") -> 17.760566 | U49: =IFERROR(IF(0=LEN(ReferenceData!$R$49),"",ReferenceData!$R$49),"") -> 17.962422 | V49: =IFERROR(IF(0=LEN(ReferenceData!$Q$49),"",ReferenceData!$Q$49),"") -> 23.707632 | W49: =IFERROR(IF(0=LEN(ReferenceData!$P$49),"",ReferenceData!$P$49),"") -> 18.512647 | X49: =IFERROR(IF(0=LEN(ReferenceData!$O$49),"",ReferenceData!$O$49),"") -> 17.215405 | Y49: =IFERROR(IF(0=LEN(ReferenceData!$N$49),"",ReferenceData!$N$49),"") -> 17.202946 | Z49: =IFERROR(IF(0=LEN(ReferenceData!$M$49),"",ReferenceData!$M$49),"") -> 19.918264 | AA49: =IFERROR(IF(0=LEN(ReferenceData!$L$49),"",ReferenceData!$L$49),"") -> 21.361751 | AB49: =IFERROR(IF(0=LEN(ReferenceData!$K$49),"",ReferenceData!$K$49),"") -> 22.245646 | AC49: =IFERROR(IF(0=LEN(ReferenceData!$J$49),"",ReferenceData!$J$49),"") -> 22.60512 | AD49: =IFERROR(IF(0=LEN(ReferenceData!$I$49),"",ReferenceData!$I$49),"") -> 21.273746 | AE49: =IFERROR(IF(0=LEN(ReferenceData!$H$49),"",ReferenceData!$H$49),"") -> 22.550767 | AF49: =IFERROR(IF(0=LEN(ReferenceData!$G$49),"",ReferenceData!$G$49),"") -> 21.610837 | AG49: =IFERROR(IF(0=LEN(ReferenceData!$F$49),"",ReferenceData!$F$49),"") -> 22.244996
A50: =IFERROR(IF(0=LEN(ReferenceData!$A$50),"",ReferenceData!$A$50),"") -> Ratio of Money Mkt Fund Assets to Total US Equity Market Cap | B50: =IFERROR(IF(0=LEN(ReferenceData!$B$50),"",ReferenceData!$B$50),"") -> WCAUUS Index | C50: =IFERROR(IF(0=LEN(ReferenceData!$C$50),"",ReferenceData!$C$50),"") | D50: =IFERROR(IF(0=LEN(ReferenceData!$D$50),"",ReferenceData!$D$50),"") | E50: =IFERROR(IF(0=LEN(ReferenceData!$E$50),"",ReferenceData!$E$50),"") -> Expression | F50: =IFERROR(IF(0=LEN(ReferenceData!$AG$50),"",ReferenceData!$AG$50),"") -> 13.965038 | G50: =IFERROR(IF(0=LEN(ReferenceData!$AF$50),"",ReferenceData!$AF$50),"") -> 14.566104 | H50: =IFERROR(IF(0=LEN(ReferenceData!$AE$50),"",ReferenceData!$AE$50),"") -> 12.480513 | I50: =IFERROR(IF(0=LEN(ReferenceData!$AD$50),"",ReferenceData!$AD$50),"") -> 11.080282 | J50: =IFERROR(IF(0=LEN(ReferenceData!$AC$50),"",ReferenceData!$AC$50),"") -> 9.9454587 | K50: =IFERROR(IF(0=LEN(ReferenceData!$AB$50),"",ReferenceData!$AB$50),"") -> 10.224538 | L50: =IFERROR(IF(0=LEN(ReferenceData!$AA$50),"",ReferenceData!$AA$50),"") -> 9.7969094 | M50: =IFERROR(IF(0=LEN(ReferenceData!$Z$50),"",ReferenceData!$Z$50),"") -> 10.740295 | N50: =IFERROR(IF(0=LEN(ReferenceData!$Y$50),"",ReferenceData!$Y$50),"") -> 10.989365 | O50: =IFERROR(IF(0=LEN(ReferenceData!$X$50),"",ReferenceData!$X$50),"") -> 10.220572 | P50: =IFERROR(IF(0=LEN(ReferenceData!$W$50),"",ReferenceData!$W$50),"") -> 9.390219 | Q50: =IFERROR(IF(0=LEN(ReferenceData!$V$50),"",ReferenceData!$V$50),"") -> 9.147597 | R50: =IFERROR(IF(0=LEN(ReferenceData!$U$50),"",ReferenceData!$U$50),"") -> 9.2884755 | S50: =IFERROR(IF(0=LEN(ReferenceData!$T$50),"",ReferenceData!$T$50),"") -> 11.540303 | T50: =IFERROR(IF(0=LEN(ReferenceData!$S$50),"",ReferenceData!$S$50),"") -> 10.374677 | U50: =IFERROR(IF(0=LEN(ReferenceData!$R$50),"",ReferenceData!$R$50),"") -> 10.628332 | V50: =IFERROR(IF(0=LEN(ReferenceData!$Q$50),"",ReferenceData!$Q$50),"") -> 14.332689 | W50: =IFERROR(IF(0=LEN(ReferenceData!$P$50),"",ReferenceData!$P$50),"") -> 10.162975 | X50: =IFERROR(IF(0=LEN(ReferenceData!$O$50),"",ReferenceData!$O$50),"") -> 9.10443 | Y50: =IFERROR(IF(0=LEN(ReferenceData!$N$50),"",ReferenceData!$N$50),"") -> 8.8287517 | Z50: =IFERROR(IF(0=LEN(ReferenceData!$M$50),"",ReferenceData!$M$50),"") -> 10.936271 | AA50: =IFERROR(IF(0=LEN(ReferenceData!$L$50),"",ReferenceData!$L$50),"") -> 11.779574 | AB50: =IFERROR(IF(0=LEN(ReferenceData!$K$50),"",ReferenceData!$K$50),"") -> 11.749683 | AC50: =IFERROR(IF(0=LEN(ReferenceData!$J$50),"",ReferenceData!$J$50),"") -> 11.760303 | AD50: =IFERROR(IF(0=LEN(ReferenceData!$I$50),"",ReferenceData!$I$50),"") -> 10.78617 | AE50: =IFERROR(IF(0=LEN(ReferenceData!$H$50),"",ReferenceData!$H$50),"") -> 11.125507 | AF50: =IFERROR(IF(0=LEN(ReferenceData!$G$50),"",ReferenceData!$G$50),"") -> 10.899931 | AG50: =IFERROR(IF(0=LEN(ReferenceData!$F$50),"",ReferenceData!$F$50),"")
A51: =IFERROR(IF(0=LEN(ReferenceData!$A$51),"",ReferenceData!$A$51),"") -> Ratio of Money Mkt Fund Assets to US M2 Money Supply | B51: =IFERROR(IF(0=LEN(ReferenceData!$B$51),"",ReferenceData!$B$51),"") -> M2 Index | C51: =IFERROR(IF(0=LEN(ReferenceData!$C$51),"",ReferenceData!$C$51),"") | D51: =IFERROR(IF(0=LEN(ReferenceData!$D$51),"",ReferenceData!$D$51),"") | E51: =IFERROR(IF(0=LEN(ReferenceData!$E$51),"",ReferenceData!$E$51),"") -> Expression | F51: =IFERROR(IF(0=LEN(ReferenceData!$AG$51),"",ReferenceData!$AG$51),"") -> 22.564218 | G51: =IFERROR(IF(0=LEN(ReferenceData!$AF$51),"",ReferenceData!$AF$51),"") -> 23.440773 | H51: =IFERROR(IF(0=LEN(ReferenceData!$AE$51),"",ReferenceData!$AE$51),"") -> 22.209554 | I51: =IFERROR(IF(0=LEN(ReferenceData!$AD$51),"",ReferenceData!$AD$51),"") -> 22.347989 | J51: =IFERROR(IF(0=LEN(ReferenceData!$AC$51),"",ReferenceData!$AC$51),"") -> 20.609165 | K51: =IFERROR(IF(0=LEN(ReferenceData!$AB$51),"",ReferenceData!$AB$51),"") -> 21.333134 | L51: =IFERROR(IF(0=LEN(ReferenceData!$AA$51),"",ReferenceData!$AA$51),"") -> 20.017993 | M51: =IFERROR(IF(0=LEN(ReferenceData!$Z$51),"",ReferenceData!$Z$51),"") -> 20.445255 | N51: =IFERROR(IF(0=LEN(ReferenceData!$Y$51),"",ReferenceData!$Y$51),"") -> 20.046903 | O51: =IFERROR(IF(0=LEN(ReferenceData!$X$51),"",ReferenceData!$X$51),"") -> 19.477385 | P51: =IFERROR(IF(0=LEN(ReferenceData!$W$51),"",ReferenceData!$W$51),"") -> 18.698269 | Q51: =IFERROR(IF(0=LEN(ReferenceData!$V$51),"",ReferenceData!$V$51),"") -> 19.546257 | R51: =IFERROR(IF(0=LEN(ReferenceData!$U$51),"",ReferenceData!$U$51),"") -> 19.880649 | S51: =IFERROR(IF(0=LEN(ReferenceData!$T$51),"",ReferenceData!$T$51),"") -> 21.561989 | T51: =IFERROR(IF(0=LEN(ReferenceData!$S$51),"",ReferenceData!$S$51),"") -> 22.353327 | U51: =IFERROR(IF(0=LEN(ReferenceData!$R$51),"",ReferenceData!$R$51),"") -> 23.805546 | V51: =IFERROR(IF(0=LEN(ReferenceData!$Q$51),"",ReferenceData!$Q$51),"") -> 25.913035 | W51: =IFERROR(IF(0=LEN(ReferenceData!$P$51),"",ReferenceData!$P$51),"") -> 22.649715 | X51: =IFERROR(IF(0=LEN(ReferenceData!$O$51),"",ReferenceData!$O$51),"") -> 22.078846 | Y51: =IFERROR(IF(0=LEN(ReferenceData!$N$51),"",ReferenceData!$N$51),"") -> 22.107783 | Z51: =IFERROR(IF(0=LEN(ReferenceData!$M$51),"",ReferenceData!$M$51),"") -> 20.909074 | AA51: =IFERROR(IF(0=LEN(ReferenceData!$L$51),"",ReferenceData!$L$51),"") -> 22.795231 | AB51: =IFERROR(IF(0=LEN(ReferenceData!$K$51),"",ReferenceData!$K$51),"") -> 26.412256 | AC51: =IFERROR(IF(0=LEN(ReferenceData!$J$51),"",ReferenceData!$J$51),"") -> 28.67009 | AD51: =IFERROR(IF(0=LEN(ReferenceData!$I$51),"",ReferenceData!$I$51),"") -> 29.138417 | AE51: =IFERROR(IF(0=LEN(ReferenceData!$H$51),"",ReferenceData!$H$51),"") -> 32.188196 | AF51: =IFERROR(IF(0=LEN(ReferenceData!$G$51),"",ReferenceData!$G$51),"") -> 32.144377 | AG51: =IFERROR(IF(0=LEN(ReferenceData!$F$51),"",ReferenceData!$F$51),"")
A52: =IFERROR(IF(0=LEN(ReferenceData!$A$52),"",ReferenceData!$A$52),"") -> ETF & Mutual fund AUM by Type ($MM) | B52: =IFERROR(IF(0=LEN(ReferenceData!$B$52),"",ReferenceData!$B$52),"") | C52: =IFERROR(IF(0=LEN(ReferenceData!$C$52),"",ReferenceData!$C$52),"") | D52: =IFERROR(IF(0=LEN(ReferenceData!$D$52),"",ReferenceData!$D$52),"") | E52: =IFERROR(IF(0=LEN(ReferenceData!$E$52),"",ReferenceData!$E$52),"") -> Heading | F52: =IFERROR(IF(0=LEN(ReferenceData!$AG$52),"",ReferenceData!$AG$52),"") | G52: =IFERROR(IF(0=LEN(ReferenceData!$AF$52),"",ReferenceData!$AF$52),"") | H52: =IFERROR(IF(0=LEN(ReferenceData!$AE$52),"",ReferenceData!$AE$52),"") | I52: =IFERROR(IF(0=LEN(ReferenceData!$AD$52),"",ReferenceData!$AD$52),"") | J52: =IFERROR(IF(0=LEN(ReferenceData!$AC$52),"",ReferenceData!$AC$52),"") | K52: =IFERROR(IF(0=LEN(ReferenceData!$AB$52),"",ReferenceData!$AB$52),"") | L52: =IFERROR(IF(0=LEN(ReferenceData!$AA$52),"",ReferenceData!$AA$52),"") | M52: =IFERROR(IF(0=LEN(ReferenceData!$Z$52),"",ReferenceData!$Z$52),"") | N52: =IFERROR(IF(0=LEN(ReferenceData!$Y$52),"",ReferenceData!$Y$52),"") | O52: =IFERROR(IF(0=LEN(ReferenceData!$X$52),"",ReferenceData!$X$52),"") | P52: =IFERROR(IF(0=LEN(ReferenceData!$W$52),"",ReferenceData!$W$52),"") | Q52: =IFERROR(IF(0=LEN(ReferenceData!$V$52),"",ReferenceData!$V$52),"") | R52: =IFERROR(IF(0=LEN(ReferenceData!$U$52),"",ReferenceData!$U$52),"") | S52: =IFERROR(IF(0=LEN(ReferenceData!$T$52),"",ReferenceData!$T$52),"") | T52: =IFERROR(IF(0=LEN(ReferenceData!$S$52),"",ReferenceData!$S$52),"") | U52: =IFERROR(IF(0=LEN(ReferenceData!$R$52),"",ReferenceData!$R$52),"") | V52: =IFERROR(IF(0=LEN(ReferenceData!$Q$52),"",ReferenceData!$Q$52),"") | W52: =IFERROR(IF(0=LEN(ReferenceData!$P$52),"",ReferenceData!$P$52),"") | X52: =IFERROR(IF(0=LEN(ReferenceData!$O$52),"",ReferenceData!$O$52),"") | Y52: =IFERROR(IF(0=LEN(ReferenceData!$N$52),"",ReferenceData!$N$52),"") | Z52: =IFERROR(IF(0=LEN(ReferenceData!$M$52),"",ReferenceData!$M$52),"") | AA52: =IFERROR(IF(0=LEN(ReferenceData!$L$52),"",ReferenceData!$L$52),"") | AB52: =IFERROR(IF(0=LEN(ReferenceData!$K$52),"",ReferenceData!$K$52),"") | AC52: =IFERROR(IF(0=LEN(ReferenceData!$J$52),"",ReferenceData!$J$52),"") | AD52: =IFERROR(IF(0=LEN(ReferenceData!$I$52),"",ReferenceData!$I$52),"") | AE52: =IFERROR(IF(0=LEN(ReferenceData!$H$52),"",ReferenceData!$H$52),"") | AF52: =IFERROR(IF(0=LEN(ReferenceData!$G$52),"",ReferenceData!$G$52),"") | AG52: =IFERROR(IF(0=LEN(ReferenceData!$F$52),"",ReferenceData!$F$52),"")
A53: =IFERROR(IF(0=LEN(ReferenceData!$A$53),"",ReferenceData!$A$53),"") -> All ETFs & Mutual Funds (estimated, smoothed) | B53: =IFERROR(IF(0=LEN(ReferenceData!$B$53),"",ReferenceData!$B$53),"") | C53: =IFERROR(IF(0=LEN(ReferenceData!$C$53),"",ReferenceData!$C$53),"") | D53: =IFERROR(IF(0=LEN(ReferenceData!$D$53),"",ReferenceData!$D$53),"") | E53: =IFERROR(IF(0=LEN(ReferenceData!$E$53),"",ReferenceData!$E$53),"") -> Sum | F53: =IFERROR(IF(0=LEN(ReferenceData!$AG$53),"",ReferenceData!$AG$53),"") -> 8871800 | G53: =IFERROR(IF(0=LEN(ReferenceData!$AF$53),"",ReferenceData!$AF$53),"") -> 9709500 | H53: =IFERROR(IF(0=LEN(ReferenceData!$AE$53),"",ReferenceData!$AE$53),"") -> 10582720 | I53: =IFERROR(IF(0=LEN(ReferenceData!$AD$53),"",ReferenceData!$AD$53),"") -> 11805870 | J53: =IFERROR(IF(0=LEN(ReferenceData!$AC$53),"",ReferenceData!$AC$53),"") -> 12902600 | K53: =IFERROR(IF(0=LEN(ReferenceData!$AB$53),"",ReferenceData!$AB$53),"") -> 13019770 | L53: =IFERROR(IF(0=LEN(ReferenceData!$AA$53),"",ReferenceData!$AA$53),"") -> 13543950 | M53: =IFERROR(IF(0=LEN(ReferenceData!$Z$53),"",ReferenceData!$Z$53),"") -> 13029040 | N53: =IFERROR(IF(0=LEN(ReferenceData!$Y$53),"",ReferenceData!$Y$53),"") -> 13640670 | O53: =IFERROR(IF(0=LEN(ReferenceData!$X$53),"",ReferenceData!$X$53),"") -> 14324120 | P53: =IFERROR(IF(0=LEN(ReferenceData!$W$53),"",ReferenceData!$W$53),"") -> 15915490 | Q53: =IFERROR(IF(0=LEN(ReferenceData!$V$53),"",ReferenceData!$V$53),"") -> 17409930 | R53: =IFERROR(IF(0=LEN(ReferenceData!$U$53),"",ReferenceData!$U$53),"") -> 17807800 | S53: =IFERROR(IF(0=LEN(ReferenceData!$T$53),"",ReferenceData!$T$53),"") -> 16331690 | T53: =IFERROR(IF(0=LEN(ReferenceData!$S$53),"",ReferenceData!$S$53),"") -> 18590680 | U53: =IFERROR(IF(0=LEN(ReferenceData!$R$53),"",ReferenceData!$R$53),"") -> 20340130 | V53: =IFERROR(IF(0=LEN(ReferenceData!$Q$53),"",ReferenceData!$Q$53),"") -> 19828130 | W53: =IFERROR(IF(0=LEN(ReferenceData!$P$53),"",ReferenceData!$P$53),"") -> 23408700 | X53: =IFERROR(IF(0=LEN(ReferenceData!$O$53),"",ReferenceData!$O$53),"") -> 26256600 | Y53: =IFERROR(IF(0=LEN(ReferenceData!$N$53),"",ReferenceData!$N$53),"") -> 27592600 | Z53: =IFERROR(IF(0=LEN(ReferenceData!$M$53),"",ReferenceData!$M$53),"") -> 22719500 | AA53: =IFERROR(IF(0=LEN(ReferenceData!$L$53),"",ReferenceData!$L$53),"") -> 22642900 | AB53: =IFERROR(IF(0=LEN(ReferenceData!$K$53),"",ReferenceData!$K$53),"") -> 24675300 | AC53: =IFERROR(IF(0=LEN(ReferenceData!$J$53),"",ReferenceData!$J$53),"") -> 26255600 | AD53: =IFERROR(IF(0=LEN(ReferenceData!$I$53),"",ReferenceData!$I$53),"") -> 28836200 | AE53: =IFERROR(IF(0=LEN(ReferenceData!$H$53),"",ReferenceData!$H$53),"") -> 30580600 | AF53: =IFERROR(IF(0=LEN(ReferenceData!$G$53),"",ReferenceData!$G$53),"") -> 32637700 | AG53: =IFERROR(IF(0=LEN(ReferenceData!$F$53),"",ReferenceData!$F$53),"") -> 35084700
A54: =IFERROR(IF(0=LEN(ReferenceData!$A$54),"",ReferenceData!$A$54),"") -> Mutual Funds | B54: =IFERROR(IF(0=LEN(ReferenceData!$B$54),"",ReferenceData!$B$54),"") | C54: =IFERROR(IF(0=LEN(ReferenceData!$C$54),"",ReferenceData!$C$54),"") | D54: =IFERROR(IF(0=LEN(ReferenceData!$D$54),"",ReferenceData!$D$54),"") | E54: =IFERROR(IF(0=LEN(ReferenceData!$E$54),"",ReferenceData!$E$54),"") -> Expression | F54: =IFERROR(IF(0=LEN(ReferenceData!$AG$54),"",ReferenceData!$AG$54),"") -> 7699140 | G54: =IFERROR(IF(0=LEN(ReferenceData!$AF$54),"",ReferenceData!$AF$54),"") -> 8388070 | H54: =IFERROR(IF(0=LEN(ReferenceData!$AE$54),"",ReferenceData!$AE$54),"") -> 9131150 | I54: =IFERROR(IF(0=LEN(ReferenceData!$AD$54),"",ReferenceData!$AD$54),"") -> 10122290 | J54: =IFERROR(IF(0=LEN(ReferenceData!$AC$54),"",ReferenceData!$AC$54),"") -> 11048400 | K54: =IFERROR(IF(0=LEN(ReferenceData!$AB$54),"",ReferenceData!$AB$54),"") -> 11037520 | L54: =IFERROR(IF(0=LEN(ReferenceData!$AA$54),"",ReferenceData!$AA$54),"") -> 11405980 | M54: =IFERROR(IF(0=LEN(ReferenceData!$Z$54),"",ReferenceData!$Z$54),"") -> 10930990 | N54: =IFERROR(IF(0=LEN(ReferenceData!$Y$54),"",ReferenceData!$Y$54),"") -> 11366320 | O54: =IFERROR(IF(0=LEN(ReferenceData!$X$54),"",ReferenceData!$X$54),"") -> 11738470 | P54: =IFERROR(IF(0=LEN(ReferenceData!$W$54),"",ReferenceData!$W$54),"") -> 12911950 | Q54: =IFERROR(IF(0=LEN(ReferenceData!$V$54),"",ReferenceData!$V$54),"") -> 13911140 | R54: =IFERROR(IF(0=LEN(ReferenceData!$U$54),"",ReferenceData!$U$54),"") -> 14203910 | S54: =IFERROR(IF(0=LEN(ReferenceData!$T$54),"",ReferenceData!$T$54),"") -> 12877700 | T54: =IFERROR(IF(0=LEN(ReferenceData!$S$54),"",ReferenceData!$S$54),"") -> 14568500 | U54: =IFERROR(IF(0=LEN(ReferenceData!$R$54),"",ReferenceData!$R$54),"") -> 15846370 | V54: =IFERROR(IF(0=LEN(ReferenceData!$Q$54),"",ReferenceData!$Q$54),"") -> 15361140 | W54: =IFERROR(IF(0=LEN(ReferenceData!$P$54),"",ReferenceData!$P$54),"") -> 17823690 | X54: =IFERROR(IF(0=LEN(ReferenceData!$O$54),"",ReferenceData!$O$54),"") -> 19660920 | Y54: =IFERROR(IF(0=LEN(ReferenceData!$N$54),"",ReferenceData!$N$54),"") -> 20357360 | Z54: =IFERROR(IF(0=LEN(ReferenceData!$M$54),"",ReferenceData!$M$54),"") -> 16443140 | AA54: =IFERROR(IF(0=LEN(ReferenceData!$L$54),"",ReferenceData!$L$54),"") -> 16060910 | AB54: =IFERROR(IF(0=LEN(ReferenceData!$K$54),"",ReferenceData!$K$54),"") -> 17315390 | AC54: =IFERROR(IF(0=LEN(ReferenceData!$J$54),"",ReferenceData!$J$54),"") -> 18107990 | AD54: =IFERROR(IF(0=LEN(ReferenceData!$I$54),"",ReferenceData!$I$54),"") -> 19548480 | AE54: =IFERROR(IF(0=LEN(ReferenceData!$H$54),"",ReferenceData!$H$54),"") -> 20150880 | AF54: =IFERROR(IF(0=LEN(ReferenceData!$G$54),"",ReferenceData!$G$54),"") -> 21097640 | AG54: =IFERROR(IF(0=LEN(ReferenceData!$F$54),"",ReferenceData!$F$54),"") -> 22075840
A55: =IFERROR(IF(0=LEN(ReferenceData!$A$55),"",ReferenceData!$A$55),"") -> ETFs | B55: =IFERROR(IF(0=LEN(ReferenceData!$B$55),"",ReferenceData!$B$55),"") | C55: =IFERROR(IF(0=LEN(ReferenceData!$C$55),"",ReferenceData!$C$55),"") | D55: =IFERROR(IF(0=LEN(ReferenceData!$D$55),"",ReferenceData!$D$55),"") | E55: =IFERROR(IF(0=LEN(ReferenceData!$E$55),"",ReferenceData!$E$55),"") -> Expression | F55: =IFERROR(IF(0=LEN(ReferenceData!$AG$55),"",ReferenceData!$AG$55),"") -> 1172660 | G55: =IFERROR(IF(0=LEN(ReferenceData!$AF$55),"",ReferenceData!$AF$55),"") -> 1321430 | H55: =IFERROR(IF(0=LEN(ReferenceData!$AE$55),"",ReferenceData!$AE$55),"") -> 1451570 | I55: =IFERROR(IF(0=LEN(ReferenceData!$AD$55),"",ReferenceData!$AD$55),"") -> 1683580 | J55: =IFERROR(IF(0=LEN(ReferenceData!$AC$55),"",ReferenceData!$AC$55),"") -> 1854200 | K55: =IFERROR(IF(0=LEN(ReferenceData!$AB$55),"",ReferenceData!$AB$55),"") -> 1982250 | L55: =IFERROR(IF(0=LEN(ReferenceData!$AA$55),"",ReferenceData!$AA$55),"") -> 2137970 | M55: =IFERROR(IF(0=LEN(ReferenceData!$Z$55),"",ReferenceData!$Z$55),"") -> 2098050 | N55: =IFERROR(IF(0=LEN(ReferenceData!$Y$55),"",ReferenceData!$Y$55),"") -> 2274350 | O55: =IFERROR(IF(0=LEN(ReferenceData!$X$55),"",ReferenceData!$X$55),"") -> 2585650 | P55: =IFERROR(IF(0=LEN(ReferenceData!$W$55),"",ReferenceData!$W$55),"") -> 3003540 | Q55: =IFERROR(IF(0=LEN(ReferenceData!$V$55),"",ReferenceData!$V$55),"") -> 3498790 | R55: =IFERROR(IF(0=LEN(ReferenceData!$U$55),"",ReferenceData!$U$55),"") -> 3603890 | S55: =IFERROR(IF(0=LEN(ReferenceData!$T$55),"",ReferenceData!$T$55),"") -> 3453990 | T55: =IFERROR(IF(0=LEN(ReferenceData!$S$55),"",ReferenceData!$S$55),"") -> 4022180 | U55: =IFERROR(IF(0=LEN(ReferenceData!$R$55),"",ReferenceData!$R$55),"") -> 4493760 | V55: =IFERROR(IF(0=LEN(ReferenceData!$Q$55),"",ReferenceData!$Q$55),"") -> 4466990 | W55: =IFERROR(IF(0=LEN(ReferenceData!$P$55),"",ReferenceData!$P$55),"") -> 5585010 | X55: =IFERROR(IF(0=LEN(ReferenceData!$O$55),"",ReferenceData!$O$55),"") -> 6595680 | Y55: =IFERROR(IF(0=LEN(ReferenceData!$N$55),"",ReferenceData!$N$55),"") -> 7235240 | Z55: =IFERROR(IF(0=LEN(ReferenceData!$M$55),"",ReferenceData!$M$55),"") -> 6276360 | AA55: =IFERROR(IF(0=LEN(ReferenceData!$L$55),"",ReferenceData!$L$55),"") -> 6581990 | AB55: =IFERROR(IF(0=LEN(ReferenceData!$K$55),"",ReferenceData!$K$55),"") -> 7359910 | AC55: =IFERROR(IF(0=LEN(ReferenceData!$J$55),"",ReferenceData!$J$55),"") -> 8147610 | AD55: =IFERROR(IF(0=LEN(ReferenceData!$I$55),"",ReferenceData!$I$55),"") -> 9287720 | AE55: =IFERROR(IF(0=LEN(ReferenceData!$H$55),"",ReferenceData!$H$55),"") -> 10429720 | AF55: =IFERROR(IF(0=LEN(ReferenceData!$G$55),"",ReferenceData!$G$55),"") -> 11540060 | AG55: =IFERROR(IF(0=LEN(ReferenceData!$F$55),"",ReferenceData!$F$55),"") -> 13008860
A56: =IFERROR(IF(0=LEN(ReferenceData!$A$56),"",ReferenceData!$A$56),"") -> US Listed ETFs & Mutual Funds | B56: =IFERROR(IF(0=LEN(ReferenceData!$B$56),"",ReferenceData!$B$56),"") | C56: =IFERROR(IF(0=LEN(ReferenceData!$C$56),"",ReferenceData!$C$56),"") | D56: =IFERROR(IF(0=LEN(ReferenceData!$D$56),"",ReferenceData!$D$56),"") | E56: =IFERROR(IF(0=LEN(ReferenceData!$E$56),"",ReferenceData!$E$56),"") -> Heading | F56: =IFERROR(IF(0=LEN(ReferenceData!$AG$56),"",ReferenceData!$AG$56),"") | G56: =IFERROR(IF(0=LEN(ReferenceData!$AF$56),"",ReferenceData!$AF$56),"") | H56: =IFERROR(IF(0=LEN(ReferenceData!$AE$56),"",ReferenceData!$AE$56),"") | I56: =IFERROR(IF(0=LEN(ReferenceData!$AD$56),"",ReferenceData!$AD$56),"") | J56: =IFERROR(IF(0=LEN(ReferenceData!$AC$56),"",ReferenceData!$AC$56),"") | K56: =IFERROR(IF(0=LEN(ReferenceData!$AB$56),"",ReferenceData!$AB$56),"") | L56: =IFERROR(IF(0=LEN(ReferenceData!$AA$56),"",ReferenceData!$AA$56),"") | M56: =IFERROR(IF(0=LEN(ReferenceData!$Z$56),"",ReferenceData!$Z$56),"") | N56: =IFERROR(IF(0=LEN(ReferenceData!$Y$56),"",ReferenceData!$Y$56),"") | O56: =IFERROR(IF(0=LEN(ReferenceData!$X$56),"",ReferenceData!$X$56),"") | P56: =IFERROR(IF(0=LEN(ReferenceData!$W$56),"",ReferenceData!$W$56),"") | Q56: =IFERROR(IF(0=LEN(ReferenceData!$V$56),"",ReferenceData!$V$56),"") | R56: =IFERROR(IF(0=LEN(ReferenceData!$U$56),"",ReferenceData!$U$56),"") | S56: =IFERROR(IF(0=LEN(ReferenceData!$T$56),"",ReferenceData!$T$56),"") | T56: =IFERROR(IF(0=LEN(ReferenceData!$S$56),"",ReferenceData!$S$56),"") | U56: =IFERROR(IF(0=LEN(ReferenceData!$R$56),"",ReferenceData!$R$56),"") | V56: =IFERROR(IF(0=LEN(ReferenceData!$Q$56),"",ReferenceData!$Q$56),"") | W56: =IFERROR(IF(0=LEN(ReferenceData!$P$56),"",ReferenceData!$P$56),"") | X56: =IFERROR(IF(0=LEN(ReferenceData!$O$56),"",ReferenceData!$O$56),"") | Y56: =IFERROR(IF(0=LEN(ReferenceData!$N$56),"",ReferenceData!$N$56),"") | Z56: =IFERROR(IF(0=LEN(ReferenceData!$M$56),"",ReferenceData!$M$56),"") | AA56: =IFERROR(IF(0=LEN(ReferenceData!$L$56),"",ReferenceData!$L$56),"") | AB56: =IFERROR(IF(0=LEN(ReferenceData!$K$56),"",ReferenceData!$K$56),"") | AC56: =IFERROR(IF(0=LEN(ReferenceData!$J$56),"",ReferenceData!$J$56),"") | AD56: =IFERROR(IF(0=LEN(ReferenceData!$I$56),"",ReferenceData!$I$56),"") | AE56: =IFERROR(IF(0=LEN(ReferenceData!$H$56),"",ReferenceData!$H$56),"") | AF56: =IFERROR(IF(0=LEN(ReferenceData!$G$56),"",ReferenceData!$G$56),"") | AG56: =IFERROR(IF(0=LEN(ReferenceData!$F$56),"",ReferenceData!$F$56),"")
A57: =IFERROR(IF(0=LEN(ReferenceData!$A$57),"",ReferenceData!$A$57),"") -> Data is based on estimates from sample of over 10,000 funds | B57: =IFERROR(IF(0=LEN(ReferenceData!$B$57),"",ReferenceData!$B$57),"") | C57: =IFERROR(IF(0=LEN(ReferenceData!$C$57),"",ReferenceData!$C$57),"") | D57: =IFERROR(IF(0=LEN(ReferenceData!$D$57),"",ReferenceData!$D$57),"") | E57: =IFERROR(IF(0=LEN(ReferenceData!$E$57),"",ReferenceData!$E$57),"") -> Heading | F57: =IFERROR(IF(0=LEN(ReferenceData!$AG$57),"",ReferenceData!$AG$57),"") | G57: =IFERROR(IF(0=LEN(ReferenceData!$AF$57),"",ReferenceData!$AF$57),"") | H57: =IFERROR(IF(0=LEN(ReferenceData!$AE$57),"",ReferenceData!$AE$57),"") | I57: =IFERROR(IF(0=LEN(ReferenceData!$AD$57),"",ReferenceData!$AD$57),"") | J57: =IFERROR(IF(0=LEN(ReferenceData!$AC$57),"",ReferenceData!$AC$57),"") | K57: =IFERROR(IF(0=LEN(ReferenceData!$AB$57),"",ReferenceData!$AB$57),"") | L57: =IFERROR(IF(0=LEN(ReferenceData!$AA$57),"",ReferenceData!$AA$57),"") | M57: =IFERROR(IF(0=LEN(ReferenceData!$Z$57),"",ReferenceData!$Z$57),"") | N57: =IFERROR(IF(0=LEN(ReferenceData!$Y$57),"",ReferenceData!$Y$57),"") | O57: =IFERROR(IF(0=LEN(ReferenceData!$X$57),"",ReferenceData!$X$57),"") | P57: =IFERROR(IF(0=LEN(ReferenceData!$W$57),"",ReferenceData!$W$57),"") | Q57: =IFERROR(IF(0=LEN(ReferenceData!$V$57),"",ReferenceData!$V$57),"") | R57: =IFERROR(IF(0=LEN(ReferenceData!$U$57),"",ReferenceData!$U$57),"") | S57: =IFERROR(IF(0=LEN(ReferenceData!$T$57),"",ReferenceData!$T$57),"") | T57: =IFERROR(IF(0=LEN(ReferenceData!$S$57),"",ReferenceData!$S$57),"") | U57: =IFERROR(IF(0=LEN(ReferenceData!$R$57),"",ReferenceData!$R$57),"") | V57: =IFERROR(IF(0=LEN(ReferenceData!$Q$57),"",ReferenceData!$Q$57),"") | W57: =IFERROR(IF(0=LEN(ReferenceData!$P$57),"",ReferenceData!$P$57),"") | X57: =IFERROR(IF(0=LEN(ReferenceData!$O$57),"",ReferenceData!$O$57),"") | Y57: =IFERROR(IF(0=LEN(ReferenceData!$N$57),"",ReferenceData!$N$57),"") | Z57: =IFERROR(IF(0=LEN(ReferenceData!$M$57),"",ReferenceData!$M$57),"") | AA57: =IFERROR(IF(0=LEN(ReferenceData!$L$57),"",ReferenceData!$L$57),"") | AB57: =IFERROR(IF(0=LEN(ReferenceData!$K$57),"",ReferenceData!$K$57),"") | AC57: =IFERROR(IF(0=LEN(ReferenceData!$J$57),"",ReferenceData!$J$57),"") | AD57: =IFERROR(IF(0=LEN(ReferenceData!$I$57),"",ReferenceData!$I$57),"") | AE57: =IFERROR(IF(0=LEN(ReferenceData!$H$57),"",ReferenceData!$H$57),"") | AF57: =IFERROR(IF(0=LEN(ReferenceData!$G$57),"",ReferenceData!$G$57),"") | AG57: =IFERROR(IF(0=LEN(ReferenceData!$F$57),"",ReferenceData!$F$57),"")
A58: =IFERROR(IF(0=LEN(ReferenceData!$A$58),"",ReferenceData!$A$58),"") -> Source: BI & BBG Funds Database | B58: =IFERROR(IF(0=LEN(ReferenceData!$B$58),"",ReferenceData!$B$58),"") | C58: =IFERROR(IF(0=LEN(ReferenceData!$C$58),"",ReferenceData!$C$58),"") | D58: =IFERROR(IF(0=LEN(ReferenceData!$D$58),"",ReferenceData!$D$58),"") | E58: =IFERROR(IF(0=LEN(ReferenceData!$E$58),"",ReferenceData!$E$58),"") -> Heading | F58: =IFERROR(IF(0=LEN(ReferenceData!$AG$58),"",ReferenceData!$AG$58),"") | G58: =IFERROR(IF(0=LEN(ReferenceData!$AF$58),"",ReferenceData!$AF$58),"") | H58: =IFERROR(IF(0=LEN(ReferenceData!$AE$58),"",ReferenceData!$AE$58),"") | I58: =IFERROR(IF(0=LEN(ReferenceData!$AD$58),"",ReferenceData!$AD$58),"") | J58: =IFERROR(IF(0=LEN(ReferenceData!$AC$58),"",ReferenceData!$AC$58),"") | K58: =IFERROR(IF(0=LEN(ReferenceData!$AB$58),"",ReferenceData!$AB$58),"") | L58: =IFERROR(IF(0=LEN(ReferenceData!$AA$58),"",ReferenceData!$AA$58),"") | M58: =IFERROR(IF(0=LEN(ReferenceData!$Z$58),"",ReferenceData!$Z$58),"") | N58: =IFERROR(IF(0=LEN(ReferenceData!$Y$58),"",ReferenceData!$Y$58),"") | O58: =IFERROR(IF(0=LEN(ReferenceData!$X$58),"",ReferenceData!$X$58),"") | P58: =IFERROR(IF(0=LEN(ReferenceData!$W$58),"",ReferenceData!$W$58),"") | Q58: =IFERROR(IF(0=LEN(ReferenceData!$V$58),"",ReferenceData!$V$58),"") | R58: =IFERROR(IF(0=LEN(ReferenceData!$U$58),"",ReferenceData!$U$58),"") | S58: =IFERROR(IF(0=LEN(ReferenceData!$T$58),"",ReferenceData!$T$58),"") | T58: =IFERROR(IF(0=LEN(ReferenceData!$S$58),"",ReferenceData!$S$58),"") | U58: =IFERROR(IF(0=LEN(ReferenceData!$R$58),"",ReferenceData!$R$58),"") | V58: =IFERROR(IF(0=LEN(ReferenceData!$Q$58),"",ReferenceData!$Q$58),"") | W58: =IFERROR(IF(0=LEN(ReferenceData!$P$58),"",ReferenceData!$P$58),"") | X58: =IFERROR(IF(0=LEN(ReferenceData!$O$58),"",ReferenceData!$O$58),"") | Y58: =IFERROR(IF(0=LEN(ReferenceData!$N$58),"",ReferenceData!$N$58),"") | Z58: =IFERROR(IF(0=LEN(ReferenceData!$M$58),"",ReferenceData!$M$58),"") | AA58: =IFERROR(IF(0=LEN(ReferenceData!$L$58),"",ReferenceData!$L$58),"") | AB58: =IFERROR(IF(0=LEN(ReferenceData!$K$58),"",ReferenceData!$K$58),"") | AC58: =IFERROR(IF(0=LEN(ReferenceData!$J$58),"",ReferenceData!$J$58),"") | AD58: =IFERROR(IF(0=LEN(ReferenceData!$I$58),"",ReferenceData!$I$58),"") | AE58: =IFERROR(IF(0=LEN(ReferenceData!$H$58),"",ReferenceData!$H$58),"") | AF58: =IFERROR(IF(0=LEN(ReferenceData!$G$58),"",ReferenceData!$G$58),"") | AG58: =IFERROR(IF(0=LEN(ReferenceData!$F$58),"",ReferenceData!$F$58),"")

Sheet ReferenceData
A2: ="Description" -> Description | B2: ="Ticker" -> Ticker | C2: ="Field ID" -> Field ID | D2: ="Field Mnemonic" -> Field Mnemonic | E2: ="Data State" -> Data State | F2: =ReferenceData!$C$118 -> 2025 S2 | G2: =ReferenceData!$D$118 -> 2025 S1 | H2: =ReferenceData!$E$118 -> 2024 S2 | I2: =ReferenceData!$F$118 -> 2024 S1 | J2: =ReferenceData!$G$118 -> 2023 S2 | K2: =ReferenceData!$H$118 -> 2023 S1 | L2: =ReferenceData!$I$118 -> 2022 S2 | M2: =ReferenceData!$J$118 -> 2022 S1 | N2: =ReferenceData!$K$118 -> 2021 S2 | O2: =ReferenceData!$L$118 -> 2021 S1 | P2: =ReferenceData!$M$118 -> 2020 S2 | Q2: =ReferenceData!$N$118 -> 2020 S1 | R2: =ReferenceData!$O$118 -> 2019 S2 | S2: =ReferenceData!$P$118 -> 2019 S1 | T2: =ReferenceData!$Q$118 -> 2018 S2 | U2: =ReferenceData!$R$118 -> 2018 S1 | V2: =ReferenceData!$S$118 -> 2017 S2 | W2: =ReferenceData!$T$118 -> 2017 S1 | X2: =ReferenceData!$U$118 -> 2016 S2 | Y2: =ReferenceData!$V$118 -> 2016 S1 | Z2: =ReferenceData!$W$118 -> 2015 S2 | AA2: =ReferenceData!$X$118 -> 2015 S1 | AB2: =ReferenceData!$Y$118 -> 2014 S2 | AC2: =ReferenceData!$Z$118 -> 2014 S1 | AD2: =ReferenceData!$AA$118 -> 2013 S2 | AE2: =ReferenceData!$AB$118 -> 2013 S1 | AF2: =ReferenceData!$AC$118 -> 2012 S2 | AG2: =ReferenceData!$AD$118 -> 2012 S1 | AH2: =$C$118 -> 2025 S2 | AI2: =$D$118 -> 2025 S1 | AJ2: =$E$118 -> 2024 S2 | AK2: =$F$118 -> 2024 S1 | AL2: =$G$118 -> 2023 S2 | AM2: =$H$118 -> 2023 S1 | AN2: =$I$118 -> 2022 S2 | AO2: =$J$118 -> 2022 S1 | AP2: =$K$118 -> 2021 S2 | AQ2: =$L$118 -> 2021 S1 | AR2: =$M$118 -> 2020 S2 | AS2: =$N$118 -> 2020 S1 | AT2: =$O$118 -> 2019 S2 | AU2: =$P$118 -> 2019 S1 | AV2: =$Q$118 -> 2018 S2 | AW2: =$R$118 -> 2018 S1 | AX2: =$S$118 -> 2017 S2 | AY2: =$T$118 -> 2017 S1 | AZ2: =$U$118 -> 2016 S2 | BA2: =$V$118 -> 2016 S1 | BB2: =$W$118 -> 2015 S2 | BC2: =$X$118 -> 2015 S1 | BD2: =$Y$118 -> 2014 S2 | BE2: =$Z$118 -> 2014 S1 | BF2: =$AA$118 -> 2013 S2 | BG2: =$AB$118 -> 2013 S1 | BH2: =$AC$118 -> 2012 S2 | BI2: =$AD$118 -> 2012 S1
A3: ="ETFs as % Of Total Fund Assets (MF & ETF)" -> ETFs as % Of Total Fund Assets (MF & ETF) | B3: ="" | E3: ="Expression" -> Expression | F3: =IF(AND($B$74=1,LEN($F$16) * LEN($F$19) * LEN($F$13)>0),(($F$16+$F$19)/($F$13))*100,HLOOKUP(INDIRECT(ADDRESS(2,COLUMN())),OFFSET($AH$2,0,0,ROW()-1,28),ROW()-1,FALSE)) -> 37.078442 | G3: =IF(AND($B$74=1,LEN($G$16) * LEN($G$19) * LEN($G$13)>0),(($G$16+$G$19)/($G$13))*100,HLOOKUP(INDIRECT(ADDRESS(2,COLUMN())),OFFSET($AH$2,0,0,ROW()-1,28),ROW()-1,FALSE)) -> 35.358068 | H3: =IF(AND($B$74=1,LEN($H$16) * LEN($H$19) * LEN($H$13)>0),(($H$16+$H$19)/($H$13))*100,HLOOKUP(INDIRECT(ADDRESS(2,COLUMN())),OFFSET($AH$2,0,0,ROW()-1,28),ROW()-1,FALSE)) -> 34.105675 | I3: =IF(AND($B$74=1,LEN($I$16) * LEN($I$19) * LEN($I$13)>0),(($I$16+$I$19)/($I$13))*100,HLOOKUP(INDIRECT(ADDRESS(2,COLUMN())),OFFSET($AH$2,0,0,ROW()-1,28),ROW()-1,FALSE)) -> 32.208543 | J3: =IF(AND($B$74=1,LEN($J$16) * LEN($J$19) * LEN($J$13)>0),(($J$16+$J$19)/($J$13))*100,HLOOKUP(INDIRECT(ADDRESS(2,COLUMN())),OFFSET($AH$2,0,0,ROW()-1,28),ROW()-1,FALSE)) -> 31.031894 | K3: =IF(AND($B$74=1,LEN($K$16) * LEN($K$19) * LEN($K$13)>0),(($K$16+$K$19)/($K$13))*100,HLOOKUP(INDIRECT(ADDRESS(2,COLUMN())),OFFSET($AH$2,0,0,ROW()-1,28),ROW()-1,FALSE)) -> 29.827034 | L3: =IF(AND($B$74=1,LEN($L$16) * LEN($L$19) * LEN($L$13)>0),(($L$16+$L$19)/($L$13))*100,HLOOKUP(INDIRECT(ADDRESS(2,COLUMN())),OFFSET($AH$2,0,0,ROW()-1,28),ROW()-1,FALSE)) -> 29.068671 | M3: =IF(AND($B$74=1,LEN($M$16) * LEN($M$19) * LEN($M$13)>0),(($M$16+$M$19)/($M$13))*100,HLOOKUP(INDIRECT(ADDRESS(2,COLUMN())),OFFSET($AH$2,0,0,ROW()-1,28),ROW()-1,FALSE)) -> 27.625432 | N3: =IF(AND($B$74=1,LEN($N$16) * LEN($N$19) * LEN($N$13)>0),(($N$16+$N$19)/($N$13))*100,HLOOKUP(INDIRECT(ADDRESS(2,COLUMN())),OFFSET($AH$2,0,0,ROW()-1,28),ROW()-1,FALSE)) -> 26.221668 | O3: =IF(AND($B$74=1,LEN($O$16) * LEN($O$19) * LEN($O$13)>0),(($O$16+$O$19)/($O$13))*100,HLOOKUP(INDIRECT(ADDRESS(2,COLUMN())),OFFSET($AH$2,0,0,ROW()-1,28),ROW()-1,FALSE)) -> 25.120084 | P3: =IF(AND($B$74=1,LEN($P$16) * LEN($P$19) * LEN($P$13)>0),(($P$16+$P$19)/($P$13))*100,HLOOKUP(INDIRECT(ADDRESS(2,COLUMN())),OFFSET($AH$2,0,0,ROW()-1,28),ROW()-1,FALSE)) -> 23.858694 | Q3: =IF(AND($B$74=1,LEN($Q$16) * LEN($Q$19) * LEN($Q$13)>0),(($Q$16+$Q$19)/($Q$13))*100,HLOOKUP(INDIRECT(ADDRESS(2,COLUMN())),OFFSET($AH$2,0,0,ROW()-1,28),ROW()-1,FALSE)) -> 22.528549 | R3: =IF(AND($B$74=1,LEN($R$16) * LEN($R$19) * LEN($R$13)>0),(($R$16+$R$19)/($R$13))*100,HLOOKUP(INDIRECT(ADDRESS(2,COLUMN())),OFFSET($AH$2,0,0,ROW()-1,28),ROW()-1,FALSE)) -> 22.093074 | S3: =IF(AND($B$74=1,LEN($S$16) * LEN($S$19) * LEN($S$13)>0),(($S$16+$S$19)/($S$13))*100,HLOOKUP(INDIRECT(ADDRESS(2,COLUMN())),OFFSET($AH$2,0,0,ROW()-1,28),ROW()-1,FALSE)) -> 21.635465 | T3: =IF(AND($B$74=1,LEN($T$16) * LEN($T$19) * LEN($T$13)>0),(($T$16+$T$19)/($T$13))*100,HLOOKUP(INDIRECT(ADDRESS(2,COLUMN())),OFFSET($AH$2,0,0,ROW()-1,28),ROW()-1,FALSE)) -> 21.149005 | U3: =IF(AND($B$74=1,LEN($U$16) * LEN($U$19) * LEN($U$13)>0),(($U$16+$U$19)/($U$13))*100,HLOOKUP(INDIRECT(ADDRESS(2,COLUMN())),OFFSET($AH$2,0,0,ROW()-1,28),ROW()-1,FALSE)) -> 20.237705 | V3: =IF(AND($B$74=1,LEN($V$16) * LEN($V$19) * LEN($V$13)>0),(($V$16+$V$19)/($V$13))*100,HLOOKUP(INDIRECT(ADDRESS(2,COLUMN())),OFFSET($AH$2,0,0,ROW()-1,28),ROW()-1,FALSE)) -> 20.09652 | W3: =IF(AND($B$74=1,LEN($W$16) * LEN($W$19) * LEN($W$13)>0),(($W$16+$W$19)/($W$13))*100,HLOOKUP(INDIRECT(ADDRESS(2,COLUMN())),OFFSET($AH$2,0,0,ROW()-1,28),ROW()-1,FALSE)) -> 18.871804 | X3: =IF(AND($B$74=1,LEN($X$16) * LEN($X$19) * LEN($X$13)>0),(($X$16+$X$19)/($X$13))*100,HLOOKUP(INDIRECT(ADDRESS(2,COLUMN())),OFFSET($AH$2,0,0,ROW()-1,28),ROW()-1,FALSE)) -> 18.051022 | Y3: =IF(AND($B$74=1,LEN($Y$16) * LEN($Y$19) * LEN($Y$13)>0),(($Y$16+$Y$19)/($Y$13))*100,HLOOKUP(INDIRECT(ADDRESS(2,COLUMN())),OFFSET($AH$2,0,0,ROW()-1,28),ROW()-1,FALSE)) -> 16.673301 | Z3: =IF(AND($B$74=1,LEN($Z$16) * LEN($Z$19) * LEN($Z$13)>0),(($Z$16+$Z$19)/($Z$13))*100,HLOOKUP(INDIRECT(ADDRESS(2,COLUMN())),OFFSET($AH$2,0,0,ROW()-1,28),ROW()-1,FALSE)) -> 16.102875 | AA3: =IF(AND($B$74=1,LEN($AA$16) * LEN($AA$19) * LEN($AA$13)>0),(($AA$16+$AA$19)/($AA$13))*100,HLOOKUP(INDIRECT(ADDRESS(2,COLUMN())),OFFSET($AH$2,0,0,ROW()-1,28),ROW()-1,FALSE)) -> 15.785424 | AB3: =IF(AND($B$74=1,LEN($AB$16) * LEN($AB$19) * LEN($AB$13)>0),(($AB$16+$AB$19)/($AB$13))*100,HLOOKUP(INDIRECT(ADDRESS(2,COLUMN())),OFFSET($AH$2,0,0,ROW()-1,28),ROW()-1,FALSE)) -> 15.224923 | AC3: =IF(AND($B$74=1,LEN($AC$16) * LEN($AC$19) * LEN($AC$13)>0),(($AC$16+$AC$19)/($AC$13))*100,HLOOKUP(INDIRECT(ADDRESS(2,COLUMN())),OFFSET($AH$2,0,0,ROW()-1,28),ROW()-1,FALSE)) -> 14.370747 | AD3: =IF(AND($B$74=1,LEN($AD$16) * LEN($AD$19) * LEN($AD$13)>0),(($AD$16+$AD$19)/($AD$13))*100,HLOOKUP(INDIRECT(ADDRESS(2,COLUMN())),OFFSET($AH$2,0,0,ROW()-1,28),ROW()-1,FALSE)) -> 14.260533 | AE3: =IF(AND($B$74=1,LEN($AE$16) * LEN($AE$19) * LEN($AE$13)>0),(($AE$16+$AE$19)/($AE$13))*100,HLOOKUP(INDIRECT(ADDRESS(2,COLUMN())),OFFSET($AH$2,0,0,ROW()-1,28),ROW()-1,FALSE)) -> 13.716417 | AF3: =IF(AND($B$74=1,LEN($AF$16) * LEN($AF$19) * LEN($AF$13)>0),(($AF$16+$AF$19)/($AF$13))*100,HLOOKUP(INDIRECT(ADDRESS(2,COLUMN())),OFFSET($AH$2,0,0,ROW()-1,28),ROW()-1,FALSE)) -> 13.609661 | AG3: =IF(AND($B$74=1,LEN($AG$16) * LEN($AG$19) * LEN($AG$13)>0),(($AG$16+$AG$19)/($AG$13))*100,HLOOKUP(INDIRECT(ADDRESS(2,COLUMN())),OFFSET($AH$2,0,0,ROW()-1,28),ROW()-1,FALSE)) -> 13.217836 | AH3: =37.0784416 -> 37.078442 | AI3: =35.35806751 -> 35.358068 | AJ3: =34.10567484 -> 34.105675 | AK3: =32.20854343 -> 32.208543 | AL3: =31.03189415 -> 31.031894 | AM3: =29.82703351 -> 29.827034 | AN3: =29.06867053 -> 29.068671 | AO3: =27.6254319 -> 27.625432 | AP3: =26.22166813 -> 26.221668 | AQ3: =25.12008409 -> 25.120084 | AR3: =23.85869356 -> 23.858694 | AS3: =22.52854909 -> 22.528549 | AT3: =22.09307413 -> 22.093074 | AU3: =21.63546465 -> 21.635465 | AV3: =21.1490054 -> 21.149005 | AW3: =20.23770483 -> 20.237705 | AX3: =20.09651963 -> 20.09652 | AY3: =18.87180351 -> 18.871804 | AZ3: =18.05102163 -> 18.051022 | BA3: =16.67330124 -> 16.673301 | BB3: =16.10287481 -> 16.102875 | BC3: =15.78542449 -> 15.785424 | BD3: =15.22492333 -> 15.224923 | BE3: =14.37074698 -> 14.370747 | BF3: =14.26053311 -> 14.260533 | BG3: =13.71641695 -> 13.716417 | BH3: =13.60966064 -> 13.609661 | BI3: =13.21783629 -> 13.217836
A4: ="ETFs as % Of Equity Fund Assets (MF & ETF)" -> ETFs as % Of Equity Fund Assets (MF & ETF) | B4: ="" | E4: ="Expression" -> Expression | F4: =IF(AND($B$74=1,LEN($F$33) * LEN($F$30) * LEN($F$27)>0),(($F$33+$F$30)/($F$27))*100,HLOOKUP(INDIRECT(ADDRESS(2,COLUMN())),OFFSET($AH$2,0,0,ROW()-1,28),ROW()-1,FALSE)) -> 40.405625 | G4: =IF(AND($B$74=1,LEN($G$33) * LEN($G$30) * LEN($G$27)>0),(($G$33+$G$30)/($G$27))*100,HLOOKUP(INDIRECT(ADDRESS(2,COLUMN())),OFFSET($AH$2,0,0,ROW()-1,28),ROW()-1,FALSE)) -> 38.517793 | H4: =IF(AND($B$74=1,LEN($H$33) * LEN($H$30) * LEN($H$27)>0),(($H$33+$H$30)/($H$27))*100,HLOOKUP(INDIRECT(ADDRESS(2,COLUMN())),OFFSET($AH$2,0,0,ROW()-1,28),ROW()-1,FALSE)) -> 37.546944 | I4: =IF(AND($B$74=1,LEN($I$33) * LEN($I$30) * LEN($I$27)>0),(($I$33+$I$30)/($I$27))*100,HLOOKUP(INDIRECT(ADDRESS(2,COLUMN())),OFFSET($AH$2,0,0,ROW()-1,28),ROW()-1,FALSE)) -> 35.565675 | J4: =IF(AND($B$74=1,LEN($J$33) * LEN($J$30) * LEN($J$27)>0),(($J$33+$J$30)/($J$27))*100,HLOOKUP(INDIRECT(ADDRESS(2,COLUMN())),OFFSET($AH$2,0,0,ROW()-1,28),ROW()-1,FALSE)) -> 34.533582 | K4: =IF(AND($B$74=1,LEN($K$33) * LEN($K$30) * LEN($K$27)>0),(($K$33+$K$30)/($K$27))*100,HLOOKUP(INDIRECT(ADDRESS(2,COLUMN())),OFFSET($AH$2,0,0,ROW()-1,28),ROW()-1,FALSE)) -> 33.307887 | L4: =IF(AND($B$74=1,LEN($L$33) * LEN($L$30) * LEN($L$27)>0),(($L$33+$L$30)/($L$27))*100,HLOOKUP(INDIRECT(ADDRESS(2,COLUMN())),OFFSET($AH$2,0,0,ROW()-1,28),ROW()-1,FALSE)) -> 32.998992 | M4: =IF(AND($B$74=1,LEN($M$33) * LEN($M$30) * LEN($M$27)>0),(($M$33+$M$30)/($M$27))*100,HLOOKUP(INDIRECT(ADDRESS(2,COLUMN())),OFFSET($AH$2,0,0,ROW()-1,28),ROW()-1,FALSE)) -> 31.845603 | N4: =IF(AND($B$74=1,LEN($N$33) * LEN($N$30) * LEN($N$27)>0),(($N$33+$N$30)/($N$27))*100,HLOOKUP(INDIRECT(ADDRESS(2,COLUMN())),OFFSET($AH$2,0,0,ROW()-1,28),ROW()-1,FALSE)) -> 30.197149 | O4: =IF(AND($B$74=1,LEN($O$33) * LEN($O$30) * LEN($O$27)>0),(($O$33+$O$30)/($O$27))*100,HLOOKUP(INDIRECT(ADDRESS(2,COLUMN())),OFFSET($AH$2,0,0,ROW()-1,28),ROW()-1,FALSE)) -> 28.927924 | P4: =IF(AND($B$74=1,LEN($P$33) * LEN($P$30) * LEN($P$27)>0),(($P$33+$P$30)/($P$27))*100,HLOOKUP(INDIRECT(ADDRESS(2,COLUMN())),OFFSET($AH$2,0,0,ROW()-1,28),ROW()-1,FALSE)) -> 27.335587 | Q4: =IF(AND($B$74=1,LEN($Q$33) * LEN($Q$30) * LEN($Q$27)>0),(($Q$33+$Q$30)/($Q$27))*100,HLOOKUP(INDIRECT(ADDRESS(2,COLUMN())),OFFSET($AH$2,0,0,ROW()-1,28),ROW()-1,FALSE)) -> 25.835629 | R4: =IF(AND($B$74=1,LEN($R$33) * LEN($R$30) * LEN($R$27)>0),(($R$33+$R$30)/($R$27))*100,HLOOKUP(INDIRECT(ADDRESS(2,COLUMN())),OFFSET($AH$2,0,0,ROW()-1,28),ROW()-1,FALSE)) -> 25.914774 | S4: =IF(AND($B$74=1,LEN($S$33) * LEN($S$30) * LEN($S$27)>0),(($S$33+$S$30)/($S$27))*100,HLOOKUP(INDIRECT(ADDRESS(2,COLUMN())),OFFSET($AH$2,0,0,ROW()-1,28),ROW()-1,FALSE)) -> 25.510193 | T4: =IF(AND($B$74=1,LEN($T$33) * LEN($T$30) * LEN($T$27)>0),(($T$33+$T$30)/($T$27))*100,HLOOKUP(INDIRECT(ADDRESS(2,COLUMN())),OFFSET($AH$2,0,0,ROW()-1,28),ROW()-1,FALSE)) -> 25.357024 | U4: =IF(AND($B$74=1,LEN($U$33) * LEN($U$30) * LEN($U$27)>0),(($U$33+$U$30)/($U$27))*100,HLOOKUP(INDIRECT(ADDRESS(2,COLUMN())),OFFSET($AH$2,0,0,ROW()-1,28),ROW()-1,FALSE)) -> 24.1134 | V4: =IF(AND($B$74=1,LEN($V$33) * LEN($V$30) * LEN($V$27)>0),(($V$33+$V$30)/($V$27))*100,HLOOKUP(INDIRECT(ADDRESS(2,COLUMN())),OFFSET($AH$2,0,0,ROW()-1,28),ROW()-1,FALSE)) -> 24.075207 | W4: =IF(AND($B$74=1,LEN($W$33) * LEN($W$30) * LEN($W$27)>0),(($W$33+$W$30)/($W$27))*100,HLOOKUP(INDIRECT(ADDRESS(2,COLUMN())),OFFSET($AH$2,0,0,ROW()-1,28),ROW()-1,FALSE)) -> 22.733653 | X4: =IF(AND($B$74=1,LEN($X$33) * LEN($X$30) * LEN($X$27)>0),(($X$33+$X$30)/($X$27))*100,HLOOKUP(INDIRECT(ADDRESS(2,COLUMN())),OFFSET($AH$2,0,0,ROW()-1,28),ROW()-1,FALSE)) -> 22.073154 | Y4: =IF(AND($B$74=1,LEN($Y$33) * LEN($Y$30) * LEN($Y$27)>0),(($Y$33+$Y$30)/($Y$27))*100,HLOOKUP(INDIRECT(ADDRESS(2,COLUMN())),OFFSET($AH$2,0,0,ROW()-1,28),ROW()-1,FALSE)) -> 20.249502 | Z4: =IF(AND($B$74=1,LEN($Z$33) * LEN($Z$30) * LEN($Z$27)>0),(($Z$33+$Z$30)/($Z$27))*100,HLOOKUP(INDIRECT(ADDRESS(2,COLUMN())),OFFSET($AH$2,0,0,ROW()-1,28),ROW()-1,FALSE)) -> 19.886805 | AA4: =IF(AND($B$74=1,LEN($AA$33) * LEN($AA$30) * LEN($AA$27)>0),(($AA$33+$AA$30)/($AA$27))*100,HLOOKUP(INDIRECT(ADDRESS(2,COLUMN())),OFFSET($AH$2,0,0,ROW()-1,28),ROW()-1,FALSE)) -> 19.550153 | AB4: =IF(AND($B$74=1,LEN($AB$33) * LEN($AB$30) * LEN($AB$27)>0),(($AB$33+$AB$30)/($AB$27))*100,HLOOKUP(INDIRECT(ADDRESS(2,COLUMN())),OFFSET($AH$2,0,0,ROW()-1,28),ROW()-1,FALSE)) -> 18.957734 | AC4: =IF(AND($B$74=1,LEN($AC$33) * LEN($AC$30) * LEN($AC$27)>0),(($AC$33+$AC$30)/($AC$27))*100,HLOOKUP(INDIRECT(ADDRESS(2,COLUMN())),OFFSET($AH$2,0,0,ROW()-1,28),ROW()-1,FALSE)) -> 17.945907 | AD4: =IF(AND($B$74=1,LEN($AD$33) * LEN($AD$30) * LEN($AD$27)>0),(($AD$33+$AD$30)/($AD$27))*100,HLOOKUP(INDIRECT(ADDRESS(2,COLUMN())),OFFSET($AH$2,0,0,ROW()-1,28),ROW()-1,FALSE)) -> 17.835893 | AE4: =IF(AND($B$74=1,LEN($AE$33) * LEN($AE$30) * LEN($AE$27)>0),(($AE$33+$AE$30)/($AE$27))*100,HLOOKUP(INDIRECT(ADDRESS(2,COLUMN())),OFFSET($AH$2,0,0,ROW()-1,28),ROW()-1,FALSE)) -> 17.331619 | AF4: =IF(AND($B$74=1,LEN($AF$33) * LEN($AF$30) * LEN($AF$27)>0),(($AF$33+$AF$30)/($AF$27))*100,HLOOKUP(INDIRECT(ADDRESS(2,COLUMN())),OFFSET($AH$2,0,0,ROW()-1,28),ROW()-1,FALSE)) -> 16.974729 | AG4: =IF(AND($B$74=1,LEN($AG$33) * LEN($AG$30) * LEN($AG$27)>0),(($AG$33+$AG$30)/($AG$27))*100,HLOOKUP(INDIRECT(ADDRESS(2,COLUMN())),OFFSET($AH$2,0,0,ROW()-1,28),ROW()-1,FALSE)) -> 16.258832 | AH4: =40.40562533 -> 40.405625 | AI4: =38.51779305 -> 38.517793 | AJ4: =37.54694356 -> 37.546944 | AK4: =35.56567488 -> 35.565675 | AL4: =34.53358166 -> 34.533582 | AM4: =33.30788654 -> 33.307887 | AN4: =32.99899166 -> 32.998992 | AO4: =31.84560328 -> 31.845603 | AP4: =30.19714933 -> 30.197149 | AQ4: =28.92792354 -> 28.927924 | AR4: =27.33558717 -> 27.335587 | AS4: =25.83562906 -> 25.835629 | AT4: =25.91477353 -> 25.914774 | AU4: =25.51019259 -> 25.510193 | AV4: =25.35702438 -> 25.357024 | AW4: =24.11340045 -> 24.1134 | AX4: =24.07520703 -> 24.075207 | AY4: =22.73365323 -> 22.733653 | AZ4: =22.07315416 -> 22.073154 | BA4: =20.24950212 -> 20.249502 | BB4: =19.8868052 -> 19.886805 | BC4: =19.55015264 -> 19.550153 | BD4: =18.957734 -> 18.957734 | BE4: =17.94590713 -> 17.945907 | BF4: =17.83589311 -> 17.835893 | BG4: =17.3316186 -> 17.331619 | BH4: =16.97472858 -> 16.974729 | BI4: =16.25883189 -> 16.258832
A5: ="ETFs as % Of Bond Fund Assets (MF & ETF)" -> ETFs as % Of Bond Fund Assets (MF & ETF) | B5: ="" | E5: ="Expression" -> Expression | F5: =IF(AND($B$74=1,LEN($F$23) * LEN($F$26) * LEN($F$20)>0),(($F$23+$F$26)/($F$20))*100,HLOOKUP(INDIRECT(ADDRESS(2,COLUMN())),OFFSET($AH$2,0,0,ROW()-1,28),ROW()-1,FALSE)) -> 29.70135 | G5: =IF(AND($B$74=1,LEN($G$23) * LEN($G$26) * LEN($G$20)>0),(($G$23+$G$26)/($G$20))*100,HLOOKUP(INDIRECT(ADDRESS(2,COLUMN())),OFFSET($AH$2,0,0,ROW()-1,28),ROW()-1,FALSE)) -> 28.762254 | H5: =IF(AND($B$74=1,LEN($H$23) * LEN($H$26) * LEN($H$20)>0),(($H$23+$H$26)/($H$20))*100,HLOOKUP(INDIRECT(ADDRESS(2,COLUMN())),OFFSET($AH$2,0,0,ROW()-1,28),ROW()-1,FALSE)) -> 27.24881 | I5: =IF(AND($B$74=1,LEN($I$23) * LEN($I$26) * LEN($I$20)>0),(($I$23+$I$26)/($I$20))*100,HLOOKUP(INDIRECT(ADDRESS(2,COLUMN())),OFFSET($AH$2,0,0,ROW()-1,28),ROW()-1,FALSE)) -> 26.128748 | J5: =IF(AND($B$74=1,LEN($J$23) * LEN($J$26) * LEN($J$20)>0),(($J$23+$J$26)/($J$20))*100,HLOOKUP(INDIRECT(ADDRESS(2,COLUMN())),OFFSET($AH$2,0,0,ROW()-1,28),ROW()-1,FALSE)) -> 25.469519 | K5: =IF(AND($B$74=1,LEN($K$23) * LEN($K$26) * LEN($K$20)>0),(($K$23+$K$26)/($K$20))*100,HLOOKUP(INDIRECT(ADDRESS(2,COLUMN())),OFFSET($AH$2,0,0,ROW()-1,28),ROW()-1,FALSE)) -> 24.507879 | L5: =IF(AND($B$74=1,LEN($L$23) * LEN($L$26) * LEN($L$20)>0),(($L$23+$L$26)/($L$20))*100,HLOOKUP(INDIRECT(ADDRESS(2,COLUMN())),OFFSET($AH$2,0,0,ROW()-1,28),ROW()-1,FALSE)) -> 23.275326 | M5: =IF(AND($B$74=1,LEN($M$23) * LEN($M$26) * LEN($M$20)>0),(($M$23+$M$26)/($M$20))*100,HLOOKUP(INDIRECT(ADDRESS(2,COLUMN())),OFFSET($AH$2,0,0,ROW()-1,28),ROW()-1,FALSE)) -> 20.9858 | N5: =IF(AND($B$74=1,LEN($N$23) * LEN($N$26) * LEN($N$20)>0),(($N$23+$N$26)/($N$20))*100,HLOOKUP(INDIRECT(ADDRESS(2,COLUMN())),OFFSET($AH$2,0,0,ROW()-1,28),ROW()-1,FALSE)) -> 19.089849 | O5: =IF(AND($B$74=1,LEN($O$23) * LEN($O$26) * LEN($O$20)>0),(($O$23+$O$26)/($O$20))*100,HLOOKUP(INDIRECT(ADDRESS(2,COLUMN())),OFFSET($AH$2,0,0,ROW()-1,28),ROW()-1,FALSE)) -> 18.516782 | P5: =IF(AND($B$74=1,LEN($P$23) * LEN($P$26) * LEN($P$20)>0),(($P$23+$P$26)/($P$20))*100,HLOOKUP(INDIRECT(ADDRESS(2,COLUMN())),OFFSET($AH$2,0,0,ROW()-1,28),ROW()-1,FALSE)) -> 18.192209 | Q5: =IF(AND($B$74=1,LEN($Q$23) * LEN($Q$26) * LEN($Q$20)>0),(($Q$23+$Q$26)/($Q$20))*100,HLOOKUP(INDIRECT(ADDRESS(2,COLUMN())),OFFSET($AH$2,0,0,ROW()-1,28),ROW()-1,FALSE)) -> 17.96908 | R5: =IF(AND($B$74=1,LEN($R$23) * LEN($R$26) * LEN($R$20)>0),(($R$23+$R$26)/($R$20))*100,HLOOKUP(INDIRECT(ADDRESS(2,COLUMN())),OFFSET($AH$2,0,0,ROW()-1,28),ROW()-1,FALSE)) -> 16.415011 | S5: =IF(AND($B$74=1,LEN($S$23) * LEN($S$26) * LEN($S$20)>0),(($S$23+$S$26)/($S$20))*100,HLOOKUP(INDIRECT(ADDRESS(2,COLUMN())),OFFSET($AH$2,0,0,ROW()-1,28),ROW()-1,FALSE)) -> 16.049755 | T5: =IF(AND($B$74=1,LEN($T$23) * LEN($T$26) * LEN($T$20)>0),(($T$23+$T$26)/($T$20))*100,HLOOKUP(INDIRECT(ADDRESS(2,COLUMN())),OFFSET($AH$2,0,0,ROW()-1,28),ROW()-1,FALSE)) -> 15.259093 | U5: =IF(AND($B$74=1,LEN($U$23) * LEN($U$26) * LEN($U$20)>0),(($U$23+$U$26)/($U$20))*100,HLOOKUP(INDIRECT(ADDRESS(2,COLUMN())),OFFSET($AH$2,0,0,ROW()-1,28),ROW()-1,FALSE)) -> 14.188845 | V5: =IF(AND($B$74=1,LEN($V$23) * LEN($V$26) * LEN($V$20)>0),(($V$23+$V$26)/($V$20))*100,HLOOKUP(INDIRECT(ADDRESS(2,COLUMN())),OFFSET($AH$2,0,0,ROW()-1,28),ROW()-1,FALSE)) -> 13.824428 | W5: =IF(AND($B$74=1,LEN($W$23) * LEN($W$26) * LEN($W$20)>0),(($W$23+$W$26)/($W$20))*100,HLOOKUP(INDIRECT(ADDRESS(2,COLUMN())),OFFSET($AH$2,0,0,ROW()-1,28),ROW()-1,FALSE)) -> 13.180263 | X5: =IF(AND($B$74=1,LEN($X$23) * LEN($X$26) * LEN($X$20)>0),(($X$23+$X$26)/($X$20))*100,HLOOKUP(INDIRECT(ADDRESS(2,COLUMN())),OFFSET($AH$2,0,0,ROW()-1,28),ROW()-1,FALSE)) -> 12.216942 | Y5: =IF(AND($B$74=1,LEN($Y$23) * LEN($Y$26) * LEN($Y$20)>0),(($Y$23+$Y$26)/($Y$20))*100,HLOOKUP(INDIRECT(ADDRESS(2,COLUMN())),OFFSET($AH$2,0,0,ROW()-1,28),ROW()-1,FALSE)) -> 11.58322 | Z5: =IF(AND($B$74=1,LEN($Z$23) * LEN($Z$26) * LEN($Z$20)>0),(($Z$23+$Z$26)/($Z$20))*100,HLOOKUP(INDIRECT(ADDRESS(2,COLUMN())),OFFSET($AH$2,0,0,ROW()-1,28),ROW()-1,FALSE)) -> 10.622748 | AA5: =IF(AND($B$74=1,LEN($AA$23) * LEN($AA$26) * LEN($AA$20)>0),(($AA$23+$AA$26)/($AA$20))*100,HLOOKUP(INDIRECT(ADDRESS(2,COLUMN())),OFFSET($AH$2,0,0,ROW()-1,28),ROW()-1,FALSE)) -> 9.6919105 | AB5: =IF(AND($B$74=1,LEN($AB$23) * LEN($AB$26) * LEN($AB$20)>0),(($AB$23+$AB$26)/($AB$20))*100,HLOOKUP(INDIRECT(ADDRESS(2,COLUMN())),OFFSET($AH$2,0,0,ROW()-1,28),ROW()-1,FALSE)) -> 9.2535089 | AC5: =IF(AND($B$74=1,LEN($AC$23) * LEN($AC$26) * LEN($AC$20)>0),(($AC$23+$AC$26)/($AC$20))*100,HLOOKUP(INDIRECT(ADDRESS(2,COLUMN())),OFFSET($AH$2,0,0,ROW()-1,28),ROW()-1,FALSE)) -> 8.4660436 | AD5: =IF(AND($B$74=1,LEN($AD$23) * LEN($AD$26) * LEN($AD$20)>0),(($AD$23+$AD$26)/($AD$20))*100,HLOOKUP(INDIRECT(ADDRESS(2,COLUMN())),OFFSET($AH$2,0,0,ROW()-1,28),ROW()-1,FALSE)) -> 8.2122219 | AE5: =IF(AND($B$74=1,LEN($AE$23) * LEN($AE$26) * LEN($AE$20)>0),(($AE$23+$AE$26)/($AE$20))*100,HLOOKUP(INDIRECT(ADDRESS(2,COLUMN())),OFFSET($AH$2,0,0,ROW()-1,28),ROW()-1,FALSE)) -> 8.2138024 | AF5: =IF(AND($B$74=1,LEN($AF$23) * LEN($AF$26) * LEN($AF$20)>0),(($AF$23+$AF$26)/($AF$20))*100,HLOOKUP(INDIRECT(ADDRESS(2,COLUMN())),OFFSET($AH$2,0,0,ROW()-1,28),ROW()-1,FALSE)) -> 7.923056 | AG5: =IF(AND($B$74=1,LEN($AG$23) * LEN($AG$26) * LEN($AG$20)>0),(($AG$23+$AG$26)/($AG$20))*100,HLOOKUP(INDIRECT(ADDRESS(2,COLUMN())),OFFSET($AH$2,0,0,ROW()-1,28),ROW()-1,FALSE)) -> 8.1925826 | AH5: =29.70134988 -> 29.70135 | AI5: =28.76225387 -> 28.762254 | AJ5: =27.24881016 -> 27.24881 | AK5: =26.12874808 -> 26.128748 | AL5: =25.46951911 -> 25.469519 | AM5: =24.50787946 -> 24.507879 | AN5: =23.27532647 -> 23.275326 | AO5: =20.98580002 -> 20.9858 | AP5: =19.08984883 -> 19.089849 | AQ5: =18.51678224 -> 18.516782 | AR5: =18.19220858 -> 18.192209 | AS5: =17.96908019 -> 17.96908 | AT5: =16.41501112 -> 16.415011 | AU5: =16.04975513 -> 16.049755 | AV5: =15.25909257 -> 15.259093 | AW5: =14.18884479 -> 14.188845 | AX5: =13.82442784 -> 13.824428 | AY5: =13.18026318 -> 13.180263 | AZ5: =12.21694181 -> 12.216942 | BA5: =11.58322002 -> 11.58322 | BB5: =10.62274807 -> 10.622748 | BC5: =9.69191048 -> 9.6919105 | BD5: =9.25350893 -> 9.2535089 | BE5: =8.466043602 -> 8.4660436 | BF5: =8.21222189 -> 8.2122219 | BG5: =8.213802353 -> 8.2138024 | BH5: =7.923055989 -> 7.923056 | BI5: =8.192582625 -> 8.1925826
A6: ="ETFs & Mutual Funds Passive %" -> ETFs & Mutual Funds Passive % | B6: ="" | E6: ="Heading" -> Heading | AH6: ="" | AI6: ="" | AJ6: ="" | AK6: ="" | AL6: ="" | AM6: ="" | AN6: ="" | AO6: ="" | ... BI6: =""
A7: =" Passive % Of All ETFs & Mutual Funds" -> Passive % Of All ETFs & Mutual Funds | B7: ="" | E7: ="Expression" -> Expression | F7: =IF(AND($B$74=1,LEN($F$14) * LEN($F$13)>0),($F$14/$F$13)*100,HLOOKUP(INDIRECT(ADDRESS(2,COLUMN())),OFFSET($AH$2,0,0,ROW()-1,28),ROW()-1,FALSE)) -> 54.081124 | G7: =IF(AND($B$74=1,LEN($G$14) * LEN($G$13)>0),($G$14/$G$13)*100,HLOOKUP(INDIRECT(ADDRESS(2,COLUMN())),OFFSET($AH$2,0,0,ROW()-1,28),ROW()-1,FALSE)) -> 53.441266 | H7: =IF(AND($B$74=1,LEN($H$14) * LEN($H$13)>0),($H$14/$H$13)*100,HLOOKUP(INDIRECT(ADDRESS(2,COLUMN())),OFFSET($AH$2,0,0,ROW()-1,28),ROW()-1,FALSE)) -> 52.638601 | I7: =IF(AND($B$74=1,LEN($I$14) * LEN($I$13)>0),($I$14/$I$13)*100,HLOOKUP(INDIRECT(ADDRESS(2,COLUMN())),OFFSET($AH$2,0,0,ROW()-1,28),ROW()-1,FALSE)) -> 51.126709 | J7: =IF(AND($B$74=1,LEN($J$14) * LEN($J$13)>0),($J$14/$J$13)*100,HLOOKUP(INDIRECT(ADDRESS(2,COLUMN())),OFFSET($AH$2,0,0,ROW()-1,28),ROW()-1,FALSE)) -> 50.136733 | K7: =IF(AND($B$74=1,LEN($K$14) * LEN($K$13)>0),($K$14/$K$13)*100,HLOOKUP(INDIRECT(ADDRESS(2,COLUMN())),OFFSET($AH$2,0,0,ROW()-1,28),ROW()-1,FALSE)) -> 48.953407 | L7: =IF(AND($B$74=1,LEN($L$14) * LEN($L$13)>0),($L$14/$L$13)*100,HLOOKUP(INDIRECT(ADDRESS(2,COLUMN())),OFFSET($AH$2,0,0,ROW()-1,28),ROW()-1,FALSE)) -> 47.964704 | M7: =IF(AND($B$74=1,LEN($M$14) * LEN($M$13)>0),($M$14/$M$13)*100,HLOOKUP(INDIRECT(ADDRESS(2,COLUMN())),OFFSET($AH$2,0,0,ROW()-1,28),ROW()-1,FALSE)) -> 46.40419 | N7: =IF(AND($B$74=1,LEN($N$14) * LEN($N$13)>0),($N$14/$N$13)*100,HLOOKUP(INDIRECT(ADDRESS(2,COLUMN())),OFFSET($AH$2,0,0,ROW()-1,28),ROW()-1,FALSE)) -> 45.328458 | O7: =IF(AND($B$74=1,LEN($O$14) * LEN($O$13)>0),($O$14/$O$13)*100,HLOOKUP(INDIRECT(ADDRESS(2,COLUMN())),OFFSET($AH$2,0,0,ROW()-1,28),ROW()-1,FALSE)) -> 43.878492 | P7: =IF(AND($B$74=1,LEN($P$14) * LEN($P$13)>0),($P$14/$P$13)*100,HLOOKUP(INDIRECT(ADDRESS(2,COLUMN())),OFFSET($AH$2,0,0,ROW()-1,28),ROW()-1,FALSE)) -> 42.791783 | Q7: =IF(AND($B$74=1,LEN($Q$14) * LEN($Q$13)>0),($Q$14/$Q$13)*100,HLOOKUP(INDIRECT(ADDRESS(2,COLUMN())),OFFSET($AH$2,0,0,ROW()-1,28),ROW()-1,FALSE)) -> 41.780188 | R7: =IF(AND($B$74=1,LEN($R$14) * LEN($R$13)>0),($R$14/$R$13)*100,HLOOKUP(INDIRECT(ADDRESS(2,COLUMN())),OFFSET($AH$2,0,0,ROW()-1,28),ROW()-1,FALSE)) -> 41.605093 | S7: =IF(AND($B$74=1,LEN($S$14) * LEN($S$13)>0),($S$14/$S$13)*100,HLOOKUP(INDIRECT(ADDRESS(2,COLUMN())),OFFSET($AH$2,0,0,ROW()-1,28),ROW()-1,FALSE)) -> 41.186121 | T7: =IF(AND($B$74=1,LEN($T$14) * LEN($T$13)>0),($T$14/$T$13)*100,HLOOKUP(INDIRECT(ADDRESS(2,COLUMN())),OFFSET($AH$2,0,0,ROW()-1,28),ROW()-1,FALSE)) -> 39.842111 | U7: =IF(AND($B$74=1,LEN($U$14) * LEN($U$13)>0),($U$14/$U$13)*100,HLOOKUP(INDIRECT(ADDRESS(2,COLUMN())),OFFSET($AH$2,0,0,ROW()-1,28),ROW()-1,FALSE)) -> 38.2237 | V7: =IF(AND($B$74=1,LEN($V$14) * LEN($V$13)>0),($V$14/$V$13)*100,HLOOKUP(INDIRECT(ADDRESS(2,COLUMN())),OFFSET($AH$2,0,0,ROW()-1,28),ROW()-1,FALSE)) -> 37.751042 | W7: =IF(AND($B$74=1,LEN($W$14) * LEN($W$13)>0),($W$14/$W$13)*100,HLOOKUP(INDIRECT(ADDRESS(2,COLUMN())),OFFSET($AH$2,0,0,ROW()-1,28),ROW()-1,FALSE)) -> 36.026475 | X7: =IF(AND($B$74=1,LEN($X$14) * LEN($X$13)>0),($X$14/$X$13)*100,HLOOKUP(INDIRECT(ADDRESS(2,COLUMN())),OFFSET($AH$2,0,0,ROW()-1,28),ROW()-1,FALSE)) -> 34.352407 | Y7: =IF(AND($B$74=1,LEN($Y$14) * LEN($Y$13)>0),($Y$14/$Y$13)*100,HLOOKUP(INDIRECT(ADDRESS(2,COLUMN())),OFFSET($AH$2,0,0,ROW()-1,28),ROW()-1,FALSE)) -> 32.505148 | Z7: =IF(AND($B$74=1,LEN($Z$14) * LEN($Z$13)>0),($Z$14/$Z$13)*100,HLOOKUP(INDIRECT(ADDRESS(2,COLUMN())),OFFSET($AH$2,0,0,ROW()-1,28),ROW()-1,FALSE)) -> 31.409682 | AA7: =IF(AND($B$74=1,LEN($AA$14) * LEN($AA$13)>0),($AA$14/$AA$13)*100,HLOOKUP(INDIRECT(ADDRESS(2,COLUMN())),OFFSET($AH$2,0,0,ROW()-1,28),ROW()-1,FALSE)) -> 30.417419 | AB7: =IF(AND($B$74=1,LEN($AB$14) * LEN($AB$13)>0),($AB$14/$AB$13)*100,HLOOKUP(INDIRECT(ADDRESS(2,COLUMN())),OFFSET($AH$2,0,0,ROW()-1,28),ROW()-1,FALSE)) -> 29.426864 | AC7: =IF(AND($B$74=1,LEN($AC$14) * LEN($AC$13)>0),($AC$14/$AC$13)*100,HLOOKUP(INDIRECT(ADDRESS(2,COLUMN())),OFFSET($AH$2,0,0,ROW()-1,28),ROW()-1,FALSE)) -> 27.712089 | AD7: =IF(AND($B$74=1,LEN($AD$14) * LEN($AD$13)>0),($AD$14/$AD$13)*100,HLOOKUP(INDIRECT(ADDRESS(2,COLUMN())),OFFSET($AH$2,0,0,ROW()-1,28),ROW()-1,FALSE)) -> 27.224338 | AE7: =IF(AND($B$74=1,LEN($AE$14) * LEN($AE$13)>0),($AE$14/$AE$13)*100,HLOOKUP(INDIRECT(ADDRESS(2,COLUMN())),OFFSET($AH$2,0,0,ROW()-1,28),ROW()-1,FALSE)) -> 26.094993 | AF7: =IF(AND($B$74=1,LEN($AF$14) * LEN($AF$13)>0),($AF$14/$AF$13)*100,HLOOKUP(INDIRECT(ADDRESS(2,COLUMN())),OFFSET($AH$2,0,0,ROW()-1,28),ROW()-1,FALSE)) -> 25.482054 | AG7: =IF(AND($B$74=1,LEN($AG$14) * LEN($AG$13)>0),($AG$14/$AG$13)*100,HLOOKUP(INDIRECT(ADDRESS(2,COLUMN())),OFFSET($AH$2,0,0,ROW()-1,28),ROW()-1,FALSE)) -> 25.019725 | AH7: =54.08112368 -> 54.081124 | AI7: =53.44126578 -> 53.441266 | AJ7: =52.63860094 -> 52.638601 | AK7: =51.12670879 -> 51.126709 | AL7: =50.13673274 -> 50.136733 | AM7: =48.95340685 -> 48.953407 | AN7: =47.96470417 -> 47.964704 | AO7: =46.40419023 -> 46.40419 | AP7: =45.32845763 -> 45.328458 | AQ7: =43.8784915 -> 43.878492 | AR7: =42.79178254 -> 42.791783 | AS7: =41.78018805 -> 41.780188 | AT7: =41.60509299 -> 41.605093 | AU7: =41.18612122 -> 41.186121 | AV7: =39.84211065 -> 39.842111 | AW7: =38.22369973 -> 38.2237 | AX7: =37.75104208 -> 37.751042 | AY7: =36.02647484 -> 36.026475 | AZ7: =34.35240699 -> 34.352407 | BA7: =32.50514821 -> 32.505148 | BB7: =31.40968176 -> 31.409682 | BC7: =30.41741885 -> 30.417419 | BD7: =29.42686392 -> 29.426864 | BE7: =27.71208904 -> 27.712089 | BF7: =27.2243384 -> 27.224338 | BG7: =26.09499259 -> 26.094993 | BH7: =25.48205366 -> 25.482054 | BI7: =25.01972542 -> 25.019725
A8: =" Passive % Of All Fixed Income Funds" -> Passive % Of All Fixed Income Funds | B8: ="" | E8: ="Expression" -> Expression | F8: =IF(AND($B$74=1,LEN($F$21) * LEN($F$20)>0),($F$21/$F$20)*100,HLOOKUP(INDIRECT(ADDRESS(2,COLUMN())),OFFSET($AH$2,0,0,ROW()-1,28),ROW()-1,FALSE)) -> 38.508901 | G8: =IF(AND($B$74=1,LEN($G$21) * LEN($G$20)>0),($G$21/$G$20)*100,HLOOKUP(INDIRECT(ADDRESS(2,COLUMN())),OFFSET($AH$2,0,0,ROW()-1,28),ROW()-1,FALSE)) -> 38.189375 | H8: =IF(AND($B$74=1,LEN($H$21) * LEN($H$20)>0),($H$21/$H$20)*100,HLOOKUP(INDIRECT(ADDRESS(2,COLUMN())),OFFSET($AH$2,0,0,ROW()-1,28),ROW()-1,FALSE)) -> 37.551428 | I8: =IF(AND($B$74=1,LEN($I$21) * LEN($I$20)>0),($I$21/$I$20)*100,HLOOKUP(INDIRECT(ADDRESS(2,COLUMN())),OFFSET($AH$2,0,0,ROW()-1,28),ROW()-1,FALSE)) -> 37.440026 | J8: =IF(AND($B$74=1,LEN($J$21) * LEN($J$20)>0),($J$21/$J$20)*100,HLOOKUP(INDIRECT(ADDRESS(2,COLUMN())),OFFSET($AH$2,0,0,ROW()-1,28),ROW()-1,FALSE)) -> 37.408446 | K8: =IF(AND($B$74=1,LEN($K$21) * LEN($K$20)>0),($K$21/$K$20)*100,HLOOKUP(INDIRECT(ADDRESS(2,COLUMN())),OFFSET($AH$2,0,0,ROW()-1,28),ROW()-1,FALSE)) -> 36.457365 | L8: =IF(AND($B$74=1,LEN($L$21) * LEN($L$20)>0),($L$21/$L$20)*100,HLOOKUP(INDIRECT(ADDRESS(2,COLUMN())),OFFSET($AH$2,0,0,ROW()-1,28),ROW()-1,FALSE)) -> 36.325285 | M8: =IF(AND($B$74=1,LEN($M$21) * LEN($M$20)>0),($M$21/$M$20)*100,HLOOKUP(INDIRECT(ADDRESS(2,COLUMN())),OFFSET($AH$2,0,0,ROW()-1,28),ROW()-1,FALSE)) -> 34.004146 | N8: =IF(AND($B$74=1,LEN($N$21) * LEN($N$20)>0),($N$21/$N$20)*100,HLOOKUP(INDIRECT(ADDRESS(2,COLUMN())),OFFSET($AH$2,0,0,ROW()-1,28),ROW()-1,FALSE)) -> 31.896073 | O8: =IF(AND($B$74=1,LEN($O$21) * LEN($O$20)>0),($O$21/$O$20)*100,HLOOKUP(INDIRECT(ADDRESS(2,COLUMN())),OFFSET($AH$2,0,0,ROW()-1,28),ROW()-1,FALSE)) -> 31.377922 | P8: =IF(AND($B$74=1,LEN($P$21) * LEN($P$20)>0),($P$21/$P$20)*100,HLOOKUP(INDIRECT(ADDRESS(2,COLUMN())),OFFSET($AH$2,0,0,ROW()-1,28),ROW()-1,FALSE)) -> 31.159512 | Q8: =IF(AND($B$74=1,LEN($Q$21) * LEN($Q$20)>0),($Q$21/$Q$20)*100,HLOOKUP(INDIRECT(ADDRESS(2,COLUMN())),OFFSET($AH$2,0,0,ROW()-1,28),ROW()-1,FALSE)) -> 31.117414 | R8: =IF(AND($B$74=1,LEN($R$21) * LEN($R$20)>0),($R$21/$R$20)*100,HLOOKUP(INDIRECT(ADDRESS(2,COLUMN())),OFFSET($AH$2,0,0,ROW()-1,28),ROW()-1,FALSE)) -> 29.576187 | S8: =IF(AND($B$74=1,LEN($S$21) * LEN($S$20)>0),($S$21/$S$20)*100,HLOOKUP(INDIRECT(ADDRESS(2,COLUMN())),OFFSET($AH$2,0,0,ROW()-1,28),ROW()-1,FALSE)) -> 29.469729 | T8: =IF(AND($B$74=1,LEN($T$21) * LEN($T$20)>0),($T$21/$T$20)*100,HLOOKUP(INDIRECT(ADDRESS(2,COLUMN())),OFFSET($AH$2,0,0,ROW()-1,28),ROW()-1,FALSE)) -> 28.077709 | U8: =IF(AND($B$74=1,LEN($U$21) * LEN($U$20)>0),($U$21/$U$20)*100,HLOOKUP(INDIRECT(ADDRESS(2,COLUMN())),OFFSET($AH$2,0,0,ROW()-1,28),ROW()-1,FALSE)) -> 26.764075 | V8: =IF(AND($B$74=1,LEN($V$21) * LEN($V$20)>0),($V$21/$V$20)*100,HLOOKUP(INDIRECT(ADDRESS(2,COLUMN())),OFFSET($AH$2,0,0,ROW()-1,28),ROW()-1,FALSE)) -> 26.11505 | W8: =IF(AND($B$74=1,LEN($W$21) * LEN($W$20)>0),($W$21/$W$20)*100,HLOOKUP(INDIRECT(ADDRESS(2,COLUMN())),OFFSET($AH$2,0,0,ROW()-1,28),ROW()-1,FALSE)) -> 24.783601 | X8: =IF(AND($B$74=1,LEN($X$21) * LEN($X$20)>0),($X$21/$X$20)*100,HLOOKUP(INDIRECT(ADDRESS(2,COLUMN())),OFFSET($AH$2,0,0,ROW()-1,28),ROW()-1,FALSE)) -> 23.272017 | Y8: =IF(AND($B$74=1,LEN($Y$21) * LEN($Y$20)>0),($Y$21/$Y$20)*100,HLOOKUP(INDIRECT(ADDRESS(2,COLUMN())),OFFSET($AH$2,0,0,ROW()-1,28),ROW()-1,FALSE)) -> 22.318445 | Z8: =IF(AND($B$74=1,LEN($Z$21) * LEN($Z$20)>0),($Z$21/$Z$20)*100,HLOOKUP(INDIRECT(ADDRESS(2,COLUMN())),OFFSET($AH$2,0,0,ROW()-1,28),ROW()-1,FALSE)) -> 20.954989 | AA8: =IF(AND($B$74=1,LEN($AA$21) * LEN($AA$20)>0),($AA$21/$AA$20)*100,HLOOKUP(INDIRECT(ADDRESS(2,COLUMN())),OFFSET($AH$2,0,0,ROW()-1,28),ROW()-1,FALSE)) -> 19.511031 | AB8: =IF(AND($B$74=1,LEN($AB$21) * LEN($AB$20)>0),($AB$21/$AB$20)*100,HLOOKUP(INDIRECT(ADDRESS(2,COLUMN())),OFFSET($AH$2,0,0,ROW()-1,28),ROW()-1,FALSE)) -> 18.517265 | AC8: =IF(AND($B$74=1,LEN($AC$21) * LEN($AC$20)>0),($AC$21/$AC$20)*100,HLOOKUP(INDIRECT(ADDRESS(2,COLUMN())),OFFSET($AH$2,0,0,ROW()-1,28),ROW()-1,FALSE)) -> 16.767667 | AD8: =IF(AND($B$74=1,LEN($AD$21) * LEN($AD$20)>0),($AD$21/$AD$20)*100,HLOOKUP(INDIRECT(ADDRESS(2,COLUMN())),OFFSET($AH$2,0,0,ROW()-1,28),ROW()-1,FALSE)) -> 16.241755 | AE8: =IF(AND($B$74=1,LEN($AE$21) * LEN($AE$20)>0),($AE$21/$AE$20)*100,HLOOKUP(INDIRECT(ADDRESS(2,COLUMN())),OFFSET($AH$2,0,0,ROW()-1,28),ROW()-1,FALSE)) -> 15.865767 | AF8: =IF(AND($B$74=1,LEN($AF$21) * LEN($AF$20)>0),($AF$21/$AF$20)*100,HLOOKUP(INDIRECT(ADDRESS(2,COLUMN())),OFFSET($AH$2,0,0,ROW()-1,28),ROW()-1,FALSE)) -> 15.511313 | AG8: =IF(AND($B$74=1,LEN($AG$21) * LEN($AG$20)>0),($AG$21/$AG$20)*100,HLOOKUP(INDIRECT(ADDRESS(2,COLUMN())),OFFSET($AH$2,0,0,ROW()-1,28),ROW()-1,FALSE)) -> 15.79825 | AH8: =38.50890068 -> 38.508901 | AI8: =38.18937548 -> 38.189375 | AJ8: =37.55142781 -> 37.551428 | AK8: =37.44002593 -> 37.440026 | AL8: =37.40844573 -> 37.408446 | AM8: =36.45736473 -> 36.457365 | AN8: =36.32528521 -> 36.325285 | AO8: =34.00414553 -> 34.004146 | AP8: =31.89607302 -> 31.896073 | AQ8: =31.37792198 -> 31.377922 | AR8: =31.15951209 -> 31.159512 | AS8: =31.11741371 -> 31.117414 | AT8: =29.57618713 -> 29.576187 | AU8: =29.46972895 -> 29.469729 | AV8: =28.07770923 -> 28.077709 | AW8: =26.76407467 -> 26.764075 | AX8: =26.11504972 -> 26.11505 | AY8: =24.7836012 -> 24.783601 | AZ8: =23.27201667 -> 23.272017 | BA8: =22.31844531 -> 22.318445 | BB8: =20.95498892 -> 20.954989 | BC8: =19.51103062 -> 19.511031 | BD8: =18.51726467 -> 18.517265 | BE8: =16.76766668 -> 16.767667 | BF8: =16.24175533 -> 16.241755 | BG8: =15.86576705 -> 15.865767 | BH8: =15.51131314 -> 15.511313 | BI8: =15.79825001 -> 15.79825
A9: =" Passive % Of All Equity Funds" -> Passive % Of All Equity Funds | B9: ="" | E9: ="Expression" -> Expression | F9: =IF(AND($B$74=1,LEN($F$28) * LEN($F$27)>0),($F$28/$F$27)*100,HLOOKUP(INDIRECT(ADDRESS(2,COLUMN())),OFFSET($AH$2,0,0,ROW()-1,28),ROW()-1,FALSE)) -> 61.171637 | G9: =IF(AND($B$74=1,LEN($G$28) * LEN($G$27)>0),($G$28/$G$27)*100,HLOOKUP(INDIRECT(ADDRESS(2,COLUMN())),OFFSET($AH$2,0,0,ROW()-1,28),ROW()-1,FALSE)) -> 60.580739 | H9: =IF(AND($B$74=1,LEN($H$28) * LEN($H$27)>0),($H$28/$H$27)*100,HLOOKUP(INDIRECT(ADDRESS(2,COLUMN())),OFFSET($AH$2,0,0,ROW()-1,28),ROW()-1,FALSE)) -> 59.983843 | I9: =IF(AND($B$74=1,LEN($I$28) * LEN($I$27)>0),($I$28/$I$27)*100,HLOOKUP(INDIRECT(ADDRESS(2,COLUMN())),OFFSET($AH$2,0,0,ROW()-1,28),ROW()-1,FALSE)) -> 58.220891 | J9: =IF(AND($B$74=1,LEN($J$28) * LEN($J$27)>0),($J$28/$J$27)*100,HLOOKUP(INDIRECT(ADDRESS(2,COLUMN())),OFFSET($AH$2,0,0,ROW()-1,28),ROW()-1,FALSE)) -> 57.433797 | K9: =IF(AND($B$74=1,LEN($K$28) * LEN($K$27)>0),($K$28/$K$27)*100,HLOOKUP(INDIRECT(ADDRESS(2,COLUMN())),OFFSET($AH$2,0,0,ROW()-1,28),ROW()-1,FALSE)) -> 56.394548 | L9: =IF(AND($B$74=1,LEN($L$28) * LEN($L$27)>0),($L$28/$L$27)*100,HLOOKUP(INDIRECT(ADDRESS(2,COLUMN())),OFFSET($AH$2,0,0,ROW()-1,28),ROW()-1,FALSE)) -> 55.749346 | M9: =IF(AND($B$74=1,LEN($M$28) * LEN($M$27)>0),($M$28/$M$27)*100,HLOOKUP(INDIRECT(ADDRESS(2,COLUMN())),OFFSET($AH$2,0,0,ROW()-1,28),ROW()-1,FALSE)) -> 54.656961 | N9: =IF(AND($B$74=1,LEN($N$28) * LEN($N$27)>0),($N$28/$N$27)*100,HLOOKUP(INDIRECT(ADDRESS(2,COLUMN())),OFFSET($AH$2,0,0,ROW()-1,28),ROW()-1,FALSE)) -> 53.073346 | O9: =IF(AND($B$74=1,LEN($O$28) * LEN($O$27)>0),($O$28/$O$27)*100,HLOOKUP(INDIRECT(ADDRESS(2,COLUMN())),OFFSET($AH$2,0,0,ROW()-1,28),ROW()-1,FALSE)) -> 51.397546 | P9: =IF(AND($B$74=1,LEN($P$28) * LEN($P$27)>0),($P$28/$P$27)*100,HLOOKUP(INDIRECT(ADDRESS(2,COLUMN())),OFFSET($AH$2,0,0,ROW()-1,28),ROW()-1,FALSE)) -> 50.207717 | Q9: =IF(AND($B$74=1,LEN($Q$28) * LEN($Q$27)>0),($Q$28/$Q$27)*100,HLOOKUP(INDIRECT(ADDRESS(2,COLUMN())),OFFSET($AH$2,0,0,ROW()-1,28),ROW()-1,FALSE)) -> 49.461105 | R9: =IF(AND($B$74=1,LEN($R$28) * LEN($R$27)>0),($R$28/$R$27)*100,HLOOKUP(INDIRECT(ADDRESS(2,COLUMN())),OFFSET($AH$2,0,0,ROW()-1,28),ROW()-1,FALSE)) -> 49.626281 | S9: =IF(AND($B$74=1,LEN($S$28) * LEN($S$27)>0),($S$28/$S$27)*100,HLOOKUP(INDIRECT(ADDRESS(2,COLUMN())),OFFSET($AH$2,0,0,ROW()-1,28),ROW()-1,FALSE)) -> 49.255014 | T9: =IF(AND($B$74=1,LEN($T$28) * LEN($T$27)>0),($T$28/$T$27)*100,HLOOKUP(INDIRECT(ADDRESS(2,COLUMN())),OFFSET($AH$2,0,0,ROW()-1,28),ROW()-1,FALSE)) -> 48.345162 | U9: =IF(AND($B$74=1,LEN($U$28) * LEN($U$27)>0),($U$28/$U$27)*100,HLOOKUP(INDIRECT(ADDRESS(2,COLUMN())),OFFSET($AH$2,0,0,ROW()-1,28),ROW()-1,FALSE)) -> 45.835681 | V9: =IF(AND($B$74=1,LEN($V$28) * LEN($V$27)>0),($V$28/$V$27)*100,HLOOKUP(INDIRECT(ADDRESS(2,COLUMN())),OFFSET($AH$2,0,0,ROW()-1,28),ROW()-1,FALSE)) -> 45.449154 | W9: =IF(AND($B$74=1,LEN($W$28) * LEN($W$27)>0),($W$28/$W$27)*100,HLOOKUP(INDIRECT(ADDRESS(2,COLUMN())),OFFSET($AH$2,0,0,ROW()-1,28),ROW()-1,FALSE)) -> 43.8448 | X9: =IF(AND($B$74=1,LEN($X$28) * LEN($X$27)>0),($X$28/$X$27)*100,HLOOKUP(INDIRECT(ADDRESS(2,COLUMN())),OFFSET($AH$2,0,0,ROW()-1,28),ROW()-1,FALSE)) -> 42.348753 | Y9: =IF(AND($B$74=1,LEN($Y$28) * LEN($Y$27)>0),($Y$28/$Y$27)*100,HLOOKUP(INDIRECT(ADDRESS(2,COLUMN())),OFFSET($AH$2,0,0,ROW()-1,28),ROW()-1,FALSE)) -> 40.179994 | Z9: =IF(AND($B$74=1,LEN($Z$28) * LEN($Z$27)>0),($Z$28/$Z$27)*100,HLOOKUP(INDIRECT(ADDRESS(2,COLUMN())),OFFSET($AH$2,0,0,ROW()-1,28),ROW()-1,FALSE)) -> 39.017128 | AA9: =IF(AND($B$74=1,LEN($AA$28) * LEN($AA$27)>0),($AA$28/$AA$27)*100,HLOOKUP(INDIRECT(ADDRESS(2,COLUMN())),OFFSET($AH$2,0,0,ROW()-1,28),ROW()-1,FALSE)) -> 37.733408 | AB9: =IF(AND($B$74=1,LEN($AB$28) * LEN($AB$27)>0),($AB$28/$AB$27)*100,HLOOKUP(INDIRECT(ADDRESS(2,COLUMN())),OFFSET($AH$2,0,0,ROW()-1,28),ROW()-1,FALSE)) -> 36.808456 | AC9: =IF(AND($B$74=1,LEN($AC$28) * LEN($AC$27)>0),($AC$28/$AC$27)*100,HLOOKUP(INDIRECT(ADDRESS(2,COLUMN())),OFFSET($AH$2,0,0,ROW()-1,28),ROW()-1,FALSE)) -> 34.973911 | AD9: =IF(AND($B$74=1,LEN($AD$28) * LEN($AD$27)>0),($AD$28/$AD$27)*100,HLOOKUP(INDIRECT(ADDRESS(2,COLUMN())),OFFSET($AH$2,0,0,ROW()-1,28),ROW()-1,FALSE)) -> 34.371796 | AE9: =IF(AND($B$74=1,LEN($AE$28) * LEN($AE$27)>0),($AE$28/$AE$27)*100,HLOOKUP(INDIRECT(ADDRESS(2,COLUMN())),OFFSET($AH$2,0,0,ROW()-1,28),ROW()-1,FALSE)) -> 33.706485 | AF9: =IF(AND($B$74=1,LEN($AF$28) * LEN($AF$27)>0),($AF$28/$AF$27)*100,HLOOKUP(INDIRECT(ADDRESS(2,COLUMN())),OFFSET($AH$2,0,0,ROW()-1,28),ROW()-1,FALSE)) -> 33.024504 | AG9: =IF(AND($B$74=1,LEN($AG$28) * LEN($AG$27)>0),($AG$28/$AG$27)*100,HLOOKUP(INDIRECT(ADDRESS(2,COLUMN())),OFFSET($AH$2,0,0,ROW()-1,28),ROW()-1,FALSE)) -> 32.260807 | AH9: =61.17163678 -> 61.171637 | AI9: =60.58073897 -> 60.580739 | AJ9: =59.9838431 -> 59.983843 | AK9: =58.22089075 -> 58.220891 | AL9: =57.43379694 -> 57.433797 | AM9: =56.39454791 -> 56.394548 | AN9: =55.74934614 -> 55.749346 | AO9: =54.65696074 -> 54.656961 | AP9: =53.07334575 -> 53.073346 | AQ9: =51.39754579 -> 51.397546 | AR9: =50.20771713 -> 50.207717 | AS9: =49.46110484 -> 49.461105 | AT9: =49.62628065 -> 49.626281 | AU9: =49.25501428 -> 49.255014 | AV9: =48.34516173 -> 48.345162 | AW9: =45.8356807 -> 45.835681 | AX9: =45.44915359 -> 45.449154 | AY9: =43.84480012 -> 43.8448 | AZ9: =42.34875293 -> 42.348753 | BA9: =40.17999354 -> 40.179994 | BB9: =39.01712804 -> 39.017128 | BC9: =37.73340793 -> 37.733408 | BD9: =36.8084565 -> 36.808456 | BE9: =34.97391096 -> 34.973911 | BF9: =34.37179591 -> 34.371796 | BG9: =33.7064849 -> 33.706485 | BH9: =33.0245041 -> 33.024504 | BI9: =32.26080741 -> 32.260807
